Workbook
Name UPDATE: 'Data Sheet'!$E$1

Sheet FINANCIALS
B2: ="HISTORICAL FINANCIAL STATEMENT - "&'Data Sheet'!B1 -> HISTORICAL FINANCIAL STATEMENT - HINDUSTAN UNILEVER LTD
B3: YEARS | C3: ='Data Sheet'!B16 -> 42825 | D3: ='Data Sheet'!C16 -> 43190 | E3: ='Data Sheet'!D16 -> 43555 | F3: ='Data Sheet'!E16 -> 43921 | G3: ='Data Sheet'!F16 -> 44286 | H3: ='Data Sheet'!G16 -> 44651 | I3: ='Data Sheet'!H16 -> 45016 | J3: ='Data Sheet'!I16 -> 45382 | ... L3: ='Data Sheet'!K16 -> 46112 | M3: LTM
A4: # | B4: INCOME STATEMENT (IN CRORES)
B5: SALES | C5: =IFERROR('Data Sheet'!B17,0) -> 33162 | D5: =IFERROR('Data Sheet'!C17,0) -> 35545 | E5: =IFERROR('Data Sheet'!D17,0) -> 39310 | F5: =IFERROR('Data Sheet'!E17,0) -> 39783 | G5: =IFERROR('Data Sheet'!F17,0) -> 47028 | H5: =IFERROR('Data Sheet'!G17,0) -> 52446 | I5: =IFERROR('Data Sheet'!H17,0) -> 60580 | J5: =IFERROR('Data Sheet'!I17,0) -> 61896 | ... L5: =IFERROR('Data Sheet'!K17,0) -> 64468 | M5: =IFERROR(SUM('Data Sheet'!H42:K42),0) -> 65225
B6: SALES GROWTH | C6: - | D6: =D5/C5-1 -> 0.071859357 | E6: =E5/D5-1 -> 0.10592207 | F6: =F5/E5-1 -> 0.012032562 | G6: =G5/F5-1 -> 0.18211296 | H6: =H5/G5-1 -> 0.11520796 | I6: =I5/H5-1 -> 0.15509286 | J6: =J5/I5-1 -> 0.021723341 | K6: =K5/J5-1 -> -0.0091766835 | ... M6: =M5/L5-1 -> 0.01174226
B8: COGS | C8: =IFERROR(SUM('Data Sheet'!B18,'Data Sheet'!B20,'Data Sheet'!B21,'Data Sheet'!B22-1*'Data Sheet'!B19),0) -> 18675 | D8: =IFERROR(SUM('Data Sheet'!C18,'Data Sheet'!C20,'Data Sheet'!C21,'Data Sheet'!C22-1*'Data Sheet'!C19),0) -> 19314 | E8: =IFERROR(SUM('Data Sheet'!D18,'Data Sheet'!D20,'Data Sheet'!D21,'Data Sheet'!D22-1*'Data Sheet'!D19),0) -> 21081 | F8: =IFERROR(SUM('Data Sheet'!E18,'Data Sheet'!E20,'Data Sheet'!E21,'Data Sheet'!E22-1*'Data Sheet'!E19),0) -> 20614 | G8: =IFERROR(SUM('Data Sheet'!F18,'Data Sheet'!F20,'Data Sheet'!F21,'Data Sheet'!F22-1*'Data Sheet'!F19),0) -> 25301 | H8: =IFERROR(SUM('Data Sheet'!G18,'Data Sheet'!G20,'Data Sheet'!G21,'Data Sheet'!G22-1*'Data Sheet'!G19),0) -> 29066 | I8: =IFERROR(SUM('Data Sheet'!H18,'Data Sheet'!H20,'Data Sheet'!H21,'Data Sheet'!H22-1*'Data Sheet'!H19),0) -> 35381 | J8: =IFERROR(SUM('Data Sheet'!I18,'Data Sheet'!I20,'Data Sheet'!I21,'Data Sheet'!I22-1*'Data Sheet'!I19),0) -> 33651 | ... L8: =IFERROR(SUM('Data Sheet'!K18,'Data Sheet'!K20,'Data Sheet'!K21,'Data Sheet'!K22-1*'Data Sheet'!K19),0) -> 35634 | M8: =IFERROR(SUM('Data Sheet'!H43:K43),0) -> 50108
B9: COGS % SALES | C9: =C8/C5 -> 0.56314456 | D9: =D8/D5 -> 0.54336756 | E9: =E8/E5 -> 0.53627576 | F9: =F8/F5 -> 0.51816102 | G9: =G8/G5 -> 0.53799864 | H9: =H8/H5 -> 0.55420814 | I9: =I8/I5 -> 0.58403764 | J9: =J8/J5 -> 0.54367003 | ... M9: =M8/M5 -> 0.76823304
B11: GROSS PROFIT | C11: =C5-C8 -> 14487 | D11: =D5-D8 -> 16231 | E11: =E5-E8 -> 18229 | F11: =F5-F8 -> 19169 | G11: =G5-G8 -> 21727 | H11: =H5-H8 -> 23380 | I11: =I5-I8 -> 25199 | J11: =J5-J8 -> 28245 | ... M11: =M5-M8 -> 15117
B12: GROSS PROFIT % SALES | C12: =C11/C5 -> 0.43685544 | D12: =D11/D5 -> 0.45663244 | E12: =E11/E5 -> 0.46372424 | F12: =F11/F5 -> 0.48183898 | G12: =G11/G5 -> 0.46200136 | H12: =H11/H5 -> 0.44579186 | I12: =I11/I5 -> 0.41596236 | J12: =J11/J5 -> 0.45632997 | ... M12: =M11/M5 -> 0.23176696
B14: SELLING &GENERAL EXPENSES | C14: =IFERROR(SUM('Data Sheet'!B23:B24),0) -> 8159 | D14: =IFERROR(SUM('Data Sheet'!C23:C24),0) -> 8732 | E14: =IFERROR(SUM('Data Sheet'!D23:D24),0) -> 9349 | F14: =IFERROR(SUM('Data Sheet'!E23:E24),0) -> 9308 | G14: =IFERROR(SUM('Data Sheet'!F23:F24),0) -> 10101 | H14: =IFERROR(SUM('Data Sheet'!G23:G24),0) -> 10523 | I14: =IFERROR(SUM('Data Sheet'!H23:H24),0) -> 11052 | J14: =IFERROR(SUM('Data Sheet'!I23:I24),0) -> 13586 | ... M14: =IFERROR(SUM('Data Sheet'!L23:L24),0) -> 0
B15: SG EXP % SALES | C15: =C14/C5 -> 0.24603462 | D15: =D14/D5 -> 0.24566043 | E15: =E14/E5 -> 0.23782752 | F15: =F14/F5 -> 0.23396928 | G15: =G14/G5 -> 0.21478694 | H15: =H14/H5 -> 0.20064447 | I15: =I14/I5 -> 0.18243645 | J15: =J14/J5 -> 0.21949722 | ... L15: =L14/L5 -> 0.21398213
B17: EBITDA | C17: =C11-C14 -> 6328 | D17: =D11-D14 -> 7499 | E17: =E11-E14 -> 8880 | F17: =F11-F14 -> 9861 | G17: =G11-G14 -> 11626 | H17: =H11-H14 -> 12857 | I17: =I11-I14 -> 14147 | J17: =J11-J14 -> 14659 | ... M17: =M11-M14 -> 15117
B18: EBITDA % SALES | C18: =C17/C5 -> 0.19082082 | D18: =D17/D5 -> 0.21097201 | E18: =E17/E5 -> 0.22589672 | F18: =F17/F5 -> 0.24786969 | G18: =G17/G5 -> 0.24721443 | H18: =H17/H5 -> 0.24514739 | I18: =I17/I5 -> 0.23352592 | J18: =J17/J5 -> 0.23683275 | ... M18: =M17/M5 -> 0.23176696
B20: INTEREST | C20: =IFERROR('Data Sheet'!B27,0) -> 35 | D20: =IFERROR('Data Sheet'!C27,0) -> 26 | E20: =IFERROR('Data Sheet'!D27,0) -> 33 | F20: =IFERROR('Data Sheet'!E27,0) -> 118 | G20: =IFERROR('Data Sheet'!F27,0) -> 117 | H20: =IFERROR('Data Sheet'!G27,0) -> 106 | I20: =IFERROR('Data Sheet'!H27,0) -> 114 | J20: =IFERROR('Data Sheet'!I27,0) -> 334 | ... L20: =IFERROR('Data Sheet'!K27,0) -> 410 | M20: =IFERROR(SUM('Data Sheet'!H46:K46),0) -> 415
B21: INTEREST % SALES | C21: =C20/C5 -> 0.0010554249 | D21: =D20/D5 -> 0.00073146715 | E21: =E20/E5 -> 0.00083948105 | F21: =F20/F5 -> 0.002966091 | G21: =G20/G5 -> 0.0024878796 | H21: =H20/H5 -> 0.0020211265 | I21: =I20/I5 -> 0.0018818092 | J21: =J20/J5 -> 0.0053961484 | ... M21: =M20/M5 -> 0.006362591
B23: DEPRECIATION | C23: =IFERROR('Data Sheet'!B26,0) -> 432 | D23: =IFERROR('Data Sheet'!C26,0) -> 520 | E23: =IFERROR('Data Sheet'!D26,0) -> 565 | F23: =IFERROR('Data Sheet'!E26,0) -> 1002 | G23: =IFERROR('Data Sheet'!F26,0) -> 1074 | H23: =IFERROR('Data Sheet'!G26,0) -> 1091 | I23: =IFERROR('Data Sheet'!H26,0) -> 1137 | J23: =IFERROR('Data Sheet'!I26,0) -> 1216 | ... L23: =IFERROR('Data Sheet'!K26,0) -> 1333 | M23: =IFERROR(SUM('Data Sheet'!H45:K45),0) -> 1368
B24: DEPRECIATION% SALES | C24: =C23/C8 -> 0.02313253 | D24: =D23/D8 -> 0.026923475 | E24: =E23/E8 -> 0.026801385 | F24: =F23/F8 -> 0.048607742 | G24: =G23/G8 -> 0.042448915 | H24: =H23/H8 -> 0.037535265 | I24: =I23/I8 -> 0.032135892 | J24: =J23/J8 -> 0.036135627 | ... M24: =M23/M8 -> 0.02730103
B26: EARNINGS BEFORE TAX | C26: =IFERROR(C17-SUM(C20,C23),0) -> 5861 | D26: =IFERROR(D17-SUM(D20,D23),0) -> 6953 | E26: =IFERROR(E17-SUM(E20,E23),0) -> 8282 | F26: =IFERROR(F17-SUM(F20,F23),0) -> 8741 | G26: =IFERROR(G17-SUM(G20,G23),0) -> 10435 | H26: =IFERROR(H17-SUM(H20,H23),0) -> 11660 | I26: =IFERROR(I17-SUM(I20,I23),0) -> 12896 | J26: =IFERROR(J17-SUM(J20,J23),0) -> 13109 | ... M26: =IFERROR(M17-SUM(M20,M23),0) -> 13334
B27: EBT % SALES | C27: =C26/C5 -> 0.17673844 | D27: =D26/D5 -> 0.1956112 | E27: =E26/E5 -> 0.2106843 | F27: =F26/F5 -> 0.21971696 | G27: =G26/G5 -> 0.22188909 | H27: =H26/H5 -> 0.22232391 | I27: =I26/I5 -> 0.21287554 | J27: =J26/J5 -> 0.21179075 | ... M27: =M26/M5 -> 0.20443082
B29: TAX | C29: =IFERROR('Data Sheet'!B29,0) -> 1977 | D29: =IFERROR('Data Sheet'!C29,0) -> 2079 | E29: =IFERROR('Data Sheet'!D29,0) -> 2544 | F29: =IFERROR('Data Sheet'!E29,0) -> 2409 | G29: =IFERROR('Data Sheet'!F29,0) -> 2606 | H29: =IFERROR('Data Sheet'!G29,0) -> 2987 | I29: =IFERROR('Data Sheet'!H29,0) -> 3201 | J29: =IFERROR('Data Sheet'!I29,0) -> 3644 | ... L29: =IFERROR('Data Sheet'!K29,0) -> 3160 | M29: =IFERROR(SUM('Data Sheet'!H48:K48),0) -> 3169
B30: EFFECTIVE TAX RATE | C30: =C29/C26 -> 0.33731445 | D30: =D29/D26 -> 0.29900762 | E30: =E29/E26 -> 0.30717218 | F30: =F29/F26 -> 0.27559776 | G30: =G29/G26 -> 0.24973646 | H30: =H29/H26 -> 0.25617496 | I30: =I29/I26 -> 0.2482165 | J30: =J29/J26 -> 0.27797696 | ... M30: =M29/M26 -> 0.23766312
B32: NET PROFIT | C32: =C26-C29 -> 3884 | D32: =D26-D29 -> 4874 | E32: =E26-E29 -> 5738 | F32: =F26-F29 -> 6332 | G32: =G26-G29 -> 7829 | H32: =H26-H29 -> 8673 | I32: =I26-I29 -> 9695 | J32: =J26-J29 -> 9465 | ... M32: =M26-M29 -> 10165
B33: NET PROFIT % SALES | C33: =IFERROR(C32/C5,0) -> 0.11712201 | D33: =IFERROR(D32/D5,0) -> 0.13712196 | E33: =IFERROR(E32/E5,0) -> 0.14596795 | F33: =IFERROR(F32/F5,0) -> 0.15916346 | G33: =IFERROR(G32/G5,0) -> 0.16647529 | H33: =IFERROR(H32/H5,0) -> 0.16537009 | I33: =IFERROR(I32/I5,0) -> 0.16003632 | J33: =IFERROR(J32/J5,0) -> 0.1529178 | ... M33: =IFERROR(M32/M5,0) -> 0.15584515
B35: NO OF EQUITY SHARES | C35: =IFERROR('Data Sheet'!B93,0) -> 216.43 | D35: =IFERROR('Data Sheet'!C93,0) -> 216.45 | E35: =IFERROR('Data Sheet'!D93,0) -> 216.47 | F35: =IFERROR('Data Sheet'!E93,0) -> 216.48 | G35: =IFERROR('Data Sheet'!F93,0) -> 234.96 | H35: =IFERROR('Data Sheet'!G93,0) -> 234.96 | I35: =IFERROR('Data Sheet'!H93,0) -> 234.96 | J35: =IFERROR('Data Sheet'!I93,0) -> 234.96 | ... M35: =IFERROR('Data Sheet'!L93,0) -> 0
B37: EPS | C37: =IFERROR(C32/C35,0) -> 17.945756 | D37: =IFERROR(D32/D35,0) -> 22.517903 | E37: =IFERROR(E32/E35,0) -> 26.507137 | F37: =IFERROR(F32/F35,0) -> 29.249815 | G37: =IFERROR(G32/G35,0) -> 33.320565 | H37: =IFERROR(H32/H35,0) -> 36.912666 | I37: =IFERROR(I32/I35,0) -> 41.262343 | J37: =IFERROR(J32/J35,0) -> 40.283453 | ... M37: =IFERROR(M32/M35,0) -> 0
B38: EPS GROWTH % | D38: =IFERROR(D37/C37-1,0) -> 0.25477591 | E38: =E37/D37-1 -> 0.17715836 | F38: =F37/E37-1 -> 0.10346941 | G38: =G37/F37-1 -> 0.13917182 | H38: =H37/G37-1 -> 0.10780432 | I38: =I37/H37-1 -> 0.11783697 | J38: =J37/I37-1 -> -0.023723569 | K38: =K37/J37-1 -> -0.015742208 | L38: =L37/K37-1 -> 0.08802061 | M38: =M37/L37-1 -> -1
B40: DIVIDEND PER SHARE | C40: =IFERROR('Data Sheet'!B31/FINANCIALS!C35,0) -> 16.966225 | D40: =IFERROR('Data Sheet'!C31/FINANCIALS!D35,0) -> 19.95842 | E40: =IFERROR('Data Sheet'!D31/FINANCIALS!E35,0) -> 21.952234 | F40: =IFERROR('Data Sheet'!E31/FINANCIALS!F35,0) -> 24.944568 | G40: =IFERROR('Data Sheet'!F31/FINANCIALS!G35,0) -> 40.506895 | H40: =IFERROR('Data Sheet'!G31/FINANCIALS!H35,0) -> 34.005788 | I40: =IFERROR('Data Sheet'!H31/FINANCIALS!I35,0) -> 39.006639 | J40: =IFERROR('Data Sheet'!I31/FINANCIALS!J35,0) -> 42.00715 | ... M40: =IFERROR('Data Sheet'!L31/FINANCIALS!M35,0) -> 0
B41: DIVIDEND PAYOUT RATIO | C41: =IFERROR(C40/C37,0) -> 0.9454171 | D41: =IFERROR(D40/D37,0) -> 0.88633566 | E41: =IFERROR(E40/E37,0) -> 0.82816312 | F41: =IFERROR(F40/F37,0) -> 0.85281112 | G41: =IFERROR(G40/G37,0) -> 1.2156725 | H41: =IFERROR(H40/H37,0) -> 0.92124986 | I41: =IFERROR(I40/I37,0) -> 0.94533265 | J41: =IFERROR(J40/J37,0) -> 1.0427892 | ... M41: =IFERROR(M40/M37,0) -> 0
B43: RETAINED EARNINGS | C43: =IFERROR(IF(C37>C40,1-C41,0),0) -> 0.054582904 | D43: =IFERROR(IF(D37>D40,1-D41,0),0) -> 0.11366434 | E43: =IFERROR(IF(E37>E40,1-E41,0),0) -> 0.17183688 | F43: =IFERROR(IF(F37>F40,1-F41,0),0) -> 0.14718888 | G43: =IFERROR(IF(G37>G40,1-G41,0),0) -> 0 | H43: =IFERROR(IF(H37>H40,1-H41,0),0) -> 0.078750144 | I43: =IFERROR(IF(I37>I40,1-I41,0),0) -> 0.054667354 | J43: =IFERROR(IF(J37>J40,1-J41,0),0) -> 0 | ... M43: =IFERROR(IF(M37>M40,1-M41,0),0) -> 0
B48: YEARS | C48: 42825 | D48: 43190 | E48: 43555 | F48: 43921 | G48: 44286 | H48: 44651 | I48: 45016 | J48: 45382 | K48: 45747 | L48: 46112 | M48: LTM
A49: # | B49: BALANCE SHEET
B50: Equity Share Capital | C50: =IFERROR('Data Sheet'!B57,0) -> 216 | D50: =IFERROR('Data Sheet'!C57,0) -> 216 | E50: =IFERROR('Data Sheet'!D57,0) -> 216 | F50: =IFERROR('Data Sheet'!E57,0) -> 216 | G50: =IFERROR('Data Sheet'!F57,0) -> 235 | H50: =IFERROR('Data Sheet'!G57,0) -> 235 | I50: =IFERROR('Data Sheet'!H57,0) -> 235 | J50: =IFERROR('Data Sheet'!I57,0) -> 235 | ... L50: =IFERROR('Data Sheet'!K57,0) -> 235
B51: Reserves | C51: =IFERROR('Data Sheet'!B58,0) -> 6528 | D51: =IFERROR('Data Sheet'!C58,0) -> 7065 | E51: =IFERROR('Data Sheet'!D58,0) -> 7651 | F51: =IFERROR('Data Sheet'!E58,0) -> 8013 | G51: =IFERROR('Data Sheet'!F58,0) -> 47439 | H51: =IFERROR('Data Sheet'!G58,0) -> 48826 | I51: =IFERROR('Data Sheet'!H58,0) -> 50069 | J51: =IFERROR('Data Sheet'!I58,0) -> 50983 | ... L51: =IFERROR('Data Sheet'!K58,0) -> 48504
B52: Borrowings | C52: =IFERROR('Data Sheet'!B59,0) -> 277 | D52: =IFERROR('Data Sheet'!C59,0) -> 0 | E52: =IFERROR('Data Sheet'!D59,0) -> 99 | F52: =IFERROR('Data Sheet'!E59,0) -> 0 | G52: =IFERROR('Data Sheet'!F59,0) -> 0 | H52: =IFERROR('Data Sheet'!G59,0) -> 1043 | I52: =IFERROR('Data Sheet'!H59,0) -> 1219 | J52: =IFERROR('Data Sheet'!I59,0) -> 1484 | ... L52: =IFERROR('Data Sheet'!K59,0) -> 1478
B53: Other Liabilities | C53: =IFERROR('Data Sheet'!B60,0) -> 8685 | D53: =IFERROR('Data Sheet'!C60,0) -> 10581 | E53: =IFERROR('Data Sheet'!D60,0) -> 10663 | F53: =IFERROR('Data Sheet'!E60,0) -> 11924 | G53: =IFERROR('Data Sheet'!F60,0) -> 21066 | H53: =IFERROR('Data Sheet'!G60,0) -> 20402 | I53: =IFERROR('Data Sheet'!H60,0) -> 21554 | J53: =IFERROR('Data Sheet'!I60,0) -> 25787 | ... L53: =IFERROR('Data Sheet'!K60,0) -> 29521
B54: Total LIABILITY | C54: =IFERROR('Data Sheet'!B61,0) -> 15706 | D54: =IFERROR('Data Sheet'!C61,0) -> 17862 | E54: =IFERROR('Data Sheet'!D61,0) -> 18629 | F54: =IFERROR('Data Sheet'!E61,0) -> 20153 | G54: =IFERROR('Data Sheet'!F61,0) -> 68740 | H54: =IFERROR('Data Sheet'!G61,0) -> 70506 | I54: =IFERROR('Data Sheet'!H61,0) -> 73077 | J54: =IFERROR('Data Sheet'!I61,0) -> 78489 | ... L54: =IFERROR('Data Sheet'!K61,0) -> 79738
B56: FIXED ASSETS NET BLOCK | C56: =IFERROR('Data Sheet'!B62,0) -> 4419 | D56: =IFERROR('Data Sheet'!C62,0) -> 4528 | E56: =IFERROR('Data Sheet'!D62,0) -> 4715 | F56: =IFERROR('Data Sheet'!E62,0) -> 5479 | G56: =IFERROR('Data Sheet'!F62,0) -> 51443 | H56: =IFERROR('Data Sheet'!G62,0) -> 51473 | I56: =IFERROR('Data Sheet'!H62,0) -> 52678 | J56: =IFERROR('Data Sheet'!I62,0) -> 53744 | ... L56: =IFERROR('Data Sheet'!K62,0) -> 57428
B57: Capital Work in Progress | C57: =IFERROR('Data Sheet'!B63,0) -> 229 | D57: =IFERROR('Data Sheet'!C63,0) -> 461 | E57: =IFERROR('Data Sheet'!D63,0) -> 406 | F57: =IFERROR('Data Sheet'!E63,0) -> 597 | G57: =IFERROR('Data Sheet'!F63,0) -> 745 | H57: =IFERROR('Data Sheet'!G63,0) -> 1313 | I57: =IFERROR('Data Sheet'!H63,0) -> 1132 | J57: =IFERROR('Data Sheet'!I63,0) -> 1025 | ... L57: =IFERROR('Data Sheet'!K63,0) -> 880
B58: Investments | C58: =IFERROR('Data Sheet'!B64,0) -> 3794 | D58: =IFERROR('Data Sheet'!C64,0) -> 2873 | E58: =IFERROR('Data Sheet'!D64,0) -> 2716 | F58: =IFERROR('Data Sheet'!E64,0) -> 1255 | G58: =IFERROR('Data Sheet'!F64,0) -> 2709 | H58: =IFERROR('Data Sheet'!G64,0) -> 3521 | I58: =IFERROR('Data Sheet'!H64,0) -> 2882 | J58: =IFERROR('Data Sheet'!I64,0) -> 4625 | ... L58: =IFERROR('Data Sheet'!K64,0) -> 4359
B59: Other Assets | C59: =IFERROR('Data Sheet'!B65-SUM('Data Sheet'!B67:B69),0) -> 1810 | D59: =IFERROR('Data Sheet'!C65-SUM('Data Sheet'!C67:C69),0) -> 2692 | E59: =IFERROR('Data Sheet'!D65-SUM('Data Sheet'!D67:D69),0) -> 2645 | F59: =IFERROR('Data Sheet'!E65-SUM('Data Sheet'!E67:E69),0) -> 3793 | G59: =IFERROR('Data Sheet'!F65-SUM('Data Sheet'!F67:F69),0) -> 4035 | H59: =IFERROR('Data Sheet'!G65-SUM('Data Sheet'!G67:G69),0) -> 4021 | I59: =IFERROR('Data Sheet'!H65-SUM('Data Sheet'!H67:H69),0) -> 4377 | J59: =IFERROR('Data Sheet'!I65-SUM('Data Sheet'!I67:I69),0) -> 4517 | ... L59: =IFERROR('Data Sheet'!K65-SUM('Data Sheet'!K67:K69),0) -> 5655
B60: Total Assets Non current | C60: =IFERROR(SUM(C56:C59),0) -> 10252 | D60: =IFERROR(SUM(D56:D59),0) -> 10554 | E60: =IFERROR(SUM(E56:E59),0) -> 10482 | F60: =IFERROR(SUM(F56:F59),0) -> 11124 | G60: =IFERROR(SUM(G56:G59),0) -> 58932 | H60: =IFERROR(SUM(H56:H59),0) -> 60328 | I60: =IFERROR(SUM(I56:I59),0) -> 61069 | J60: =IFERROR(SUM(J56:J59),0) -> 63911 | ... L60: =IFERROR(SUM(L56:L59),0) -> 68322
B62: Receivables | C62: =IFERROR('Data Sheet'!B67,0) -> 1085 | D62: =IFERROR('Data Sheet'!C67,0) -> 1310 | E62: =IFERROR('Data Sheet'!D67,0) -> 1816 | F62: =IFERROR('Data Sheet'!E67,0) -> 1149 | G62: =IFERROR('Data Sheet'!F67,0) -> 1758 | H62: =IFERROR('Data Sheet'!G67,0) -> 2236 | I62: =IFERROR('Data Sheet'!H67,0) -> 3079 | J62: =IFERROR('Data Sheet'!I67,0) -> 2997 | ... L62: =IFERROR('Data Sheet'!K67,0) -> 3379
B63: Inventory | C63: =IFERROR('Data Sheet'!B68,0) -> 2541 | D63: =IFERROR('Data Sheet'!C68,0) -> 2513 | E63: =IFERROR('Data Sheet'!D68,0) -> 2574 | F63: =IFERROR('Data Sheet'!E68,0) -> 2767 | G63: =IFERROR('Data Sheet'!F68,0) -> 3579 | H63: =IFERROR('Data Sheet'!G68,0) -> 4096 | I63: =IFERROR('Data Sheet'!H68,0) -> 4251 | J63: =IFERROR('Data Sheet'!I68,0) -> 4022 | ... L63: =IFERROR('Data Sheet'!K68,0) -> 4789
B64: Cash & Bank | C64: =IFERROR('Data Sheet'!B69,0) -> 1828 | D64: =IFERROR('Data Sheet'!C69,0) -> 3485 | E64: =IFERROR('Data Sheet'!D69,0) -> 3757 | F64: =IFERROR('Data Sheet'!E69,0) -> 5113 | G64: =IFERROR('Data Sheet'!F69,0) -> 4471 | H64: =IFERROR('Data Sheet'!G69,0) -> 3846 | I64: =IFERROR('Data Sheet'!H69,0) -> 4678 | J64: =IFERROR('Data Sheet'!I69,0) -> 7559 | ... L64: =IFERROR('Data Sheet'!K69,0) -> 3248
B65: Total current assets | C65: =IFERROR(SUM(C62:C64),0) -> 5454 | D65: =IFERROR(SUM(D62:D64),0) -> 7308 | E65: =IFERROR(SUM(E62:E64),0) -> 8147 | F65: =IFERROR(SUM(F62:F64),0) -> 9029 | G65: =IFERROR(SUM(G62:G64),0) -> 9808 | H65: =IFERROR(SUM(H62:H64),0) -> 10178 | I65: =IFERROR(SUM(I62:I64),0) -> 12008 | J65: =IFERROR(SUM(J62:J64),0) -> 14578 | ... L65: =IFERROR(SUM(L62:L64),0) -> 11416
B67: Total assets | C67: =IFERROR(SUM(C65,C60),0) -> 15706 | D67: =IFERROR(SUM(D65,D60),0) -> 17862 | E67: =IFERROR(SUM(E65,E60),0) -> 18629 | F67: =IFERROR(SUM(F65,F60),0) -> 20153 | G67: =IFERROR(SUM(G65,G60),0) -> 68740 | H67: =IFERROR(SUM(H65,H60),0) -> 70506 | I67: =IFERROR(SUM(I65,I60),0) -> 73077 | J67: =IFERROR(SUM(J65,J60),0) -> 78489 | ... L67: =IFERROR(SUM(L65,L60),0) -> 79738
B68: CHECK | C68: =C67=C54 -> TRUE | D68: =D67=D54 -> TRUE | E68: =E67=E54 -> TRUE | F68: =F67=F54 -> TRUE | G68: =G67=G54 -> TRUE | H68: =H67=H54 -> TRUE | I68: =I67=I54 -> TRUE | J68: =J67=J54 -> TRUE | ... L68: =L67=L54 -> TRUE
A72: # | B72: CASH FLOW STATEMENT
B73: operating activities
B74: Profit from operations | C74: =IFERROR('HISTORICAL FS'!V6,0) -> 28840 | D74: =IFERROR('HISTORICAL FS'!W6,0) -> 33312 | E74: =IFERROR('HISTORICAL FS'!X6,0) -> 28771 | F74: =IFERROR('HISTORICAL FS'!Y6,0) -> 23352 | G74: =IFERROR('HISTORICAL FS'!Z6,0) -> 31198 | H74: =IFERROR('HISTORICAL FS'!AA6,0) -> 26943 | I74: =IFERROR('HISTORICAL FS'!AB6,0) -> 41694 | J74: =IFERROR('HISTORICAL FS'!AC6,0) -> 65106 | ... L74: =IFERROR('HISTORICAL FS'!AE6,0) -> 25393
B75: Receivables | C75: =IFERROR('HISTORICAL FS'!V7,0) -> -4152 | D75: =IFERROR('HISTORICAL FS'!W7,0) -> -10688 | E75: =IFERROR('HISTORICAL FS'!X7,0) -> -9109 | F75: =IFERROR('HISTORICAL FS'!Y7,0) -> 9950 | G75: =IFERROR('HISTORICAL FS'!Z7,0) -> -5505 | H75: =IFERROR('HISTORICAL FS'!AA7,0) -> 185 | I75: =IFERROR('HISTORICAL FS'!AB7,0) -> -2213 | J75: =IFERROR('HISTORICAL FS'!AC7,0) -> -1876 | ... L75: =IFERROR('HISTORICAL FS'!AE7,0) -> -1587
B76: Inventory | C76: =IFERROR('HISTORICAL FS'!V8,0) -> -6621 | D76: =IFERROR('HISTORICAL FS'!W8,0) -> -3560 | E76: =IFERROR('HISTORICAL FS'!X8,0) -> 2069 | F76: =IFERROR('HISTORICAL FS'!Y8,0) -> 2326 | G76: =IFERROR('HISTORICAL FS'!Z8,0) -> 3814 | H76: =IFERROR('HISTORICAL FS'!AA8,0) -> 472 | I76: =IFERROR('HISTORICAL FS'!AB8,0) -> -5665 | J76: =IFERROR('HISTORICAL FS'!AC8,0) -> -7265 | ... L76: =IFERROR('HISTORICAL FS'!AE8,0) -> -4318
B77: Payables | C77: =IFERROR('HISTORICAL FS'!V9,0) -> 9301 | D77: =IFERROR('HISTORICAL FS'!W9,0) -> 7320 | E77: =IFERROR('HISTORICAL FS'!X9,0) -> -4692 | F77: =IFERROR('HISTORICAL FS'!Y9,0) -> -8085 | G77: =IFERROR('HISTORICAL FS'!Z9,0) -> 5748 | H77: =IFERROR('HISTORICAL FS'!AA9,0) -> -7012 | I77: =IFERROR('HISTORICAL FS'!AB9,0) -> 6945 | J77: =IFERROR('HISTORICAL FS'!AC9,0) -> 13706 | ... L77: =IFERROR('HISTORICAL FS'!AE9,0) -> -1973
B78: Loans Advances | C78: =IFERROR('HISTORICAL FS'!V10,0) -> 0 | D78: =IFERROR('HISTORICAL FS'!W10,0) -> 0 | E78: =IFERROR('HISTORICAL FS'!X10,0) -> 0 | F78: =IFERROR('HISTORICAL FS'!Y10,0) -> 0 | G78: =IFERROR('HISTORICAL FS'!Z10,0) -> 0 | H78: =IFERROR('HISTORICAL FS'!AA10,0) -> 0 | I78: =IFERROR('HISTORICAL FS'!AB10,0) -> 0 | J78: =IFERROR('HISTORICAL FS'!AC10,0) -> 0 | ... L78: =IFERROR('HISTORICAL FS'!AE10,0) -> -815
B79: Other WC items | C79: =IFERROR('HISTORICAL FS'!V11,0) -> 4727 | D79: =IFERROR('HISTORICAL FS'!W11,0) -> 494 | E79: =IFERROR('HISTORICAL FS'!X11,0) -> 4512 | F79: =IFERROR('HISTORICAL FS'!Y11,0) -> 875 | G79: =IFERROR('HISTORICAL FS'!Z11,0) -> -4150 | H79: =IFERROR('HISTORICAL FS'!AA11,0) -> -4396 | I79: =IFERROR('HISTORICAL FS'!AB11,0) -> -2194 | J79: =IFERROR('HISTORICAL FS'!AC11,0) -> 2760 | ... L79: =IFERROR('HISTORICAL FS'!AE11,0) -> -345
B80: Working capital changes | C80: =IFERROR('HISTORICAL FS'!V12,0) -> 3254 | D80: =IFERROR('HISTORICAL FS'!W12,0) -> -6434 | E80: =IFERROR('HISTORICAL FS'!X12,0) -> -7221 | F80: =IFERROR('HISTORICAL FS'!Y12,0) -> 5065 | G80: =IFERROR('HISTORICAL FS'!Z12,0) -> -93 | H80: =IFERROR('HISTORICAL FS'!AA12,0) -> -10750 | I80: =IFERROR('HISTORICAL FS'!AB12,0) -> -3127 | J80: =IFERROR('HISTORICAL FS'!AC12,0) -> 7325 | ... L80: =IFERROR('HISTORICAL FS'!AE12,0) -> -9038
B81: Direct taxes | C81: =IFERROR('HISTORICAL FS'!V13,0) -> -1895 | D81: =IFERROR('HISTORICAL FS'!W13,0) -> -3021 | E81: =IFERROR('HISTORICAL FS'!X13,0) -> -2659 | F81: =IFERROR('HISTORICAL FS'!Y13,0) -> -1785 | G81: =IFERROR('HISTORICAL FS'!Z13,0) -> -2105 | H81: =IFERROR('HISTORICAL FS'!AA13,0) -> -1910 | I81: =IFERROR('HISTORICAL FS'!AB13,0) -> -3179 | J81: =IFERROR('HISTORICAL FS'!AC13,0) -> -4516 | ... L81: =IFERROR('HISTORICAL FS'!AE13,0) -> -3314
B82: Cash from operating activities | C82: =SUM(C74:C81) -> 33454 | D82: =SUM(D74:D81) -> 17423 | E82: =SUM(E74:E81) -> 11671 | F82: =SUM(F74:F81) -> 31698 | G82: =SUM(G74:G81) -> 28907 | H82: =SUM(H74:H81) -> 3532 | I82: =SUM(I74:I81) -> 32261 | J82: =SUM(J74:J81) -> 75240 | ... L82: =SUM(L74:L81) -> 4003
B85: Investing activities
B86: Fixed assets purchased | C86: =IFERROR('HISTORICAL FS'!V15,0) -> -16072 | D86: =IFERROR('HISTORICAL FS'!W15,0) -> -35079 | E86: =IFERROR('HISTORICAL FS'!X15,0) -> -35304 | F86: =IFERROR('HISTORICAL FS'!Y15,0) -> -29702 | G86: =IFERROR('HISTORICAL FS'!Z15,0) -> -20205 | H86: =IFERROR('HISTORICAL FS'!AA15,0) -> -15168 | I86: =IFERROR('HISTORICAL FS'!AB15,0) -> -19230 | J86: =IFERROR('HISTORICAL FS'!AC15,0) -> -31414 | ... L86: =IFERROR('HISTORICAL FS'!AE15,0) -> -36282
B87: Fixed assets sold | C87: =IFERROR('HISTORICAL FS'!V16,0) -> 53 | D87: =IFERROR('HISTORICAL FS'!W16,0) -> 30 | E87: =IFERROR('HISTORICAL FS'!X16,0) -> 67 | F87: =IFERROR('HISTORICAL FS'!Y16,0) -> 171 | G87: =IFERROR('HISTORICAL FS'!Z16,0) -> 351 | H87: =IFERROR('HISTORICAL FS'!AA16,0) -> 230 | I87: =IFERROR('HISTORICAL FS'!AB16,0) -> 285 | J87: =IFERROR('HISTORICAL FS'!AC16,0) -> 231 | ... L87: =IFERROR('HISTORICAL FS'!AE16,0) -> 46
B88: Investments purchased | C88: =IFERROR('HISTORICAL FS'!V17,0) -> -6 | D88: =IFERROR('HISTORICAL FS'!W17,0) -> -329 | E88: =IFERROR('HISTORICAL FS'!X17,0) -> -130 | F88: =IFERROR('HISTORICAL FS'!Y17,0) -> -1439 | G88: =IFERROR('HISTORICAL FS'!Z17,0) -> -7530 | H88: =IFERROR('HISTORICAL FS'!AA17,0) -> -3008 | I88: =IFERROR('HISTORICAL FS'!AB17,0) -> -50 | J88: =IFERROR('HISTORICAL FS'!AC17,0) -> -74 | ... L88: =IFERROR('HISTORICAL FS'!AE17,0) -> -102
B89: Investments sold | C89: =IFERROR('HISTORICAL FS'!V18,0) -> 1965 | D89: =IFERROR('HISTORICAL FS'!W18,0) -> 2381 | E89: =IFERROR('HISTORICAL FS'!X18,0) -> 5644 | F89: =IFERROR('HISTORICAL FS'!Y18,0) -> 21 | G89: =IFERROR('HISTORICAL FS'!Z18,0) -> 226 | H89: =IFERROR('HISTORICAL FS'!AA18,0) -> 104 | I89: =IFERROR('HISTORICAL FS'!AB18,0) -> 6895 | J89: =IFERROR('HISTORICAL FS'!AC18,0) -> 10821 | ... L89: =IFERROR('HISTORICAL FS'!AE18,0) -> 10704
B90: Interest received | C90: =IFERROR('HISTORICAL FS'!V19,0) -> 638 | D90: =IFERROR('HISTORICAL FS'!W19,0) -> 690 | E90: =IFERROR('HISTORICAL FS'!X19,0) -> 761 | F90: =IFERROR('HISTORICAL FS'!Y19,0) -> 1104 | G90: =IFERROR('HISTORICAL FS'!Z19,0) -> 428 | H90: =IFERROR('HISTORICAL FS'!AA19,0) -> 653 | I90: =IFERROR('HISTORICAL FS'!AB19,0) -> 973 | J90: =IFERROR('HISTORICAL FS'!AC19,0) -> 2493 | ... L90: =IFERROR('HISTORICAL FS'!AE19,0) -> 1940
B91: Dividends received | C91: =IFERROR('HISTORICAL FS'!V20,0) -> 620 | D91: =IFERROR('HISTORICAL FS'!W20,0) -> 1797 | E91: =IFERROR('HISTORICAL FS'!X20,0) -> 232 | F91: =IFERROR('HISTORICAL FS'!Y20,0) -> 21 | G91: =IFERROR('HISTORICAL FS'!Z20,0) -> 18 | H91: =IFERROR('HISTORICAL FS'!AA20,0) -> 32 | I91: =IFERROR('HISTORICAL FS'!AB20,0) -> 46 | J91: =IFERROR('HISTORICAL FS'!AC20,0) -> 47 | ... L91: =IFERROR('HISTORICAL FS'!AE20,0) -> 199
B92: Investment in group cos | C92: =IFERROR('HISTORICAL FS'!V21,0) -> -107 | D92: =IFERROR('HISTORICAL FS'!W21,0) -> -4 | E92: =IFERROR('HISTORICAL FS'!X21,0) -> -9 | F92: =IFERROR('HISTORICAL FS'!Y21,0) -> -606 | G92: =IFERROR('HISTORICAL FS'!Z21,0) -> -10 | H92: =IFERROR('HISTORICAL FS'!AA21,0) -> 0 | I92: =IFERROR('HISTORICAL FS'!AB21,0) -> 0 | J92: =IFERROR('HISTORICAL FS'!AC21,0) -> -150 | ... L92: =IFERROR('HISTORICAL FS'!AE21,0) -> -5
B93: Redemp n Canc of Shares | C93: =IFERROR('HISTORICAL FS'!V22,0) -> 0 | D93: =IFERROR('HISTORICAL FS'!W22,0) -> 14 | E93: =IFERROR('HISTORICAL FS'!X22,0) -> 533 | F93: =IFERROR('HISTORICAL FS'!Y22,0) -> 0 | G93: =IFERROR('HISTORICAL FS'!Z22,0) -> 0 | H93: =IFERROR('HISTORICAL FS'!AA22,0) -> 0 | I93: =IFERROR('HISTORICAL FS'!AB22,0) -> 19 | J93: =IFERROR('HISTORICAL FS'!AC22,0) -> 107 | ... L93: =IFERROR('HISTORICAL FS'!AE22,0) -> 0
B94: Acquisition of companies | C94: =IFERROR('HISTORICAL FS'!V23,0) -> 0 | D94: =IFERROR('HISTORICAL FS'!W23,0) -> 0 | E94: =IFERROR('HISTORICAL FS'!X23,0) -> -8 | F94: =IFERROR('HISTORICAL FS'!Y23,0) -> -27 | G94: =IFERROR('HISTORICAL FS'!Z23,0) -> 0 | H94: =IFERROR('HISTORICAL FS'!AA23,0) -> -98 | I94: =IFERROR('HISTORICAL FS'!AB23,0) -> 0 | J94: =IFERROR('HISTORICAL FS'!AC23,0) -> 0 | ... L94: =IFERROR('HISTORICAL FS'!AE23,0) -> -512
B95: Inter corporate deposits | C95: =IFERROR('HISTORICAL FS'!V24,0) -> 0 | D95: =IFERROR('HISTORICAL FS'!W24,0) -> 0 | E95: =IFERROR('HISTORICAL FS'!X24,0) -> 0 | F95: =IFERROR('HISTORICAL FS'!Y24,0) -> 0 | G95: =IFERROR('HISTORICAL FS'!Z24,0) -> 0 | H95: =IFERROR('HISTORICAL FS'!AA24,0) -> 0 | I95: =IFERROR('HISTORICAL FS'!AB24,0) -> 0 | J95: =IFERROR('HISTORICAL FS'!AC24,0) -> -25 | ... L95: =IFERROR('HISTORICAL FS'!AE24,0) -> -83
B96: Other investing items | C96: =IFERROR('HISTORICAL FS'!V25,0) -> -26663 | D96: =IFERROR('HISTORICAL FS'!W25,0) -> 5360 | E96: =IFERROR('HISTORICAL FS'!X25,0) -> 7335 | F96: =IFERROR('HISTORICAL FS'!Y25,0) -> -2659 | G96: =IFERROR('HISTORICAL FS'!Z25,0) -> 1051 | H96: =IFERROR('HISTORICAL FS'!AA25,0) -> 12813 | I96: =IFERROR('HISTORICAL FS'!AB25,0) -> -4357 | J96: =IFERROR('HISTORICAL FS'!AC25,0) -> -4817 | ... L96: =IFERROR('HISTORICAL FS'!AE25,0) -> -715
B97: Cash From Investing Activities | C97: =SUM(C86:C95) -> -12909 | D97: =SUM(D86:D95) -> -30500 | E97: =SUM(E86:E95) -> -28214 | F97: =SUM(F86:F95) -> -30457 | G97: =SUM(G86:G95) -> -26722 | H97: =SUM(H86:H95) -> -17255 | I97: =SUM(I86:I95) -> -11062 | J97: =SUM(J86:J95) -> -17964 | ... L97: =SUM(L86:L95) -> -24095
B100: Financing Activities
B101: Proceeds from shares | C101: =IFERROR('HISTORICAL FS'!V27,0) -> 5 | D101: =IFERROR('HISTORICAL FS'!W27,0) -> 0 | E101: =IFERROR('HISTORICAL FS'!X27,0) -> 0 | F101: =IFERROR('HISTORICAL FS'!Y27,0) -> 3889 | G101: =IFERROR('HISTORICAL FS'!Z27,0) -> 2603 | H101: =IFERROR('HISTORICAL FS'!AA27,0) -> 19 | I101: =IFERROR('HISTORICAL FS'!AB27,0) -> 20 | J101: =IFERROR('HISTORICAL FS'!AC27,0) -> 82 | ... L101: =IFERROR('HISTORICAL FS'!AE27,0) -> 18
B102: Redemption of debentures | C102: =IFERROR('HISTORICAL FS'!V28,0) -> 0 | D102: =IFERROR('HISTORICAL FS'!W28,0) -> 0 | E102: =IFERROR('HISTORICAL FS'!X28,0) -> 0 | F102: =IFERROR('HISTORICAL FS'!Y28,0) -> 0 | G102: =IFERROR('HISTORICAL FS'!Z28,0) -> 0 | H102: =IFERROR('HISTORICAL FS'!AA28,0) -> 0 | I102: =IFERROR('HISTORICAL FS'!AB28,0) -> 0 | J102: =IFERROR('HISTORICAL FS'!AC28,0) -> 0 | ... L102: =IFERROR('HISTORICAL FS'!AE28,0) -> 0
B103: Proceeds from borrowings | C103: =IFERROR('HISTORICAL FS'!V29,0) -> 33390 | D103: =IFERROR('HISTORICAL FS'!W29,0) -> 37482 | E103: =IFERROR('HISTORICAL FS'!X29,0) -> 51128 | F103: =IFERROR('HISTORICAL FS'!Y29,0) -> 38297 | G103: =IFERROR('HISTORICAL FS'!Z29,0) -> 46641 | H103: =IFERROR('HISTORICAL FS'!AA29,0) -> 46578 | I103: =IFERROR('HISTORICAL FS'!AB29,0) -> 43934 | J103: =IFERROR('HISTORICAL FS'!AC29,0) -> 18829 | ... L103: =IFERROR('HISTORICAL FS'!AE29,0) -> 26425
B104: Repayment of borrowings | C104: =IFERROR('HISTORICAL FS'!V30,0) -> -21732 | D104: =IFERROR('HISTORICAL FS'!W30,0) -> -29964 | E104: =IFERROR('HISTORICAL FS'!X30,0) -> -35198 | F104: =IFERROR('HISTORICAL FS'!Y30,0) -> -29847 | G104: =IFERROR('HISTORICAL FS'!Z30,0) -> -29709 | H104: =IFERROR('HISTORICAL FS'!AA30,0) -> -42816 | I104: =IFERROR('HISTORICAL FS'!AB30,0) -> -62557 | J104: =IFERROR('HISTORICAL FS'!AC30,0) -> -47414 | ... L104: =IFERROR('HISTORICAL FS'!AE30,0) -> -18110
B105: Interest paid fin | C105: =IFERROR('HISTORICAL FS'!V31,0) -> -5336 | D105: =IFERROR('HISTORICAL FS'!W31,0) -> -5411 | E105: =IFERROR('HISTORICAL FS'!X31,0) -> -7005 | F105: =IFERROR('HISTORICAL FS'!Y31,0) -> -7518 | G105: =IFERROR('HISTORICAL FS'!Z31,0) -> -8123 | H105: =IFERROR('HISTORICAL FS'!AA31,0) -> -9251 | I105: =IFERROR('HISTORICAL FS'!AB31,0) -> -9336 | J105: =IFERROR('HISTORICAL FS'!AC31,0) -> -9332 | ... L105: =IFERROR('HISTORICAL FS'!AE31,0) -> -5111
B106: Dividends paid | C106: =IFERROR('HISTORICAL FS'!V32,0) -> -121 | D106: =IFERROR('HISTORICAL FS'!W32,0) -> -96 | E106: =IFERROR('HISTORICAL FS'!X32,0) -> -95 | F106: =IFERROR('HISTORICAL FS'!Y32,0) -> -57 | G106: =IFERROR('HISTORICAL FS'!Z32,0) -> -30 | H106: =IFERROR('HISTORICAL FS'!AA32,0) -> -100 | I106: =IFERROR('HISTORICAL FS'!AB32,0) -> -141 | J106: =IFERROR('HISTORICAL FS'!AC32,0) -> -1059 | ... L106: =IFERROR('HISTORICAL FS'!AE32,0) -> -2203
B107: Financial liabilities | C107: =IFERROR('HISTORICAL FS'!V33,0) -> 0 | D107: =IFERROR('HISTORICAL FS'!W33,0) -> 0 | E107: =IFERROR('HISTORICAL FS'!X33,0) -> 0 | F107: =IFERROR('HISTORICAL FS'!Y33,0) -> -1346 | G107: =IFERROR('HISTORICAL FS'!Z33,0) -> -1477 | H107: =IFERROR('HISTORICAL FS'!AA33,0) -> -1559 | I107: =IFERROR('HISTORICAL FS'!AB33,0) -> -1517 | J107: =IFERROR('HISTORICAL FS'!AC33,0) -> -1924 | ... L107: =IFERROR('HISTORICAL FS'!AE33,0) -> -2145
B108: Other financing items | C108: =IFERROR('HISTORICAL FS'!V34,0) -> 0 | D108: =IFERROR('HISTORICAL FS'!W34,0) -> 0 | E108: =IFERROR('HISTORICAL FS'!X34,0) -> 0 | F108: =IFERROR('HISTORICAL FS'!Y34,0) -> -29 | G108: =IFERROR('HISTORICAL FS'!Z34,0) -> 0 | H108: =IFERROR('HISTORICAL FS'!AA34,0) -> 3750 | I108: =IFERROR('HISTORICAL FS'!AB34,0) -> 3355 | J108: =IFERROR('HISTORICAL FS'!AC34,0) -> 3812 | ... L108: =IFERROR('HISTORICAL FS'!AE34,0) -> -218
B110: Cash Financing Activities | C110: =SUM(C101:C108) -> 6206 | D110: =SUM(D101:D108) -> 2011 | E110: =SUM(E101:E108) -> 8830 | F110: =SUM(F101:F108) -> 3389 | G110: =SUM(G101:G108) -> 9905 | H110: =SUM(H101:H108) -> -3379 | I110: =SUM(I101:I108) -> -26242 | J110: =SUM(J101:J108) -> -37006 | ... L110: =SUM(L101:L108) -> -1344
B112: Net Cash Flow | C112: =SUM(C110+C97+C82) -> 26751 | D112: =SUM(D110+D97+D82) -> -11066 | E112: =SUM(E110+E97+E82) -> -7713 | F112: =SUM(F110+F97+F82) -> 4630 | G112: =SUM(G110+G97+G82) -> 12090 | H112: =SUM(H110+H97+H82) -> -17102 | I112: =SUM(I110+I97+I82) -> -5043 | J112: =SUM(J110+J97+J82) -> 20270 | ... L112: =SUM(L110+L97+L82) -> -21436
A118: #Cash Flow Statement
B119: Cash from Operating Activity | C119: 30199.25 | D119: 23857.42 | E119: 18890.75 | F119: 26632.94 | G119: 29000.51 | H119: 14282.83 | I119: 35388.01 | J119: 67915 | K119: 63102 | L119: 13041
B121: Cash from Investing Activity | C121: -39571.4 | D121: -25139.14 | E121: -20878.07 | F121: -33114.55 | G121: -25672.5 | H121: -4443.66 | I121: -15417.17 | J121: -22781 | K121: -49982 | L121: -24810
B123: Cash from Financing Activity | C123: 6205.3 | D123: 2011.71 | E123: 8830.37 | F123: 3389.61 | G123: 9904.2 | H123: -3380.17 | I123: -26242.9 | J123: -37006 | K123: -18786 | L123: -1344
B125: Net Cash Flow | C125: -3166.85 | D125: 729.99 | E125: 6843.05 | F125: -3092 | G125: 13232.21 | H125: 6459 | I125: -6272.06 | J125: 8128 | K125: -5666 | L125: -13113

Sheet Sheet1
B2: ="RATIO ANALYSIS - "&'Data Sheet'!B1 -> RATIO ANALYSIS - HINDUSTAN UNILEVER LTD
B3: YEARS | C3: ='Data Sheet'!B16 -> 42825 | D3: ='Data Sheet'!C16 -> 43190 | E3: ='Data Sheet'!D16 -> 43555 | F3: ='Data Sheet'!E16 -> 43921 | G3: ='Data Sheet'!F16 -> 44286 | H3: ='Data Sheet'!G16 -> 44651 | I3: ='Data Sheet'!H16 -> 45016 | J3: ='Data Sheet'!I16 -> 45382 | ... L3: ='Data Sheet'!K16 -> 46112
B5: SALES GROWTH | D5: =IFERROR(FINANCIALS!D6,0) -> 0.071859357 | E5: =IFERROR(FINANCIALS!E6,0) -> 0.10592207 | F5: =IFERROR(FINANCIALS!F6,0) -> 0.012032562 | G5: =IFERROR(FINANCIALS!G6,0) -> 0.18211296 | H5: =IFERROR(FINANCIALS!H6,0) -> 0.11520796 | I5: =IFERROR(FINANCIALS!I6,0) -> 0.15509286 | J5: =IFERROR(FINANCIALS!J6,0) -> 0.021723341 | K5: =IFERROR(FINANCIALS!K6,0) -> -0.0091766835 | L5: =IFERROR(FINANCIALS!L6,0) -> 0.051200104
B6: EBITDA GROWTH | D6: =IFERROR(FINANCIALS!D17/FINANCIALS!C17-1,0) -> 0.18505057 | E6: =IFERROR(FINANCIALS!E17/FINANCIALS!D17-1,0) -> 0.18415789 | F6: =IFERROR(FINANCIALS!F17/FINANCIALS!E17-1,0) -> 0.11047297 | G6: =IFERROR(FINANCIALS!G17/FINANCIALS!F17-1,0) -> 0.17898793 | H6: =IFERROR(FINANCIALS!H17/FINANCIALS!G17-1,0) -> 0.10588336 | I6: =IFERROR(FINANCIALS!I17/FINANCIALS!H17-1,0) -> 0.10033445 | J6: =IFERROR(FINANCIALS!J17/FINANCIALS!I17-1,0) -> 0.036191419 | K6: =IFERROR(FINANCIALS!K17/FINANCIALS!J17-1,0) -> 0.0026604816 | L6: =IFERROR(FINANCIALS!L17/FINANCIALS!K17-1,0) -> 0.023200435
B7: EBIT GROWTH | D7: =IFERROR(FINANCIALS!D26/FINANCIALS!C26-1,0) -> 0.18631633 | E7: =IFERROR(FINANCIALS!E26/FINANCIALS!D26-1,0) -> 0.19114051 | F7: =IFERROR(FINANCIALS!F26/FINANCIALS!E26-1,0) -> 0.055421396 | G7: =IFERROR(FINANCIALS!G26/FINANCIALS!F26-1,0) -> 0.19379934 | H7: =IFERROR(FINANCIALS!H26/FINANCIALS!G26-1,0) -> 0.11739339 | I7: =IFERROR(FINANCIALS!I26/FINANCIALS!H26-1,0) -> 0.10600343 | J7: =IFERROR(FINANCIALS!J26/FINANCIALS!I26-1,0) -> 0.016516749 | K7: =IFERROR(FINANCIALS!K26/FINANCIALS!J26-1,0) -> -0.0034327561 | L7: =IFERROR(FINANCIALS!L26/FINANCIALS!K26-1,0) -> 0.017758726
B8: NET PROFIT GROWTH | D8: =IFERROR(FINANCIALS!D32/FINANCIALS!C32-1,0) -> 0.25489186 | E8: =IFERROR(FINANCIALS!E32/FINANCIALS!D32-1,0) -> 0.17726713 | F8: =IFERROR(FINANCIALS!F32/FINANCIALS!E32-1,0) -> 0.10352039 | G8: =IFERROR(FINANCIALS!G32/FINANCIALS!F32-1,0) -> 0.23641819 | H8: =IFERROR(FINANCIALS!H32/FINANCIALS!G32-1,0) -> 0.10780432 | I8: =IFERROR(FINANCIALS!I32/FINANCIALS!H32-1,0) -> 0.11783697 | J8: =IFERROR(FINANCIALS!J32/FINANCIALS!I32-1,0) -> -0.023723569 | K8: =IFERROR(FINANCIALS!K32/FINANCIALS!J32-1,0) -> -0.015742208 | L8: =IFERROR(FINANCIALS!L32/FINANCIALS!K32-1,0) -> 0.08802061
B9: DIVIDENED GROWTH | D9: =IFERROR(FINANCIALS!D40/FINANCIALS!C40-1,0) -> 0.17636188 | E9: =IFERROR(FINANCIALS!E40/FINANCIALS!D40-1,0) -> 0.099898369 | F9: =IFERROR(FINANCIALS!F40/FINANCIALS!E40-1,0) -> 0.13631114 | G9: =IFERROR(FINANCIALS!G40/FINANCIALS!F40-1,0) -> 0.6238764 | H9: =IFERROR(FINANCIALS!H40/FINANCIALS!G40-1,0) -> -0.16049383 | I9: =IFERROR(FINANCIALS!I40/FINANCIALS!H40-1,0) -> 0.14705882 | J9: =IFERROR(FINANCIALS!J40/FINANCIALS!I40-1,0) -> 0.076923077 | K9: =IFERROR(FINANCIALS!K40/FINANCIALS!J40-1,0) -> 0.26190476 | L9: =IFERROR(FINANCIALS!L40/FINANCIALS!K40-1,0) -> -0.22641509
B11: GROSS MARGIN | C11: =IFERROR(FINANCIALS!C12,0) -> 0.43685544 | D11: =IFERROR(FINANCIALS!D12,0) -> 0.45663244 | E11: =IFERROR(FINANCIALS!E12,0) -> 0.46372424 | F11: =IFERROR(FINANCIALS!F12,0) -> 0.48183898 | G11: =IFERROR(FINANCIALS!G12,0) -> 0.46200136 | H11: =IFERROR(FINANCIALS!H12,0) -> 0.44579186 | I11: =IFERROR(FINANCIALS!I12,0) -> 0.41596236 | J11: =IFERROR(FINANCIALS!J12,0) -> 0.45632997 | ... L11: =IFERROR(FINANCIALS!L12,0) -> 0.44726066
B12: EDITDA MARGIN | C12: =IFERROR(FINANCIALS!C18,0) -> 0.19082082 | D12: =IFERROR(FINANCIALS!D18,0) -> 0.21097201 | E12: =IFERROR(FINANCIALS!E18,0) -> 0.22589672 | F12: =IFERROR(FINANCIALS!F18,0) -> 0.24786969 | G12: =IFERROR(FINANCIALS!G18,0) -> 0.24721443 | H12: =IFERROR(FINANCIALS!H18,0) -> 0.24514739 | I12: =IFERROR(FINANCIALS!I18,0) -> 0.23352592 | J12: =IFERROR(FINANCIALS!J18,0) -> 0.23683275 | ... L12: =IFERROR(FINANCIALS!L18,0) -> 0.23327853
B13: EBIT MARGIN | C13: =IFERROR((FINANCIALS!C17-FINANCIALS!C23)/FINANCIALS!C5,0) -> 0.17779386 | D13: =IFERROR((FINANCIALS!D17-FINANCIALS!D23)/FINANCIALS!D5,0) -> 0.19634266 | E13: =IFERROR((FINANCIALS!E17-FINANCIALS!E23)/FINANCIALS!E5,0) -> 0.21152379 | F13: =IFERROR((FINANCIALS!F17-FINANCIALS!F23)/FINANCIALS!F5,0) -> 0.22268306 | G13: =IFERROR((FINANCIALS!G17-FINANCIALS!G23)/FINANCIALS!G5,0) -> 0.22437697 | H13: =IFERROR((FINANCIALS!H17-FINANCIALS!H23)/FINANCIALS!H5,0) -> 0.22434504 | I13: =IFERROR((FINANCIALS!I17-FINANCIALS!I23)/FINANCIALS!I5,0) -> 0.21475735 | J13: =IFERROR((FINANCIALS!J17-FINANCIALS!J23)/FINANCIALS!J5,0) -> 0.21718689 | ... L13: =IFERROR((FINANCIALS!L17-FINANCIALS!L23)/FINANCIALS!L5,0) -> 0.2126016
B14: EBT MARGIN | C14: =IFERROR(FINANCIALS!C27,0) -> 0.17673844 | D14: =IFERROR(FINANCIALS!D27,0) -> 0.1956112 | E14: =IFERROR(FINANCIALS!E27,0) -> 0.2106843 | F14: =IFERROR(FINANCIALS!F27,0) -> 0.21971696 | G14: =IFERROR(FINANCIALS!G27,0) -> 0.22188909 | H14: =IFERROR(FINANCIALS!H27,0) -> 0.22232391 | I14: =IFERROR(FINANCIALS!I27,0) -> 0.21287554 | J14: =IFERROR(FINANCIALS!J27,0) -> 0.21179075 | ... L14: =IFERROR(FINANCIALS!L27,0) -> 0.20624186
B15: NET PROFIT MARGIN | C15: =IFERROR(FINANCIALS!C33,0) -> 0.11712201 | D15: =IFERROR(FINANCIALS!D33,0) -> 0.13712196 | E15: =IFERROR(FINANCIALS!E33,0) -> 0.14596795 | F15: =IFERROR(FINANCIALS!F33,0) -> 0.15916346 | G15: =IFERROR(FINANCIALS!G33,0) -> 0.16647529 | H15: =IFERROR(FINANCIALS!H33,0) -> 0.16537009 | I15: =IFERROR(FINANCIALS!I33,0) -> 0.16003632 | J15: =IFERROR(FINANCIALS!J33,0) -> 0.1529178 | ... L15: =IFERROR(FINANCIALS!L33,0) -> 0.15722529
B18: SALESEXPENSES%SALES | C18: =IFERROR(FINANCIALS!C15,0) -> 0.24603462 | D18: =IFERROR(FINANCIALS!D15,0) -> 0.24566043 | E18: =IFERROR(FINANCIALS!E15,0) -> 0.23782752 | F18: =IFERROR(FINANCIALS!F15,0) -> 0.23396928 | G18: =IFERROR(FINANCIALS!G15,0) -> 0.21478694 | H18: =IFERROR(FINANCIALS!H15,0) -> 0.20064447 | I18: =IFERROR(FINANCIALS!I15,0) -> 0.18243645 | J18: =IFERROR(FINANCIALS!J15,0) -> 0.21949722 | ... L18: =IFERROR(FINANCIALS!L15,0) -> 0.21398213
B19: DEPRECIATION%SALES | C19: =IFERROR(FINANCIALS!C24,0) -> 0.02313253 | D19: =IFERROR(FINANCIALS!D24,0) -> 0.026923475 | E19: =IFERROR(FINANCIALS!E24,0) -> 0.026801385 | F19: =IFERROR(FINANCIALS!F24,0) -> 0.048607742 | G19: =IFERROR(FINANCIALS!G24,0) -> 0.042448915 | H19: =IFERROR(FINANCIALS!H24,0) -> 0.037535265 | I19: =IFERROR(FINANCIALS!I24,0) -> 0.032135892 | J19: =IFERROR(FINANCIALS!J24,0) -> 0.036135627 | ... L19: =IFERROR(FINANCIALS!L24,0) -> 0.037408093
B20: OPERATINGINCOME%SALES | C20: =C13 -> 0.17779386 | D20: =D13 -> 0.19634266 | E20: =E13 -> 0.21152379 | F20: =F13 -> 0.22268306 | G20: =G13 -> 0.22437697 | H20: =H13 -> 0.22434504 | I20: =I13 -> 0.21475735 | J20: =J13 -> 0.21718689 | ... L20: =L13 -> 0.2126016
B22: RETURN ON CAPITAL EMPLOYED | C22: =(FINANCIALS!C17-FINANCIALS!C23)/(SUM(FINANCIALS!C50:C52)) -> 0.83976642 | D22: =(FINANCIALS!D17-FINANCIALS!D23)/(SUM(FINANCIALS!D50:D52)) -> 0.95852218 | E22: =(FINANCIALS!E17-FINANCIALS!E23)/(SUM(FINANCIALS!E50:E52)) -> 1.0438112 | F22: =(FINANCIALS!F17-FINANCIALS!F23)/(SUM(FINANCIALS!F50:F52)) -> 1.0765585 | G22: =(FINANCIALS!G17-FINANCIALS!G23)/(SUM(FINANCIALS!G50:G52)) -> 0.22133658 | H22: =(FINANCIALS!H17-FINANCIALS!H23)/(SUM(FINANCIALS!H50:H52)) -> 0.23483155 | I22: =(FINANCIALS!I17-FINANCIALS!I23)/(SUM(FINANCIALS!I50:I52)) -> 0.25250859 | J22: =(FINANCIALS!J17-FINANCIALS!J23)/(SUM(FINANCIALS!J50:J52)) -> 0.25507571 | ... L22: =(FINANCIALS!L17-FINANCIALS!L23)/(SUM(FINANCIALS!L50:L52)) -> 0.27293546
B23: RETAINED EARNING% | C23: =IFERROR(FINANCIALS!C43,0) -> 0.054582904 | D23: =IFERROR(FINANCIALS!D43,0) -> 0.11366434 | E23: =IFERROR(FINANCIALS!E43,0) -> 0.17183688 | F23: =IFERROR(FINANCIALS!F43,0) -> 0.14718888 | G23: =IFERROR(FINANCIALS!G43,0) -> 0 | H23: =IFERROR(FINANCIALS!H43,0) -> 0.078750144 | I23: =IFERROR(FINANCIALS!I43,0) -> 0.054667354 | J23: =IFERROR(FINANCIALS!J43,0) -> 0 | ... L23: =IFERROR(FINANCIALS!L43,0) -> 0.049427782
B24: RETURN ON EQUITY % | C24: =IFERROR(FINANCIALS!C32/SUM(FINANCIALS!C50:C51),0) -> 0.57591934 | D24: =IFERROR(FINANCIALS!D32/SUM(FINANCIALS!D50:D51),0) -> 0.66941354 | E24: =IFERROR(FINANCIALS!E32/SUM(FINANCIALS!E50:E51),0) -> 0.72937587 | F24: =IFERROR(FINANCIALS!F32/SUM(FINANCIALS!F50:F51),0) -> 0.76947381 | G24: =IFERROR(FINANCIALS!G32/SUM(FINANCIALS!G50:G51),0) -> 0.16421949 | H24: =IFERROR(FINANCIALS!H32/SUM(FINANCIALS!H50:H51),0) -> 0.17677993 | I24: =IFERROR(FINANCIALS!I32/SUM(FINANCIALS!I50:I51),0) -> 0.19272821 | J24: =IFERROR(FINANCIALS!J32/SUM(FINANCIALS!J50:J51),0) -> 0.18479831 | ... L24: =IFERROR(FINANCIALS!L32/SUM(FINANCIALS!L50:L51),0) -> 0.20796487
B25: SELF SUSTAINED GROWTH RATE | C25: =IFERROR(C23*C24,0) -> 0.03143535 | D25: =IFERROR(D23*D24,0) -> 0.076088449 | E25: =IFERROR(E23*E24,0) -> 0.12533367 | F25: =IFERROR(F23*F24,0) -> 0.11325799 | G25: =IFERROR(G23*G24,0) -> 0 | H25: =IFERROR(H23*H24,0) -> 0.013921445 | I25: =IFERROR(I23*I24,0) -> 0.010535941 | J25: =IFERROR(J23*J24,0) -> 0 | ... L25: =IFERROR(L23*L24,0) -> 0.010279242
B26: INTEREST COVERAGE RATIO | C26: =(FINANCIALS!C17-FINANCIALS!C23)/FINANCIALS!C20 -> 168.45714 | D26: =(FINANCIALS!D17-FINANCIALS!D23)/FINANCIALS!D20 -> 268.42308 | E26: =(FINANCIALS!E17-FINANCIALS!E23)/FINANCIALS!E20 -> 251.9697 | F26: =(FINANCIALS!F17-FINANCIALS!F23)/FINANCIALS!F20 -> 75.076271 | G26: =(FINANCIALS!G17-FINANCIALS!G23)/FINANCIALS!G20 -> 90.188034 | H26: =(FINANCIALS!H17-FINANCIALS!H23)/FINANCIALS!H20 -> 111 | I26: =(FINANCIALS!I17-FINANCIALS!I23)/FINANCIALS!I20 -> 114.12281 | J26: =(FINANCIALS!J17-FINANCIALS!J23)/FINANCIALS!J20 -> 40.248503 | ... L26: =(FINANCIALS!L17-FINANCIALS!L23)/FINANCIALS!L20 -> 33.429268
B28: Debtor Turnover Ratio | C28: =FINANCIALS!C5/FINANCIALS!C62 -> 30.564055 | D28: =FINANCIALS!D5/FINANCIALS!D62 -> 27.133588 | E28: =FINANCIALS!E5/FINANCIALS!E62 -> 21.646476 | F28: =FINANCIALS!F5/FINANCIALS!F62 -> 34.624021 | G28: =FINANCIALS!G5/FINANCIALS!G62 -> 26.750853 | H28: =FINANCIALS!H5/FINANCIALS!H62 -> 23.455277 | I28: =FINANCIALS!I5/FINANCIALS!I62 -> 19.675219 | J28: =FINANCIALS!J5/FINANCIALS!J62 -> 20.652653 | ... L28: =FINANCIALS!L5/FINANCIALS!L62 -> 19.079017
B29: Credit Turnover Ratio | C29: =IFERROR(FINANCIALS!C5/FINANCIALS!C53,0) -> 3.8183074 | D29: =IFERROR(FINANCIALS!D5/FINANCIALS!D53,0) -> 3.3593233 | E29: =IFERROR(FINANCIALS!E5/FINANCIALS!E53,0) -> 3.6865798 | F29: =IFERROR(FINANCIALS!F5/FINANCIALS!F53,0) -> 3.3363804 | G29: =IFERROR(FINANCIALS!G5/FINANCIALS!G53,0) -> 2.2324124 | H29: =IFERROR(FINANCIALS!H5/FINANCIALS!H53,0) -> 2.5706303 | I29: =IFERROR(FINANCIALS!I5/FINANCIALS!I53,0) -> 2.8106152 | J29: =IFERROR(FINANCIALS!J5/FINANCIALS!J53,0) -> 2.4002792 | ... L29: =IFERROR(FINANCIALS!L5/FINANCIALS!L53,0) -> 2.1838014
B30: Inventory Turnoover ratio | C30: =IFERROR(FINANCIALS!C5/FINANCIALS!C63,0) -> 13.050767 | D30: =IFERROR(FINANCIALS!D5/FINANCIALS!D63,0) -> 14.144449 | E30: =IFERROR(FINANCIALS!E5/FINANCIALS!E63,0) -> 15.27195 | F30: =IFERROR(FINANCIALS!F5/FINANCIALS!F63,0) -> 14.377665 | G30: =IFERROR(FINANCIALS!G5/FINANCIALS!G63,0) -> 13.139983 | H30: =IFERROR(FINANCIALS!H5/FINANCIALS!H63,0) -> 12.804199 | I30: =IFERROR(FINANCIALS!I5/FINANCIALS!I63,0) -> 14.250765 | J30: =IFERROR(FINANCIALS!J5/FINANCIALS!J63,0) -> 15.389359 | ... L30: =IFERROR(FINANCIALS!L5/FINANCIALS!L63,0) -> 13.461683
B31: Fixed Asset Turnover | C31: =IFERROR(FINANCIALS!C5/FINANCIALS!C52,0) -> 119.71841 | D31: =IFERROR(FINANCIALS!D5/FINANCIALS!D52,0) -> 0 | E31: =IFERROR(FINANCIALS!E5/FINANCIALS!E52,0) -> 397.07071 | F31: =IFERROR(FINANCIALS!F5/FINANCIALS!F52,0) -> 0 | G31: =IFERROR(FINANCIALS!G5/FINANCIALS!G52,0) -> 0 | H31: =IFERROR(FINANCIALS!H5/FINANCIALS!H52,0) -> 50.283797 | I31: =IFERROR(FINANCIALS!I5/FINANCIALS!I52,0) -> 49.696473 | J31: =IFERROR(FINANCIALS!J5/FINANCIALS!J52,0) -> 41.708895 | ... L31: =IFERROR(FINANCIALS!L5/FINANCIALS!L52,0) -> 43.618403
B32: Capital Turnover Ratio | C32: =IFERROR(FINANCIALS!C5/SUM(FINANCIALS!C50:C51),) -> 4.9172598 | D32: =IFERROR(FINANCIALS!D5/SUM(FINANCIALS!D50:D51),) -> 4.8818844 | E32: =IFERROR(FINANCIALS!E5/SUM(FINANCIALS!E50:E51),) -> 4.9968222 | F32: =IFERROR(FINANCIALS!F5/SUM(FINANCIALS!F50:F51),) -> 4.8344878 | G32: =IFERROR(FINANCIALS!G5/SUM(FINANCIALS!G50:G51),) -> 0.98644964 | H32: =IFERROR(FINANCIALS!H5/SUM(FINANCIALS!H50:H51),) -> 1.0689957 | I32: =IFERROR(FINANCIALS!I5/SUM(FINANCIALS!I50:I51),) -> 1.204278 | J32: =IFERROR(FINANCIALS!J5/SUM(FINANCIALS!J50:J51),) -> 1.2084814 | ... L32: =IFERROR(FINANCIALS!L5/SUM(FINANCIALS!L50:L51),) -> 1.322719
B34: debtor days | C34: =IFERROR(365/C28,0) -> 11.942133
B35: Payable days | C35: =IFERROR(365/C29,0) -> 95.592093
B36: Inventory Days | C36: =IFERROR(365/C30,0) -> 27.967704
B37: Cash Conversion cycle

Sheet HISTORICAL FS
N3: 13041
T4: 42064 | U4: 42430 | V4: 42795 | W4: 43160 | X4: 43525 | Y4: 43891 | Z4: 44256 | AA4: 44621 | AB4: 44986 | AC4: 45352 | AD4: 45717 | AE4: 46082
S5: Cash from Operating Activity - | T5: 35531 | U5: 37900 | V5: 30199 | W5: 23857 | X5: 18891 | Y5: 26633 | Z5: 29001 | AA5: 14283 | AB5: 35388 | AC5: 67915 | AD5: 63102 | AE5: 13041
S6: Profit from operations | T6: 43397 | U6: 38626 | V6: 28840 | W6: 33312 | X6: 28771 | Y6: 23352 | Z6: 31198 | AA6: 26943 | AB6: 41694 | AC6: 65106 | AD6: 58937 | AE6: 25393
S7: Receivables | T7: -3179 | U7: -2223 | V7: -4152 | W7: -10688 | X7: -9109 | Y7: 9950 | Z7: -5505 | AA7: 185 | AB7: -2213 | AC7: -1876 | AD7: 3573 | AE7: -1587
S8: Inventory | T8: -3692 | U8: -5743 | V8: -6621 | W8: -3560 | X8: 2069 | Y8: 2326 | Z8: 3814 | AA8: 472 | AB8: -5665 | AC8: -7265 | AD8: 2127 | AE8: -4318
S9: Payables | T9: 3598 | U9: 3947 | V9: 9301 | W9: 7320 | X9: -4692 | Y9: -8085 | Z9: 5748 | AA9: -7012 | AB9: 6945 | AC9: 13706 | AD9: 1303 | AE9: -1973
S10: Loans Advances | T10: 0 | U10: -520 | V10: 0 | W10: 0 | X10: 0 | Y10: 0 | Z10: 0 | AA10: 0 | AB10: 0 | AC10: 0 | AD10: 0 | AE10: -815
S11: Other WC items | T11: -398 | U11: 5852 | V11: 4727 | W11: 494 | X11: 4512 | Y11: 875 | Z11: -4150 | AA11: -4396 | AB11: -2194 | AC11: 2760 | AD11: 1153 | AE11: -345
S12: Working capital changes | T12: -3672 | U12: 1313 | V12: 3254 | W12: -6434 | X12: -7221 | Y12: 5065 | Z12: -93 | AA12: -10750 | AB12: -3127 | AC12: 7325 | AD12: 8156 | AE12: -9038
S13: Direct taxes | T13: -4194 | U13: -2040 | V13: -1895 | W13: -3021 | X13: -2659 | Y13: -1785 | Z13: -2105 | AA13: -1910 | AB13: -3179 | AC13: -4516 | AD13: -3991 | AE13: -3314
S14: Cash from Investing Activity - | T14: -36232 | U14: -36694 | V14: -39571 | W14: -25139 | X14: -20878 | Y14: -33115 | Z14: -25672 | AA14: -4444 | AB14: -15417 | AC14: -22781 | AD14: -49982 | AE14: -24810
S15: Fixed assets purchased | T15: -31962 | U15: -31503 | V15: -16072 | W15: -35079 | X15: -35304 | Y15: -29702 | Z15: -20205 | AA15: -15168 | AB15: -19230 | AC15: -31414 | AD15: -38042 | AE15: -36282
S16: Fixed assets sold | T16: 74 | U16: 59 | V16: 53 | W16: 30 | X16: 67 | Y16: 171 | Z16: 351 | AA16: 230 | AB16: 285 | AC16: 231 | AD16: 974 | AE16: 46
... S19: Interest received | T19: 698 | U19: 731 | V19: 638 | W19: 690 | X19: 761 | Y19: 1104 | Z19: 428 | AA19: 653 | AB19: 973 | AC19: 2493 | AD19: 2420 | AE19: 1940
N20: 0 | S20: Dividends received | T20: 80 | U20: 58 | V20: 620 | W20: 1797 | X20: 232 | Y20: 21 | Z20: 18 | AA20: 32 | AB20: 46 | AC20: 47 | AD20: 64 | AE20: 199
N21: -512 | S21: Investment in group cos | T21: -160 | U21: 0 | V21: -107 | W21: -4 | X21: -9 | Y21: -606 | Z21: -10 | AA21: 0 | AB21: 0 | AC21: -150 | AD21: 0 | AE21: -5
N22: -83 | S22: Redemp n Canc of Shares | T22: 0 | U22: 0 | V22: 0 | W22: 14 | X22: 533 | Y22: 0 | Z22: 0 | AA22: 0 | AB22: 19 | AC22: 107 | AD22: 765 | AE22: 0
N23: -715 | S23: Acquisition of companies | T23: 0 | U23: -111 | V23: 0 | W23: 0 | X23: -8 | Y23: -27 | Z23: 0 | AA23: -98 | AB23: 0 | AC23: 0 | AD23: -688 | AE23: -512
N24: -1344 | S24: Inter corporate deposits | T24: 0 | U24: 0 | V24: 0 | W24: 0 | X24: 0 | Y24: 0 | Z24: 0 | AA24: 0 | AB24: 0 | AC24: -25 | AD24: -20 | AE24: -83
N25: 18 | S25: Other investing items | T25: 456 | U25: -1289 | V25: -26663 | W25: 5360 | X25: 7335 | Y25: -2659 | Z25: 1051 | AA25: 12813 | AB25: -4357 | AC25: -4817 | AD25: -2889 | AE25: -715
N26: 0 | S26: Cash from Financing Activity - | T26: 5201 | U26: -3795 | V26: 6205 | W26: 2012 | X26: 8830 | Y26: 3390 | Z26: 9904 | AA26: -3380 | AB26: -26243 | AC26: -37006 | AD26: -18786 | AE26: -1344
N27: 26425 | S27: Proceeds from shares | T27: 0 | U27: 7433 | V27: 5 | W27: 0 | X27: 0 | Y27: 3889 | Z27: 2603 | AA27: 19 | AB27: 20 | AC27: 82 | AD27: 1108 | AE27: 18
N28: -18110 | S28: Redemption of debentures | T28: -744 | U28: 0 | V28: 0 | W28: 0 | X28: 0 | Y28: 0 | Z28: 0 | AA28: 0 | AB28: 0 | AC28: 0 | AD28: 0 | AE28: 0
N29: -5111 | S29: Proceeds from borrowings | T29: 36363 | U29: 19519 | V29: 33390 | W29: 37482 | X29: 51128 | Y29: 38297 | Z29: 46641 | AA29: 46578 | AB29: 43934 | AC29: 18829 | AD29: 13384 | AE29: 26425
N30: -2203 | S30: Repayment of borrowings | T30: -23332 | U30: -24924 | V30: -21732 | W30: -29964 | X30: -35198 | Y30: -29847 | Z30: -29709 | AA30: -42816 | AB30: -62557 | AC30: -47414 | AD30: -21443 | AE30: -18110
N31: -2145 | S31: Interest paid fin | T31: -6307 | U31: -5716 | V31: -5336 | W31: -5411 | X31: -7005 | Y31: -7518 | Z31: -8123 | AA31: -9251 | AB31: -9336 | AC31: -9332 | AD31: -5814 | AE31: -5111
... N35: 0.87 | S35: Net Cash Flow | T35: 4500 | U35: -2589 | V35: -3167 | W35: 730 | X35: 6843 | Y35: -3092 | Z35: 13232 | AA35: 6459 | AB35: -6272 | AC35: 8128 | AD35: -5666 | AE35: -13113
S36: Free Cash Flow | T36: 3643 | U36: 6455 | V36: 14181 | W36: -11191 | X36: -16346 | Y36: -2898 | Z36: 9146 | AA36: -655 | AB36: 16443 | AC36: 36732 | AD36: 26034 | AE36: -23195
S37: CFO/OP | T37: 1.01 | U37: 1.04 | V37: 1.08 | W37: 0.85 | X37: 0.87 | Y37: 1.58 | Z37: 0.96 | AA37: 0.66 | AB37: 1.21 | AC37: 1.25 | AD37: 1.2 | AE37: 0.87

Sheet Data Sheet
A1: COMPANY NAME | B1: HINDUSTAN UNILEVER LTD | E1: =IF(B2<>B3, "A NEW VERSION OF THE WORKSHEET IS AVAILABLE", "")
A2: LATEST VERSION | B2: 2.1 | E2: PLEASE DO NOT MAKE ANY CHANGES TO THIS SHEET
A3: CURRENT VERSION | B3: 2.1
A5: META
A6: Number of shares | B6: =IF(B9>0, B9/B8, 0) -> 234.95912
A7: Face Value | B7: 1
A8: Current Price | B8: 2143.8
A9: Market Capitalization | B9: 503705.37
A15: PROFIT & LOSS
A16: Report Date | B16: 42825 | C16: 43190 | D16: 43555 | E16: 43921 | F16: 44286 | G16: 44651 | H16: 45016 | I16: 45382 | J16: 45747 | K16: 46112
A17: Sales | B17: 33162 | C17: 35545 | D17: 39310 | E17: 39783 | F17: 47028 | G17: 52446 | H17: 60580 | I17: 61896 | J17: 61328 | K17: 64468
A18: Raw Material Cost | B18: 13606 | C18: 14233 | D18: 15845 | E18: 15697 | F18: 20141 | G18: 22871 | H18: 28427 | I18: 26822 | J18: 26602 | K18: 29158
A19: Change in Inventory | B19: -144 | C19: 72 | D19: -12 | E19: 108 | F19: 405 | G19: 22 | H19: 75 | I19: 11 | J19: 125 | K19: 429
A20: Power and Fuel | B20: 295 | C20: 295 | D20: 308 | E20: 299 | F20: 339 | G20: 318 | H20: 384 | I20: 446 | J20: 403 | K20: 426
A21: Other Mfr. Exp | B21: 2887 | C21: 2998 | D21: 3041 | E21: 2906 | F21: 2868 | G21: 3354 | H21: 3791 | I21: 3385 | J21: 3687 | K21: 3304
A22: Employee Cost | B22: 1743 | C22: 1860 | D22: 1875 | E22: 1820 | F22: 2358 | G22: 2545 | H22: 2854 | I22: 3009 | J22: 2952 | K22: 3175
A23: Selling and admin | B23: 6689 | C23: 7252 | D23: 7796 | E23: 7620 | F23: 7906 | G23: 8164 | H23: 8785 | I23: 10780 | J23: 10145 | K23: 10744
A24: Other Expenses | B24: 1470 | C24: 1480 | D24: 1553 | E24: 1688 | F24: 2195 | G24: 2359 | H24: 2267 | I24: 2806 | J24: 2966 | K24: 3051
A25: Other Income | B25: 606 | C25: 353 | D25: 322 | E25: 424 | F25: 170 | G25: 219 | H25: 448 | I25: 817 | J25: 1355 | K25: 4923
A26: Depreciation | B26: 432 | C26: 520 | D26: 565 | E26: 1002 | F26: 1074 | G26: 1091 | H26: 1137 | I26: 1216 | J26: 1253 | K26: 1333
A27: Interest | B27: 35 | C27: 26 | D27: 33 | E27: 118 | F27: 117 | G27: 106 | H27: 114 | I27: 334 | J27: 381 | K27: 410
... A31: Dividend Amount | B31: 3672 | C31: 4320 | D31: 4752 | E31: 5400 | F31: 9517.5 | G31: 7990 | H31: 9165 | I31: 9870 | J31: 12455 | K31: 9635
A40: Quarters
A41: Report Date | B41: 45291 | C41: 45382 | D41: 45473 | E41: 45565 | F41: 45657 | G41: 45747 | H41: 45838 | I41: 45930 | J41: 46022 | K41: 46112
A42: Sales | B42: 15567 | C42: 15210 | D42: 15707 | E42: 15926 | F42: 15556 | G42: 15190 | H42: 16514 | I42: 15919 | J42: 16441 | K42: 16351
A43: Expenses | B43: 11902 | C43: 11675 | D43: 11965 | E43: 12139 | F43: 11867 | G43: 11572 | H43: 12797 | I43: 12137 | J43: 12660 | K43: 12514
A44: Other Income | B44: 184 | C44: 309 | D44: 209 | E44: 203 | F44: 733 | G44: 149 | H44: 74 | I44: 269 | J44: 4048 | K44: 503
A45: Depreciation | B45: 313 | C45: 320 | D45: 329 | E45: 338 | F45: 318 | G45: 318 | H45: 361 | I45: 322 | J45: 337 | K45: 348
A46: Interest | B46: 91 | C46: 105 | D46: 93 | E46: 110 | F46: 109 | G46: 77 | H46: 127 | I46: 124 | J46: 88 | K46: 76
A47: Profit before tax | B47: 3445 | C47: 3419 | D47: 3529 | E47: 3542 | F47: 3995 | G47: 3372 | H47: 3303 | I47: 3605 | J47: 7404 | K47: 3916
A48: Tax | B48: 937 | C48: 858 | D48: 917 | E48: 947 | F48: 1006 | G48: 897 | H48: 535 | I48: 911 | J48: 801 | K48: 922
A49: Net profit | B49: 2509 | C49: 2558 | D49: 2610 | E49: 2591 | F49: 2984 | G49: 2464 | H49: 2756 | I49: 2685 | J49: 6607 | K49: 2992
A50: Operating Profit | B50: 3665 | C50: 3535 | D50: 3742 | E50: 3787 | F50: 3689 | G50: 3618 | H50: 3717 | I50: 3782 | J50: 3781 | K50: 3837
A55: BALANCE SHEET
A56: Report Date | B56: 42825 | C56: 43190 | D56: 43555 | E56: 43921 | F56: 44286 | G56: 44651 | H56: 45016 | I56: 45382 | J56: 45747 | K56: 46112
A57: Equity Share Capital | B57: 216 | C57: 216 | D57: 216 | E57: 216 | F57: 235 | G57: 235 | H57: 235 | I57: 235 | J57: 235 | K57: 235
A58: Reserves | B58: 6528 | C58: 7065 | D58: 7651 | E58: 8013 | F58: 47439 | G58: 48826 | H58: 50069 | I58: 50983 | J58: 49167 | K58: 48504
A59: Borrowings | B59: 277 | D59: 99 | G59: 1043 | H59: 1219 | I59: 1484 | J59: 1648 | K59: 1478
A60: Other Liabilities | B60: 8685 | C60: 10581 | D60: 10663 | E60: 11924 | F60: 21066 | G60: 20402 | H60: 21554 | I60: 25787 | J60: 28813 | K60: 29521
A61: Total | B61: 15706 | C61: 17862 | D61: 18629 | E61: 20153 | F61: 68740 | G61: 70506 | H61: 73077 | I61: 78489 | J61: 79863 | K61: 79738
A62: Net Block | B62: 4419 | C62: 4528 | D62: 4715 | E62: 5479 | F62: 51443 | G62: 51473 | H62: 52678 | I62: 53744 | J62: 54335 | K62: 57428
A63: Capital Work in Progress | B63: 229 | C63: 461 | D63: 406 | E63: 597 | F63: 745 | G63: 1313 | H63: 1132 | I63: 1025 | J63: 1009 | K63: 880
A64: Investments | B64: 3794 | C64: 2873 | D64: 2716 | E64: 1255 | F64: 2709 | G64: 3521 | H64: 2882 | I64: 4625 | J64: 3810 | K64: 4359
A65: Other Assets | B65: 7264 | C65: 10000 | D65: 10792 | E65: 12822 | F65: 13843 | G65: 14199 | H65: 16385 | I65: 19095 | J65: 20709 | K65: 17071
A66: Total | B66: 15706 | C66: 17862 | D66: 18629 | E66: 20153 | F66: 68740 | G66: 70506 | H66: 73077 | I66: 78489 | J66: 79863 | K66: 79738
A67: Receivables | B67: 1085 | C67: 1310 | D67: 1816 | E67: 1149 | F67: 1758 | G67: 2236 | H67: 3079 | I67: 2997 | J67: 3819 | K67: 3379
A68: Inventory | B68: 2541 | C68: 2513 | D68: 2574 | E68: 2767 | F68: 3579 | G68: 4096 | H68: 4251 | I68: 4022 | J68: 4415 | K68: 4789
A69: Cash & Bank | B69: 1828 | C69: 3485 | D69: 3757 | E69: 5113 | F69: 4471 | G69: 3846 | H69: 4678 | I69: 7559 | J69: 7554 | K69: 3248
A70: No. of Equity Shares | B70: 2164349639 | C70: 2164528777 | D70: 2164704405 | E70: 2164704405 | F70: 2349567819 | G70: 2349591262 | H70: 2349591262 | I70: 2349591262 | J70: 2349591262 | K70: 2349591262
A71: New Bonus Shares
A72: Face value | B72: 1 | C72: 1 | D72: 1 | E72: 1 | F72: 1 | G72: 1 | H72: 1 | I72: 1 | J72: 1 | K72: 1
A80: CASH FLOW:
A81: Report Date | B81: 42825 | C81: 43190 | D81: 43555 | E81: 43921 | F81: 44286 | G81: 44651 | H81: 45016 | I81: 45382 | J81: 45747 | K81: 46112
A82: Cash from Operating Activity | B82: 5185 | C82: 6059 | D82: 5800 | E82: 7623 | F82: 9163 | G82: 9048 | H82: 9991 | I82: 15469 | J82: 11886 | K82: 10999
A83: Cash from Investing Activity | B83: -1173 | C83: -1063 | D83: -438 | E83: 1791 | F83: -1228 | G83: -1728 | H83: -1484 | I83: -5324 | J83: 6473 | K83: -3676
A84: Cash from Financing Activity | B84: -4214 | C84: -4975 | D84: -5390 | E84: -6819 | F84: -9309 | G84: -8015 | H84: -8953 | I84: -10034 | J84: -13101 | K84: -10810
A85: Net Cash Flow | B85: -202 | C85: 21 | D85: -28 | E85: 2595 | F85: -1374 | G85: -695 | H85: -446 | I85: 111 | J85: 5258 | K85: -3487
A90: PRICE: | B90: 872.61 | C90: 1276.11 | D90: 1633.53 | E90: 2199.83 | F90: 2327.12 | G90: 1960.7 | H90: 2450.44 | I90: 2167.14 | J90: 2161.88 | K90: 2055.2
A92: DERIVED:
A93: Adjusted Equity Shares in Cr | B93: 216.43 | C93: 216.45 | D93: 216.47 | E93: 216.48 | F93: 234.96 | G93: 234.96 | H93: 234.96 | I93: 234.96 | J93: 234.96 | K93: 234.96

Sheet Profit & Loss
A1: ='Data Sheet'!B1 -> HINDUSTAN UNILEVER LTD | H1: =UPDATE | M1: SCREENER.IN
A3: Narration | B3: ='Data Sheet'!B16 -> 42825 | C3: ='Data Sheet'!C16 -> 43190 | D3: ='Data Sheet'!D16 -> 43555 | E3: ='Data Sheet'!E16 -> 43921 | F3: ='Data Sheet'!F16 -> 44286 | G3: ='Data Sheet'!G16 -> 44651 | H3: ='Data Sheet'!H16 -> 45016 | I3: ='Data Sheet'!I16 -> 45382 | ... K3: ='Data Sheet'!K16 -> 46112 | L3: Trailing | M3: Best Case | N3: Worst Case
A4: Sales | B4: ='Data Sheet'!B17 -> 33162 | C4: ='Data Sheet'!C17 -> 35545 | D4: ='Data Sheet'!D17 -> 39310 | E4: ='Data Sheet'!E17 -> 39783 | F4: ='Data Sheet'!F17 -> 47028 | G4: ='Data Sheet'!G17 -> 52446 | H4: ='Data Sheet'!H17 -> 60580 | I4: ='Data Sheet'!I17 -> 61896 | ... K4: ='Data Sheet'!K17 -> 64468 | L4: =SUM(Quarters!H4:K4) -> 65225 | M4: =$K4+M23*K4 -> 67768.768 | N4: =$K4+N23*L4 -> 65834.541
A5: Expenses | B5: =SUM('Data Sheet'!B18,'Data Sheet'!B20:B24, -1*'Data Sheet'!B19) -> 26834 | C5: =SUM('Data Sheet'!C18,'Data Sheet'!C20:C24, -1*'Data Sheet'!C19) -> 28046 | D5: =SUM('Data Sheet'!D18,'Data Sheet'!D20:D24, -1*'Data Sheet'!D19) -> 30430 | E5: =SUM('Data Sheet'!E18,'Data Sheet'!E20:E24, -1*'Data Sheet'!E19) -> 29922 | F5: =SUM('Data Sheet'!F18,'Data Sheet'!F20:F24, -1*'Data Sheet'!F19) -> 35402 | G5: =SUM('Data Sheet'!G18,'Data Sheet'!G20:G24, -1*'Data Sheet'!G19) -> 39589 | H5: =SUM('Data Sheet'!H18,'Data Sheet'!H20:H24, -1*'Data Sheet'!H19) -> 46433 | I5: =SUM('Data Sheet'!I18,'Data Sheet'!I20:I24, -1*'Data Sheet'!I19) -> 47237 | ... K5: =SUM('Data Sheet'!K18,'Data Sheet'!K20:K24, -1*'Data Sheet'!K19) -> 49429 | L5: =SUM(Quarters!H5:K5) -> 50108 | M5: =M4-M6 -> 51738.984 | N5: =N4-N6 -> 50576.269
A6: Operating Profit | B6: =B4-B5 -> 6328 | C6: =C4-C5 -> 7499 | D6: =D4-D5 -> 8880 | E6: =E4-E5 -> 9861 | F6: =F4-F5 -> 11626 | G6: =G4-G5 -> 12857 | H6: =H4-H5 -> 14147 | I6: =I4-I5 -> 14659 | ... K6: =K4-K5 -> 15039 | L6: =SUM(Quarters!H6:K6) -> 15117 | M6: =M4*M24 -> 16029.784 | N6: =N4*N24 -> 15258.271
A7: Other Income | B7: ='Data Sheet'!B25 -> 606 | C7: ='Data Sheet'!C25 -> 353 | D7: ='Data Sheet'!D25 -> 322 | E7: ='Data Sheet'!E25 -> 424 | F7: ='Data Sheet'!F25 -> 170 | G7: ='Data Sheet'!G25 -> 219 | H7: ='Data Sheet'!H25 -> 448 | I7: ='Data Sheet'!I25 -> 817 | ... K7: ='Data Sheet'!K25 -> 4923 | L7: =SUM(Quarters!H7:K7) -> 4894 | M7: 0 | N7: 0
A8: Depreciation | B8: ='Data Sheet'!B26 -> 432 | C8: ='Data Sheet'!C26 -> 520 | D8: ='Data Sheet'!D26 -> 565 | E8: ='Data Sheet'!E26 -> 1002 | F8: ='Data Sheet'!F26 -> 1074 | G8: ='Data Sheet'!G26 -> 1091 | H8: ='Data Sheet'!H26 -> 1137 | I8: ='Data Sheet'!I26 -> 1216 | ... K8: ='Data Sheet'!K26 -> 1333 | L8: =SUM(Quarters!H8:K8) -> 1368 | M8: =+$L8 -> 1368 | N8: =+$L8 -> 1368
A9: Interest | B9: ='Data Sheet'!B27 -> 35 | C9: ='Data Sheet'!C27 -> 26 | D9: ='Data Sheet'!D27 -> 33 | E9: ='Data Sheet'!E27 -> 118 | F9: ='Data Sheet'!F27 -> 117 | G9: ='Data Sheet'!G27 -> 106 | H9: ='Data Sheet'!H27 -> 114 | I9: ='Data Sheet'!I27 -> 334 | ... K9: ='Data Sheet'!K27 -> 410 | L9: =SUM(Quarters!H9:K9) -> 415 | M9: =+$L9 -> 415 | N9: =+$L9 -> 415
A10: Profit before tax | B10: ='Data Sheet'!B28 -> 6467 | C10: ='Data Sheet'!C28 -> 7306 | D10: ='Data Sheet'!D28 -> 8604 | E10: ='Data Sheet'!E28 -> 9165 | F10: ='Data Sheet'!F28 -> 10605 | G10: ='Data Sheet'!G28 -> 11879 | H10: ='Data Sheet'!H28 -> 13344 | I10: ='Data Sheet'!I28 -> 13926 | ... K10: ='Data Sheet'!K28 -> 18219 | L10: =SUM(Quarters!H10:K10) -> 18228 | M10: =M6+M7-SUM(M8:M9) -> 14246.784 | N10: =N6+N7-SUM(N8:N9) -> 13475.271
A11: Tax | B11: ='Data Sheet'!B29 -> 1977 | C11: ='Data Sheet'!C29 -> 2079 | D11: ='Data Sheet'!D29 -> 2544 | E11: ='Data Sheet'!E29 -> 2409 | F11: ='Data Sheet'!F29 -> 2606 | G11: ='Data Sheet'!G29 -> 2987 | H11: ='Data Sheet'!H29 -> 3201 | I11: ='Data Sheet'!I29 -> 3644 | ... K11: ='Data Sheet'!K29 -> 3160 | L11: =SUM(Quarters!H11:K11) -> 3169 | M11: =IF($L10>0,$L11/$L10,0) -> 0.17385341 | N11: =IF($L10>0,$L11/$L10,0) -> 0.17385341
A12: Net profit | B12: ='Data Sheet'!B30 -> 4476 | C12: ='Data Sheet'!C30 -> 5214 | D12: ='Data Sheet'!D30 -> 6054 | E12: ='Data Sheet'!E30 -> 6748 | F12: ='Data Sheet'!F30 -> 7995 | G12: ='Data Sheet'!G30 -> 8879 | H12: ='Data Sheet'!H30 -> 10120 | I12: ='Data Sheet'!I30 -> 10277 | ... K12: ='Data Sheet'!K30 -> 15040 | L12: =SUM(Quarters!H12:K12) -> 15040 | M12: =M10-M11*M10 -> 11769.932 | N12: =N10-N11*N10 -> 11132.55
A13: EPS | B13: =IF('Data Sheet'!B93>0,B12/'Data Sheet'!B93,0) -> 20.681052 | C13: =IF('Data Sheet'!C93>0,C12/'Data Sheet'!C93,0) -> 24.088704 | D13: =IF('Data Sheet'!D93>0,D12/'Data Sheet'!D93,0) -> 27.966924 | E13: =IF('Data Sheet'!E93>0,E12/'Data Sheet'!E93,0) -> 31.171471 | F13: =IF('Data Sheet'!F93>0,F12/'Data Sheet'!F93,0) -> 34.027068 | G13: =IF('Data Sheet'!G93>0,G12/'Data Sheet'!G93,0) -> 37.789411 | H13: =IF('Data Sheet'!H93>0,H12/'Data Sheet'!H93,0) -> 43.071161 | I13: =IF('Data Sheet'!I93>0,I12/'Data Sheet'!I93,0) -> 43.73936 | ... K13: =IF('Data Sheet'!K93>0,K12/'Data Sheet'!K93,0) -> 64.010895 | L13: =IF('Data Sheet'!$B6>0,'Profit & Loss'!L12/'Data Sheet'!$B6,0) -> 64.011134 | M13: =IF('Data Sheet'!$B6>0,'Profit & Loss'!M12/'Data Sheet'!$B6,0) -> 50.093531 | N13: =IF('Data Sheet'!$B6>0,'Profit & Loss'!N12/'Data Sheet'!$B6,0) -> 47.380793
A14: Price to earning | B14: =IF(B15>0,B15/B13,"") -> 42.193696 | C14: =IF(C15>0,C15/C13,"") -> 52.975453 | D14: =IF(D15>0,D15/D13,"") -> 58.409356 | E14: =IF(E15>0,E15/E13,"") -> 70.571903 | F14: =IF(F15>0,F15/F13,"") -> 68.390258 | G14: =IF(G15>0,G15/G13,"") -> 51.884905 | H14: =IF(H15>0,H15/H13,"") -> 56.892824 | I14: =IF(I15>0,I15/I13,"") -> 49.546678 | ... K14: =IF(K15>0,K15/K13,"") -> 32.107034 | L14: =IF(L13>0,L15/L13,0) -> 33.491049 | M14: =M25 -> 40.711144 | N14: =N25 -> 33.491049
A15: Price | B15: ='Data Sheet'!B90 -> 872.61 | C15: ='Data Sheet'!C90 -> 1276.11 | D15: ='Data Sheet'!D90 -> 1633.53 | E15: ='Data Sheet'!E90 -> 2199.83 | F15: ='Data Sheet'!F90 -> 2327.12 | G15: ='Data Sheet'!G90 -> 1960.7 | H15: ='Data Sheet'!H90 -> 2450.44 | I15: ='Data Sheet'!I90 -> 2167.14 | ... K15: ='Data Sheet'!K90 -> 2055.2 | L15: ='Data Sheet'!B8 -> 2143.8 | M15: =M13*M14 -> 2039.3649 | N15: =N13*N14 -> 1586.8324
A17: RATIOS:
A18: Dividend Payout | B18: =IF('Data Sheet'!B30>0, 'Data Sheet'!B31/'Data Sheet'!B30, 0) -> 0.82037534 | C18: =IF('Data Sheet'!C30>0, 'Data Sheet'!C31/'Data Sheet'!C30, 0) -> 0.82853855 | D18: =IF('Data Sheet'!D30>0, 'Data Sheet'!D31/'Data Sheet'!D30, 0) -> 0.78493558 | E18: =IF('Data Sheet'!E30>0, 'Data Sheet'!E31/'Data Sheet'!E30, 0) -> 0.80023711 | F18: =IF('Data Sheet'!F30>0, 'Data Sheet'!F31/'Data Sheet'!F30, 0) -> 1.1904315 | G18: =IF('Data Sheet'!G30>0, 'Data Sheet'!G31/'Data Sheet'!G30, 0) -> 0.89987611 | H18: =IF('Data Sheet'!H30>0, 'Data Sheet'!H31/'Data Sheet'!H30, 0) -> 0.90563241 | I18: =IF('Data Sheet'!I30>0, 'Data Sheet'!I31/'Data Sheet'!I30, 0) -> 0.960397 | ... K18: =IF('Data Sheet'!K30>0, 'Data Sheet'!K31/'Data Sheet'!K30, 0) -> 0.640625
A19: OPM | B19: =IF(B6>0,B6/B4,0) -> 0.19082082 | C19: =IF(C6>0,C6/C4,0) -> 0.21097201 | D19: =IF(D6>0,D6/D4,0) -> 0.22589672 | E19: =IF(E6>0,E6/E4,0) -> 0.24786969 | F19: =IF(F6>0,F6/F4,0) -> 0.24721443 | G19: =IF(G6>0,G6/G4,0) -> 0.24514739 | H19: =IF(H6>0,H6/H4,0) -> 0.23352592 | I19: =IF(I6>0,I6/I4,0) -> 0.23683275 | ... L19: =IF(L6>0,L6/L4,0) -> 0.23176696
G22: TRENDS: | H22: 10 YEARS | I22: 7 YEARS | J22: 5 YEARS | K22: 3 YEARS | L22: RECENT | M22: BEST | N22: WORST
G23: Sales Growth | H23: =IF(B4=0,"",POWER($K4/B4,1/9)-1) -> 0.076658974 | I23: =IF(D4=0,"",POWER($K4/D4,1/7)-1) -> 0.073227008 | J23: =IF(F4=0,"",POWER($K4/F4,1/5)-1) -> 0.065117542 | K23: =IF(H4=0,"",POWER($K4/H4, 1/3)-1) -> 0.020951182 | L23: =IF(ISERROR(MAX(IF(J4=0,"",(K4-J4)/J4),IF(K4=0,"",(L4-K4)/K4))),"",MAX(IF(J4=0,"",(K4-J4)/J4),IF(K4=0,"",(L4-K4)/K4))) -> 0.051200104 | M23: =MAX(K23:L23) -> 0.051200104 | N23: =MIN(H23:L23) -> 0.020951182
G24: OPM | H24: =IF(SUM(B4:$K$4)=0,"",SUMPRODUCT(B19:$K$19,B4:$K$4)/SUM(B4:$K$4)) -> 0.23326593 | I24: =IF(SUM(E4:$K$4)=0,"",SUMPRODUCT(E19:$K$19,E4:$K$4)/SUM(E4:$K$4)) -> 0.23969045 | J24: =IF(SUM(G4:$K$4)=0,"",SUMPRODUCT(G19:$K$19,G4:$K$4)/SUM(G4:$K$4)) -> 0.23743175 | K24: =IF(SUM(I4:$K$4)=0, "", SUMPRODUCT(I19:$K$19,I4:$K$4)/SUM(I4:$K$4)) -> 0.23653645 | L24: =L19 -> 0.23176696 | M24: =MAX(K24:L24) -> 0.23653645 | N24: =MIN(H24:L24) -> 0.23176696
G25: Price to Earning | H25: =IF(ISERROR(AVERAGEIF(B14:$L14,">0")),"",AVERAGEIF(B14:$L14,">0")) -> 51.287543 | I25: =IF(ISERROR(AVERAGEIF(E14:$L14,">0")),"",AVERAGEIF(E14:$L14,">0")) -> 51.323058 | J25: =IF(ISERROR(AVERAGEIF(G14:$L14,">0")),"",AVERAGEIF(G14:$L14,">0")) -> 45.270384 | K25: =IF(ISERROR(AVERAGEIF(I14:$L14,">0")),"",AVERAGEIF(I14:$L14,">0")) -> 40.711144 | L25: =L14 -> 33.491049 | M25: =MAX(K25:L25) -> 40.711144 | N25: =MIN(H25:L25) -> 33.491049

Sheet Quarters
A1: ='Profit & Loss'!A1 -> HINDUSTAN UNILEVER LTD | E1: =UPDATE | J1: SCREENER.IN
A3: Narration | B3: ='Data Sheet'!B41 -> 45291 | C3: ='Data Sheet'!C41 -> 45382 | D3: ='Data Sheet'!D41 -> 45473 | E3: ='Data Sheet'!E41 -> 45565 | F3: ='Data Sheet'!F41 -> 45657 | G3: ='Data Sheet'!G41 -> 45747 | H3: ='Data Sheet'!H41 -> 45838 | I3: ='Data Sheet'!I41 -> 45930 | ... K3: ='Data Sheet'!K41 -> 46112
A4: Sales | B4: ='Data Sheet'!B42 -> 15567 | C4: ='Data Sheet'!C42 -> 15210 | D4: ='Data Sheet'!D42 -> 15707 | E4: ='Data Sheet'!E42 -> 15926 | F4: ='Data Sheet'!F42 -> 15556 | G4: ='Data Sheet'!G42 -> 15190 | H4: ='Data Sheet'!H42 -> 16514 | I4: ='Data Sheet'!I42 -> 15919 | ... K4: ='Data Sheet'!K42 -> 16351
A5: Expenses | B5: ='Data Sheet'!B43 -> 11902 | C5: ='Data Sheet'!C43 -> 11675 | D5: ='Data Sheet'!D43 -> 11965 | E5: ='Data Sheet'!E43 -> 12139 | F5: ='Data Sheet'!F43 -> 11867 | G5: ='Data Sheet'!G43 -> 11572 | H5: ='Data Sheet'!H43 -> 12797 | I5: ='Data Sheet'!I43 -> 12137 | ... K5: ='Data Sheet'!K43 -> 12514
A6: Operating Profit | B6: ='Data Sheet'!B50 -> 3665 | C6: ='Data Sheet'!C50 -> 3535 | D6: ='Data Sheet'!D50 -> 3742 | E6: ='Data Sheet'!E50 -> 3787 | F6: ='Data Sheet'!F50 -> 3689 | G6: ='Data Sheet'!G50 -> 3618 | H6: ='Data Sheet'!H50 -> 3717 | I6: ='Data Sheet'!I50 -> 3782 | ... K6: ='Data Sheet'!K50 -> 3837
A7: Other Income | B7: ='Data Sheet'!B44 -> 184 | C7: ='Data Sheet'!C44 -> 309 | D7: ='Data Sheet'!D44 -> 209 | E7: ='Data Sheet'!E44 -> 203 | F7: ='Data Sheet'!F44 -> 733 | G7: ='Data Sheet'!G44 -> 149 | H7: ='Data Sheet'!H44 -> 74 | I7: ='Data Sheet'!I44 -> 269 | ... K7: ='Data Sheet'!K44 -> 503
A8: Depreciation | B8: ='Data Sheet'!B45 -> 313 | C8: ='Data Sheet'!C45 -> 320 | D8: ='Data Sheet'!D45 -> 329 | E8: ='Data Sheet'!E45 -> 338 | F8: ='Data Sheet'!F45 -> 318 | G8: ='Data Sheet'!G45 -> 318 | H8: ='Data Sheet'!H45 -> 361 | I8: ='Data Sheet'!I45 -> 322 | ... K8: ='Data Sheet'!K45 -> 348
A9: Interest | B9: ='Data Sheet'!B46 -> 91 | C9: ='Data Sheet'!C46 -> 105 | D9: ='Data Sheet'!D46 -> 93 | E9: ='Data Sheet'!E46 -> 110 | F9: ='Data Sheet'!F46 -> 109 | G9: ='Data Sheet'!G46 -> 77 | H9: ='Data Sheet'!H46 -> 127 | I9: ='Data Sheet'!I46 -> 124 | ... K9: ='Data Sheet'!K46 -> 76
A10: Profit before tax | B10: ='Data Sheet'!B47 -> 3445 | C10: ='Data Sheet'!C47 -> 3419 | D10: ='Data Sheet'!D47 -> 3529 | E10: ='Data Sheet'!E47 -> 3542 | F10: ='Data Sheet'!F47 -> 3995 | G10: ='Data Sheet'!G47 -> 3372 | H10: ='Data Sheet'!H47 -> 3303 | I10: ='Data Sheet'!I47 -> 3605 | ... K10: ='Data Sheet'!K47 -> 3916
A11: Tax | B11: ='Data Sheet'!B48 -> 937 | C11: ='Data Sheet'!C48 -> 858 | D11: ='Data Sheet'!D48 -> 917 | E11: ='Data Sheet'!E48 -> 947 | F11: ='Data Sheet'!F48 -> 1006 | G11: ='Data Sheet'!G48 -> 897 | H11: ='Data Sheet'!H48 -> 535 | I11: ='Data Sheet'!I48 -> 911 | ... K11: ='Data Sheet'!K48 -> 922
A12: Net profit | B12: ='Data Sheet'!B49 -> 2509 | C12: ='Data Sheet'!C49 -> 2558 | D12: ='Data Sheet'!D49 -> 2610 | E12: ='Data Sheet'!E49 -> 2591 | F12: ='Data Sheet'!F49 -> 2984 | G12: ='Data Sheet'!G49 -> 2464 | H12: ='Data Sheet'!H49 -> 2756 | I12: ='Data Sheet'!I49 -> 2685 | ... K12: ='Data Sheet'!K49 -> 2992
A14: OPM | B14: =IF(B4>0,B6/B4,"") -> 0.23543393 | C14: =IF(C4>0,C6/C4,"") -> 0.23241289 | D14: =IF(D4>0,D6/D4,"") -> 0.23823773 | E14: =IF(E4>0,E6/E4,"") -> 0.23778727 | F14: =IF(F4>0,F6/F4,"") -> 0.23714322 | G14: =IF(G4>0,G6/G4,"") -> 0.23818302 | H14: =IF(H4>0,H6/H4,"") -> 0.22508175 | I14: =IF(I4>0,I6/I4,"") -> 0.23757774 | ... K14: =IF(K4>0,K6/K4,"") -> 0.23466455

Sheet Balance Sheet
A1: ='Profit & Loss'!A1 -> HINDUSTAN UNILEVER LTD | E1: =UPDATE | J1: SCREENER.IN
A3: Narration | B3: ='Data Sheet'!B56 -> 42825 | C3: ='Data Sheet'!C56 -> 43190 | D3: ='Data Sheet'!D56 -> 43555 | E3: ='Data Sheet'!E56 -> 43921 | F3: ='Data Sheet'!F56 -> 44286 | G3: ='Data Sheet'!G56 -> 44651 | H3: ='Data Sheet'!H56 -> 45016 | I3: ='Data Sheet'!I56 -> 45382 | ... K3: ='Data Sheet'!K56 -> 46112
A4: Equity Share Capital | B4: ='Data Sheet'!B57 -> 216 | C4: ='Data Sheet'!C57 -> 216 | D4: ='Data Sheet'!D57 -> 216 | E4: ='Data Sheet'!E57 -> 216 | F4: ='Data Sheet'!F57 -> 235 | G4: ='Data Sheet'!G57 -> 235 | H4: ='Data Sheet'!H57 -> 235 | I4: ='Data Sheet'!I57 -> 235 | ... K4: ='Data Sheet'!K57 -> 235
A5: Reserves | B5: ='Data Sheet'!B58 -> 6528 | C5: ='Data Sheet'!C58 -> 7065 | D5: ='Data Sheet'!D58 -> 7651 | E5: ='Data Sheet'!E58 -> 8013 | F5: ='Data Sheet'!F58 -> 47439 | G5: ='Data Sheet'!G58 -> 48826 | H5: ='Data Sheet'!H58 -> 50069 | I5: ='Data Sheet'!I58 -> 50983 | ... K5: ='Data Sheet'!K58 -> 48504
A6: Borrowings | B6: ='Data Sheet'!B59 -> 277 | C6: ='Data Sheet'!C59 -> 0 | D6: ='Data Sheet'!D59 -> 99 | E6: ='Data Sheet'!E59 -> 0 | F6: ='Data Sheet'!F59 -> 0 | G6: ='Data Sheet'!G59 -> 1043 | H6: ='Data Sheet'!H59 -> 1219 | I6: ='Data Sheet'!I59 -> 1484 | ... K6: ='Data Sheet'!K59 -> 1478
A7: Other Liabilities | B7: ='Data Sheet'!B60 -> 8685 | C7: ='Data Sheet'!C60 -> 10581 | D7: ='Data Sheet'!D60 -> 10663 | E7: ='Data Sheet'!E60 -> 11924 | F7: ='Data Sheet'!F60 -> 21066 | G7: ='Data Sheet'!G60 -> 20402 | H7: ='Data Sheet'!H60 -> 21554 | I7: ='Data Sheet'!I60 -> 25787 | ... K7: ='Data Sheet'!K60 -> 29521
A8: Total | B8: ='Data Sheet'!B61 -> 15706 | C8: ='Data Sheet'!C61 -> 17862 | D8: ='Data Sheet'!D61 -> 18629 | E8: ='Data Sheet'!E61 -> 20153 | F8: ='Data Sheet'!F61 -> 68740 | G8: ='Data Sheet'!G61 -> 70506 | H8: ='Data Sheet'!H61 -> 73077 | I8: ='Data Sheet'!I61 -> 78489 | ... K8: ='Data Sheet'!K61 -> 79738
A10: Net Block | B10: ='Data Sheet'!B62 -> 4419 | C10: ='Data Sheet'!C62 -> 4528 | D10: ='Data Sheet'!D62 -> 4715 | E10: ='Data Sheet'!E62 -> 5479 | F10: ='Data Sheet'!F62 -> 51443 | G10: ='Data Sheet'!G62 -> 51473 | H10: ='Data Sheet'!H62 -> 52678 | I10: ='Data Sheet'!I62 -> 53744 | ... K10: ='Data Sheet'!K62 -> 57428
A11: Capital Work in Progress | B11: ='Data Sheet'!B63 -> 229 | C11: ='Data Sheet'!C63 -> 461 | D11: ='Data Sheet'!D63 -> 406 | E11: ='Data Sheet'!E63 -> 597 | F11: ='Data Sheet'!F63 -> 745 | G11: ='Data Sheet'!G63 -> 1313 | H11: ='Data Sheet'!H63 -> 1132 | I11: ='Data Sheet'!I63 -> 1025 | ... K11: ='Data Sheet'!K63 -> 880
A12: Investments | B12: ='Data Sheet'!B64 -> 3794 | C12: ='Data Sheet'!C64 -> 2873 | D12: ='Data Sheet'!D64 -> 2716 | E12: ='Data Sheet'!E64 -> 1255 | F12: ='Data Sheet'!F64 -> 2709 | G12: ='Data Sheet'!G64 -> 3521 | H12: ='Data Sheet'!H64 -> 2882 | I12: ='Data Sheet'!I64 -> 4625 | ... K12: ='Data Sheet'!K64 -> 4359
A13: Other Assets | B13: ='Data Sheet'!B65 -> 7264 | C13: ='Data Sheet'!C65 -> 10000 | D13: ='Data Sheet'!D65 -> 10792 | E13: ='Data Sheet'!E65 -> 12822 | F13: ='Data Sheet'!F65 -> 13843 | G13: ='Data Sheet'!G65 -> 14199 | H13: ='Data Sheet'!H65 -> 16385 | I13: ='Data Sheet'!I65 -> 19095 | ... K13: ='Data Sheet'!K65 -> 17071
A14: Total | B14: ='Data Sheet'!B66 -> 15706 | C14: ='Data Sheet'!C66 -> 17862 | D14: ='Data Sheet'!D66 -> 18629 | E14: ='Data Sheet'!E66 -> 20153 | F14: ='Data Sheet'!F66 -> 68740 | G14: ='Data Sheet'!G66 -> 70506 | H14: ='Data Sheet'!H66 -> 73077 | I14: ='Data Sheet'!I66 -> 78489 | ... K14: ='Data Sheet'!K66 -> 79738
A16: Working Capital | B16: =B13-B7 -> -1421 | C16: =C13-C7 -> -581 | D16: =D13-D7 -> 129 | E16: =E13-E7 -> 898 | F16: =F13-F7 -> -7223 | G16: =G13-G7 -> -6203 | H16: =H13-H7 -> -5169 | I16: =I13-I7 -> -6692 | ... K16: =K13-K7 -> -12450
A17: Debtors | B17: ='Data Sheet'!B67 -> 1085 | C17: ='Data Sheet'!C67 -> 1310 | D17: ='Data Sheet'!D67 -> 1816 | E17: ='Data Sheet'!E67 -> 1149 | F17: ='Data Sheet'!F67 -> 1758 | G17: ='Data Sheet'!G67 -> 2236 | H17: ='Data Sheet'!H67 -> 3079 | I17: ='Data Sheet'!I67 -> 2997 | ... K17: ='Data Sheet'!K67 -> 3379
A18: Inventory | B18: ='Data Sheet'!B68 -> 2541 | C18: ='Data Sheet'!C68 -> 2513 | D18: ='Data Sheet'!D68 -> 2574 | E18: ='Data Sheet'!E68 -> 2767 | F18: ='Data Sheet'!F68 -> 3579 | G18: ='Data Sheet'!G68 -> 4096 | H18: ='Data Sheet'!H68 -> 4251 | I18: ='Data Sheet'!I68 -> 4022 | ... K18: ='Data Sheet'!K68 -> 4789
A20: Debtor Days | B20: =IF('Profit & Loss'!B4>0,'Balance Sheet'!B17/('Profit & Loss'!B4/365),0) -> 11.942133 | C20: =IF('Profit & Loss'!C4>0,'Balance Sheet'!C17/('Profit & Loss'!C4/365),0) -> 13.451962 | D20: =IF('Profit & Loss'!D4>0,'Balance Sheet'!D17/('Profit & Loss'!D4/365),0) -> 16.861867 | E20: =IF('Profit & Loss'!E4>0,'Balance Sheet'!E17/('Profit & Loss'!E4/365),0) -> 10.541814 | F20: =IF('Profit & Loss'!F4>0,'Balance Sheet'!F17/('Profit & Loss'!F4/365),0) -> 13.644425 | G20: =IF('Profit & Loss'!G4>0,'Balance Sheet'!G17/('Profit & Loss'!G4/365),0) -> 15.56153 | H20: =IF('Profit & Loss'!H4>0,'Balance Sheet'!H17/('Profit & Loss'!H4/365),0) -> 18.551255 | I20: =IF('Profit & Loss'!I4>0,'Balance Sheet'!I17/('Profit & Loss'!I4/365),0) -> 17.673275 | ... K20: =IF('Profit & Loss'!K4>0,'Balance Sheet'!K17/('Profit & Loss'!K4/365),0) -> 19.130964
A21: Inventory Turnover | B21: =IF('Balance Sheet'!B18>0,'Profit & Loss'!B4/'Balance Sheet'!B18,0) -> 13.050767 | C21: =IF('Balance Sheet'!C18>0,'Profit & Loss'!C4/'Balance Sheet'!C18,0) -> 14.144449 | D21: =IF('Balance Sheet'!D18>0,'Profit & Loss'!D4/'Balance Sheet'!D18,0) -> 15.27195 | E21: =IF('Balance Sheet'!E18>0,'Profit & Loss'!E4/'Balance Sheet'!E18,0) -> 14.377665 | F21: =IF('Balance Sheet'!F18>0,'Profit & Loss'!F4/'Balance Sheet'!F18,0) -> 13.139983 | G21: =IF('Balance Sheet'!G18>0,'Profit & Loss'!G4/'Balance Sheet'!G18,0) -> 12.804199 | H21: =IF('Balance Sheet'!H18>0,'Profit & Loss'!H4/'Balance Sheet'!H18,0) -> 14.250765 | I21: =IF('Balance Sheet'!I18>0,'Profit & Loss'!I4/'Balance Sheet'!I18,0) -> 15.389359 | ... K21: =IF('Balance Sheet'!K18>0,'Profit & Loss'!K4/'Balance Sheet'!K18,0) -> 13.461683
A23: Return on Equity | B23: =IF(SUM('Balance Sheet'!B4:B5)>0,'Profit & Loss'!B12/SUM('Balance Sheet'!B4:B5),"") -> 0.66370107 | C23: =IF(SUM('Balance Sheet'!C4:C5)>0,'Profit & Loss'!C12/SUM('Balance Sheet'!C4:C5),"") -> 0.71611042 | D23: =IF(SUM('Balance Sheet'!D4:D5)>0,'Profit & Loss'!D12/SUM('Balance Sheet'!D4:D5),"") -> 0.76954366 | E23: =IF(SUM('Balance Sheet'!E4:E5)>0,'Profit & Loss'!E12/SUM('Balance Sheet'!E4:E5),"") -> 0.82002673 | F23: =IF(SUM('Balance Sheet'!F4:F5)>0,'Profit & Loss'!F12/SUM('Balance Sheet'!F4:F5),"") -> 0.16770147 | G23: =IF(SUM('Balance Sheet'!G4:G5)>0,'Profit & Loss'!G12/SUM('Balance Sheet'!G4:G5),"") -> 0.18097878 | H23: =IF(SUM('Balance Sheet'!H4:H5)>0,'Profit & Loss'!H12/SUM('Balance Sheet'!H4:H5),"") -> 0.20117684 | I23: =IF(SUM('Balance Sheet'!I4:I5)>0,'Profit & Loss'!I12/SUM('Balance Sheet'!I4:I5),"") -> 0.20065211 | ... K23: =IF(SUM('Balance Sheet'!K4:K5)>0,'Profit & Loss'!K12/SUM('Balance Sheet'!K4:K5),"") -> 0.30858245
A24: Return on Capital Emp | C24: =IF((B4+B5+B6+C4+C5+C6)>0,('Profit & Loss'!C10+'Profit & Loss'!C9)*2/(B4+B5+B6+C4+C5+C6),"") -> 1.0253111 | D24: =IF((C4+C5+C6+D4+D5+D6)>0,('Profit & Loss'!D10+'Profit & Loss'!D9)*2/(C4+C5+C6+D4+D5+D6),"") -> 1.1329442 | E24: =IF((D4+D5+D6+E4+E5+E6)>0,('Profit & Loss'!E10+'Profit & Loss'!E9)*2/(D4+D5+D6+E4+E5+E6),"") -> 1.1464032 | F24: =IF((E4+E5+E6+F4+F5+F6)>0,('Profit & Loss'!F10+'Profit & Loss'!F9)*2/(E4+E5+E6+F4+F5+F6),"") -> 0.38359301 | G24: =IF((F4+F5+F6+G4+G5+G6)>0,('Profit & Loss'!G10+'Profit & Loss'!G9)*2/(F4+F5+F6+G4+G5+G6),"") -> 0.24514717 | H24: =IF((G4+G5+G6+H4+H5+H6)>0,('Profit & Loss'!H10+'Profit & Loss'!H9)*2/(G4+G5+G6+H4+H5+H6),"") -> 0.26485088 | I24: =IF((H4+H5+H6+I4+I5+I6)>0,('Profit & Loss'!I10+'Profit & Loss'!I9)*2/(H4+H5+H6+I4+I5+I6),"") -> 0.27363876 | J24: =IF((I4+I5+I6+J4+J5+J6)>0,('Profit & Loss'!J10+'Profit & Loss'!J9)*2/(I4+I5+I6+J4+J5+J6),"") -> 0.28529571 | K24: =IF((J4+J5+J6+K4+K5+K6)>0,('Profit & Loss'!K10+'Profit & Loss'!K9)*2/(J4+J5+J6+K4+K5+K6),"") -> 0.36791847

Sheet Cash Flow
A1: ='Balance Sheet'!A1 -> HINDUSTAN UNILEVER LTD | E1: =UPDATE | J1: SCREENER.IN
A3: Narration | B3: ='Data Sheet'!B81 -> 42825 | C3: ='Data Sheet'!C81 -> 43190 | D3: ='Data Sheet'!D81 -> 43555 | E3: ='Data Sheet'!E81 -> 43921 | F3: ='Data Sheet'!F81 -> 44286 | G3: ='Data Sheet'!G81 -> 44651 | H3: ='Data Sheet'!H81 -> 45016 | I3: ='Data Sheet'!I81 -> 45382 | ... K3: ='Data Sheet'!K81 -> 46112
A4: Cash from Operating Activity | B4: ='Data Sheet'!B82 -> 5185 | C4: ='Data Sheet'!C82 -> 6059 | D4: ='Data Sheet'!D82 -> 5800 | E4: ='Data Sheet'!E82 -> 7623 | F4: ='Data Sheet'!F82 -> 9163 | G4: ='Data Sheet'!G82 -> 9048 | H4: ='Data Sheet'!H82 -> 9991 | I4: ='Data Sheet'!I82 -> 15469 | ... K4: ='Data Sheet'!K82 -> 10999
A5: Cash from Investing Activity | B5: ='Data Sheet'!B83 -> -1173 | C5: ='Data Sheet'!C83 -> -1063 | D5: ='Data Sheet'!D83 -> -438 | E5: ='Data Sheet'!E83 -> 1791 | F5: ='Data Sheet'!F83 -> -1228 | G5: ='Data Sheet'!G83 -> -1728 | H5: ='Data Sheet'!H83 -> -1484 | I5: ='Data Sheet'!I83 -> -5324 | ... K5: ='Data Sheet'!K83 -> -3676
A6: Cash from Financing Activity | B6: ='Data Sheet'!B84 -> -4214 | C6: ='Data Sheet'!C84 -> -4975 | D6: ='Data Sheet'!D84 -> -5390 | E6: ='Data Sheet'!E84 -> -6819 | F6: ='Data Sheet'!F84 -> -9309 | G6: ='Data Sheet'!G84 -> -8015 | H6: ='Data Sheet'!H84 -> -8953 | I6: ='Data Sheet'!I84 -> -10034 | ... K6: ='Data Sheet'!K84 -> -10810
A7: Net Cash Flow | B7: ='Data Sheet'!B85 -> -202 | C7: ='Data Sheet'!C85 -> 21 | D7: ='Data Sheet'!D85 -> -28 | E7: ='Data Sheet'!E85 -> 2595 | F7: ='Data Sheet'!F85 -> -1374 | G7: ='Data Sheet'!G85 -> -695 | H7: ='Data Sheet'!H85 -> -446 | I7: ='Data Sheet'!I85 -> 111 | ... K7: ='Data Sheet'!K85 -> -3487

Sheet Customization
A1: How to use it?
A3: You can customize this workbook as you want.
B4: You can add custom formating, add conditional formating, add your own formulas… do ANYTHING.
B5: Please don't edit the "Data Sheet" only.
A7: After customization, you can upload this back on Screener.
B8: Upload on: | C8: https://www.screener.in/excel/
A10: Download your customized workbooks now onwards.
B11: Now whenever you will "Export to excel" from Screener, it will export your customized file.
A14: TESTING:
B15: This is a testing feature currently.
B16: You can report any formula errors on the worksheet at: support@screener.in

Sheet beta
C2: nifty 50 | H2: hul
C4: Date | D4: Price | E4: RETURNS | G4: Date | H4: Price | I4: RETURNS | M4: SLOPE | N4: =SLOPE(I6:I64,E6:E64) -> 0.79750724
C5: 46204 | D5: 24072.75 | G5: 46204 | H5: 2143.8 | K5: =N6 -> 0.79750724
C6: 46174 | D6: 23865.75 | E6: =D6/D5-1 -> -0.0085989345 | G6: 46174 | H6: 2118.2 | I6: =H6/H5-1 -> -0.011941412 | K6: 0.75 | M6: BETA | N6: =O32 -> 0.79750724
C7: 46143 | D7: 23547.75 | E7: =D7/D6-1 -> -0.013324534 | G7: 46143 | H7: 2153.5 | I7: =H7/H6-1 -> 0.016665093 | K7: 1
C8: 46113 | D8: 23997.55 | E8: =D8/D7-1 -> 0.019101613 | G8: 46113 | H8: 2250.9 | I8: =H8/H7-1 -> 0.045228697 | K8: 0.25
C9: 46082 | D9: 22331.4 | E9: =D9/D8-1 -> -0.069430004 | G9: 46082 | H9: 2055.2 | I9: =H9/H8-1 -> -0.086943001 | K9: =(K5*K6)+(K7*K8) -> 0.84813043
C10: 46054 | D10: 25178.65 | E10: =D10/D9-1 -> 0.12749984 | G10: 46054 | H10: 2338.1 | I10: =H10/H9-1 -> 0.13765084
C11: 46023 | D11: 25320.65 | E11: =D11/D10-1 -> 0.0056396987 | G11: 46023 | H11: 2373 | I11: =H11/H10-1 -> 0.01492665
C12: 45992 | D12: 26129.6 | E12: =D12/D11-1 -> 0.031948232 | G12: 45992 | H12: 2315.9 | I12: =H12/H11-1 -> -0.024062368
C13: 45962 | D13: 26202.95 | E13: =D13/D12-1 -> 0.0028071612 | G13: 45962 | H13: 2426.33 | I13: =H13/H12-1 -> 0.047683406
C14: 45931 | D14: 25722.1 | E14: =D14/D13-1 -> -0.018350987 | G14: 45931 | H14: 2425.25 | I14: =H14/H13-1 -> -0.0004451167
C15: 45901 | D15: 24611.1 | E15: =D15/D14-1 -> -0.04319243 | G15: 45901 | H15: 2473.35 | I15: =H15/H14-1 -> 0.019833007 | N15: SUMMARY OUTPUT
C16: 45870 | D16: 24426.85 | E16: =D16/D15-1 -> -0.0074864594 | G16: 45870 | H16: 2659.8 | I16: =H16/H15-1 -> 0.075383589
C17: 45839 | D17: 24768.35 | E17: =D17/D16-1 -> 0.013980517 | G17: 45839 | H17: 2521.2 | I17: =H17/H16-1 -> -0.052109181 | N17: Regression Statistics
C18: 45809 | D18: 25517.05 | E18: =D18/D17-1 -> 0.030228094 | G18: 45809 | H18: 2294.6 | I18: =H18/H17-1 -> -0.089877836 | N18: Multiple R | O18: 0.4973093
C19: 45778 | D19: 24750.7 | E19: =D19/D18-1 -> -0.03003286 | G19: 45778 | H19: 2348.3 | I19: =H19/H18-1 -> 0.023402772 | N19: R Square | O19: 0.24731654
C20: 45748 | D20: 24334.2 | E20: =D20/D19-1 -> -0.016827807 | G20: 45748 | H20: 2342.1 | I20: =H20/H19-1 -> -0.0026402078 | N20: Adjusted R Square | O20: 0.23411157
C21: 45717 | D21: 23519.35 | E21: =D21/D20-1 -> -0.033485794 | G21: 45717 | H21: 2258.85 | I21: =H21/H20-1 -> -0.035545024 | N21: Standard Error | O21: 0.05369331
C22: 45689 | D22: 22124.7 | E22: =D22/D21-1 -> -0.059297982 | G22: 45689 | H22: 2190.25 | I22: =H22/H21-1 -> -0.030369436 | N22: Observations | O22: 59
C23: 45658 | D23: 23508.4 | E23: =D23/D22-1 -> 0.062540961 | G23: 45658 | H23: 2468.8 | I23: =H23/H22-1 -> 0.12717726
C24: 45627 | D24: 23644.8 | E24: =D24/D23-1 -> 0.0058021813 | G24: 45627 | H24: 2326.85 | I24: =H24/H23-1 -> -0.05749757 | N24: ANOVA
C25: 45597 | D25: 24131.1 | E25: =D25/D24-1 -> 0.02056689 | G25: 45597 | H25: 2496.15 | I25: =H25/H24-1 -> 0.07275931 | O25: df | P25: SS | Q25: MS | R25: F | S25: Significance F
C26: 45566 | D26: 24205.35 | E26: =D26/D25-1 -> 0.0030769422 | G26: 45566 | H26: 2518.22 | I26: =H26/H25-1 -> 0.0088416161 | N26: Regression | O26: 1 | P26: 0.053995306 | Q26: 0.053995306 | R26: 18.729046 | S26: 6.148892e-05
C27: 45536 | D27: 25810.85 | E27: =D27/D26-1 -> 0.066328312 | G27: 45536 | H27: 2946.57 | I27: =H27/H26-1 -> 0.17010031 | N27: Residual | O27: 57 | P27: 0.16432938 | Q27: 0.0028829716
C28: 45505 | D28: 25235.9 | E28: =D28/D27-1 -> -0.022275516 | G28: 45505 | H28: 2766.98 | I28: =H28/H27-1 -> -0.060948832 | N28: Total | O28: 58 | P28: 0.21832469
C29: 45474 | D29: 24951.15 | E29: =D29/D28-1 -> -0.011283529 | G29: 45474 | H29: 2694.92 | I29: =H29/H28-1 -> -0.026042834
C30: 45444 | D30: 24010.6 | E30: =D30/D29-1 -> -0.037695657 | G30: 45444 | H30: 2463.24 | I30: =H30/H29-1 -> -0.085969157 | O30: Coefficients | P30: Standard Error | Q30: t Stat | R30: P-value | S30: Lower 95% | T30: Upper 95% | U30: Lower 95.0% | V30: Upper 95.0%
C31: 45413 | D31: 22530.7 | E31: =D31/D30-1 -> -0.061635278 | G31: 45413 | H31: 2319.81 | I31: =H31/H30-1 -> -0.058228187 | N31: Intercept | O31: 0.009849556 | P31: 0.0070515607 | Q31: 1.3967909 | R31: 0.16789138 | S31: -0.0042709508 | T31: 0.023970063 | U31: -0.0042709508 | V31: 0.023970063
C32: 45383 | D32: 22604.85 | E32: =D32/D31-1 -> 0.0032910651 | G32: 45383 | H32: 2221.6 | I32: =H32/H31-1 -> -0.042335364 | N32: X Variable 1 | O32: 0.79750724 | P32: 0.18427941 | Q32: 4.3277067 | R32: 6.148892e-05 | S32: 0.42849409 | T32: 1.1665204 | U32: 0.42849409 | V32: 1.1665204
C33: 45352 | D33: 22326.9 | E33: =D33/D32-1 -> -0.012296034 | G33: 45352 | H33: 2255.37 | I33: =H33/H32-1 -> 0.015200756
C34: 45323 | D34: 21982.8 | E34: =D34/D33-1 -> -0.015411902 | G34: 45323 | H34: 2402.73 | I34: =H34/H33-1 -> 0.065337395
C35: 45292 | D35: 21725.7 | E35: =D35/D34-1 -> -0.011695507 | G35: 45292 | H35: 2471.71 | I35: =H35/H34-1 -> 0.02870901
C36: 45261 | D36: 21731.4 | E36: =D36/D35-1 -> 0.00026236209 | G36: 45261 | H36: 2653.39 | I36: =H36/H35-1 -> 0.073503769
C37: 45231 | D37: 20133.15 | E37: =D37/D36-1 -> -0.073545653 | G37: 45231 | H37: 2535.45 | I37: =H37/H36-1 -> -0.044448799
C38: 45200 | D38: 19079.6 | E38: =D38/D37-1 -> -0.052329119 | G38: 45200 | H38: 2474.15 | I38: =H38/H37-1 -> -0.024177168
C39: 45170 | D39: 19638.3 | E39: =D39/D38-1 -> 0.029282585 | G39: 45170 | H39: 2455.82 | I39: =H39/H38-1 -> -0.007408605
C40: 45139 | D40: 19253.8 | E40: =D40/D39-1 -> -0.019579088 | G40: 45139 | H40: 2495.11 | I40: =H40/H39-1 -> 0.01599873
C41: 45108 | D41: 19753.8 | E41: =D41/D40-1 -> 0.0259689 | G41: 45108 | H41: 2550.64 | I41: =H41/H40-1 -> 0.022255532
C42: 45078 | D42: 19189.05 | E42: =D42/D41-1 -> -0.028589436 | G42: 45078 | H42: 2667.53 | I42: =H42/H41-1 -> 0.045827714
C43: 45047 | D43: 18534.4 | E43: =D43/D42-1 -> -0.034115811 | G43: 45047 | H43: 2656.97 | I43: =H43/H42-1 -> -0.0039587184
C44: 45017 | D44: 18065 | E44: =D44/D43-1 -> -0.025325881 | G44: 45017 | H44: 2447.55 | I44: =H44/H43-1 -> -0.078819106
... C64: 44409 | D64: 17132.2 | E64: =D64/D63-1 -> -0.027582351 | G64: 44409 | H64: 2713.3 | I64: =H64/H63-1 -> 0.008256908

Sheet DATAS
C2: 42064 | D2: 42430 | E2: 42795 | F2: 43160 | G2: 43525 | H2: 43891 | I2: 44256 | J2: 44621 | K2: 44986 | L2: 45352 | M2: 45717 | N2: 46082
B3: Equity Capital | C3: 216 | D3: 216 | E3: 216 | F3: 216 | G3: 216 | H3: 216 | I3: 235 | J3: 235 | K3: 235 | L3: 235 | M3: 235 | N3: 235
B4: Reserves | C4: 3811 | D4: 6357 | E4: 6528 | F4: 7065 | G4: 7651 | H4: 8013 | I4: 47439 | J4: 48826 | K4: 50069 | L4: 50983 | M4: 49167 | N4: 48504
B5: Borrowings -
B6: Long term Borrowings | C6: 7 | D6: 0 | E6: 0 | F6: 0 | G6: 0 | H6: 0 | I6: 0 | J6: 0 | K6: 0 | L6: 0 | M6: 0 | N6: 0
B7: Short term Borrowings | C7: 36 | D7: 177 | E7: 277 | F7: 0 | G7: 99 | H7: 0 | I7: 0 | J7: 0 | K7: 98 | L7: 13 | M7: 1 | N7: 0
B8: Lease Liabilities | C8: 0 | D8: 0 | E8: 0 | F8: 0 | G8: 0 | H8: 0 | I8: 0 | J8: 1043 | K8: 1121 | L8: 1471 | M8: 1647 | N8: 1478
B9: Other Liabilities -
B10: Non controlling int | C10: 25 | D10: 20 | E10: 22 | F10: 20 | G10: 18 | H10: 17 | I10: 20 | J10: 26 | K10: 218 | L10: 205 | M10: 207 | N10: 269
B11: Trade Payables | C11: 5506 | D11: 5685 | E11: 6186 | F11: 7170 | G11: 7206 | H11: 7535 | I11: 8802 | J11: 9068 | K11: 9574 | L11: 10486 | M11: 11315 | N11: 13325
B12: Advance from Customers | C12: 45 | D12: 45 | E12: 78 | F12: 62 | G12: 43 | H12: 158 | I12: 96 | J12: 119 | K12: 98 | L12: 91 | M12: 0 | N12: 0
B13: Other liability items | C13: 4783 | D13: 2293 | E13: 2399 | F13: 3329 | G13: 3396 | H13: 4214 | I13: 12148 | J13: 11189 | K13: 11664 | L13: 15005 | M13: 17291 | N13: 15927
B14: Total Liabilities | C14: 14430 | D14: 14793 | E14: 15706 | F14: 17862 | G14: 18629 | H14: 20153 | I14: 68740 | J14: 70506 | K14: 73077 | L14: 78489 | M14: 79863 | N14: 79738
B16: Fixed Assets -
B17: Land | C17: 102 | D17: 88 | E17: 89 | F17: 87 | G17: 86 | H17: 59 | I17: 477 | J17: 477 | K17: 609 | L17: 633 | M17: 628 | N17: 636
B18: Building | C18: 1173 | D18: 931 | E18: 1210 | F18: 1343 | G18: 1527 | H18: 2044 | I18: 2602 | J18: 2788 | K18: 3101 | L18: 3590 | M18: 3833 | N18: 4067
B19: Plant Machinery | C19: 3481 | D19: 2370 | E19: 3270 | F19: 3691 | G19: 4092 | H19: 5001 | I19: 6097 | J19: 6566 | K19: 7612 | L19: 8946 | M19: 9900 | N19: 9296
B20: Equipments | C20: 106 | D20: 41 | E20: 62 | F20: 74 | G20: 95 | H20: 139 | I20: 175 | J20: 181 | K20: 185 | L20: 206 | M20: 245 | N20: 286
B21: Furniture n fittings | C21: 108 | D21: 61 | E21: 66 | F21: 76 | G21: 88 | H21: 154 | I21: 156 | J21: 152 | K21: 161 | L21: 165 | M21: 174 | N21: 220
B22: Railway sidings | C22: 0 | D22: 0 | E22: 0 | F22: 0 | G22: 0 | H22: 0 | I22: 0 | J22: 0 | K22: 0 | L22: 0 | M22: 0 | N22: 0
B23: Vehicles | C23: 1 | D23: 0 | E23: 0 | F23: 0 | G23: 0 | H23: 0 | I23: 0 | J23: 0 | K23: 33 | L23: 39 | M23: 102 | N23: 103
B24: Intangible Assets | C24: 247 | D24: 85 | E24: 455 | F24: 455 | G24: 511 | H24: 511 | I24: 45262 | J24: 45262 | K24: 45692 | L24: 45692 | M24: 45692 | N24: 49195
B25: Other fixed assets | C25: 193 | D25: 19 | E25: 19 | F25: 26 | G25: 60 | H25: 71 | I25: 155 | J25: 152 | K25: 171 | L25: 180 | M25: 190 | N25: 210
B26: Gross Block | C26: 5412 | D26: 3595 | E26: 5171 | F26: 5752 | G26: 6459 | H26: 7979 | I26: 54924 | J26: 55578 | K26: 57564 | L26: 59451 | M26: 60764 | N26: 64013
B27: Accumulated Depreciation | C27: 2591 | D27: 337 | E27: 752 | F27: 1224 | G27: 1744 | H27: 2500 | I27: 3481 | J27: 4105 | K27: 4886 | L27: 5707 | M27: 6429 | N27: 6585 | P27: =C26-C27 -> 2821
B28: CWIP | C28: 516 | D28: 408 | E28: 229 | F28: 461 | G28: 406 | H28: 597 | I28: 745 | J28: 1313 | K28: 1132 | L28: 1025 | M28: 1009 | N28: 880 | P28: =SUM(C28:C35) -> 11608
B29: Investments | C29: 3025 | D29: 2592 | E29: 3794 | F29: 2873 | G29: 2716 | H29: 1255 | I29: 2709 | J29: 3521 | K29: 2882 | L29: 4625 | M29: 3810 | N29: 4359 | P29: =SUM(P27:P28) -> 14429
B30: Other Assets -
B31: Inventories | C31: 2849 | D31: 2726 | E31: 2541 | F31: 2513 | G31: 2574 | H31: 2767 | I31: 3579 | J31: 4096 | K31: 4251 | L31: 4022 | M31: 4415 | N31: 4789
B32: Trade receivables + | C32: 1010 | D32: 1264 | E32: 1085 | F32: 1310 | G32: 1816 | H32: 1149 | I32: 1758 | J32: 2236 | K32: 3079 | L32: 2997 | M32: 3819 | N32: 3379
B33: Cash Equivalents | C33: 2689 | D33: 3009 | E33: 1828 | F33: 3485 | G33: 3757 | H33: 5113 | I33: 4471 | J33: 3846 | K33: 4678 | L33: 7559 | M33: 7554 | N33: 3248
B34: Loans n Advances | C34: 0 | D34: 0 | E34: 71 | F34: 40 | G34: 26 | H34: 19 | I34: 78 | J34: 170 | K34: 188 | L34: 172 | M34: 619 | N34: 1024
B35: Other asset items | C35: 1519 | D35: 1536 | E35: 1739 | F35: 2652 | G35: 2619 | H35: 3774 | I35: 3957 | J35: 3851 | K35: 4189 | L35: 4345 | M35: 4302 | N35: 4631
B36: Total Assets | C36: 14430 | D36: 14793 | E36: 15706 | F36: 17862 | G36: 18629 | H36: 20153 | I36: 68740 | J36: 70506 | K36: 73077 | L36: 78489 | M36: 79863 | N36: 79738
C45: 42064 | D45: 42430 | E45: 42795 | F45: 43160 | G45: 43525 | H45: 43891 | I45: 44256 | J45: 44621 | K45: 44986 | L45: 45352 | M45: 45717 | N45: 46082
B46: Cash from Operating Activity - | C46: 3292 | D46: 4171 | E46: 5185 | F46: 6059 | G46: 5800 | H46: 7623 | I46: 9163 | J46: 9048 | K46: 9991 | L46: 15469 | M46: 11886 | N46: 10999
B47: Profit from operations | C47: 5510 | D47: 6025 | E47: 6512 | F47: 7485 | G47: 8909 | H47: 9723 | I47: 11672 | J47: 12829 | K47: 14089 | L47: 14537 | M47: 14942 | N47: 15153
B48: Receivables | C48: 3 | D48: -257 | E48: 173 | F48: 0 | G48: 0 | H48: 0 | I48: 0 | J48: 0 | K48: 0 | L48: 0 | M48: 0 | N48: 0
B49: Inventory | C49: 91 | D49: 89 | E49: 37 | F49: -146 | G49: -195 | H49: -331 | I49: -543 | J49: -758 | K49: -339 | L49: 74 | M49: -584 | N49: -692
B50: Payables | C50: -327 | D50: 164 | E50: 501 | F50: 0 | G50: 0 | H50: 0 | I50: 0 | J50: 0 | K50: 0 | L50: 0 | M50: 0 | N50: 0
B51: Loans Advances | C51: -148 | D51: 0 | E51: 0 | F51: 0 | G51: 0 | H51: 0 | I51: 0 | J51: 0 | K51: 0 | L51: 0 | M51: 0 | N51: 0
B52: Operating Deposits | C52: 0 | D52: 0 | E52: -46 | F52: 0 | G52: 0 | H52: 0 | I52: 0 | J52: 0 | K52: 0 | L52: 0 | M52: 0 | N52: 0
B53: Other WC items | C53: 38 | D53: -77 | E53: -99 | F53: 982 | G53: -147 | H53: 742 | I53: 442 | J53: -242 | K53: -621 | L53: 1239 | M53: -204 | N53: 1378
B54: Working capital changes | C54: -342 | D54: -81 | E54: 566 | F54: 836 | G54: -342 | H54: 411 | I54: -101 | J54: -1000 | K54: -960 | L54: 1313 | M54: -788 | N54: 686
B55: Direct taxes | C55: -1862 | D55: -1765 | E55: -1859 | F55: -2264 | G55: -2767 | H55: -2505 | I55: -2407 | J55: -2784 | K55: -3138 | L55: -381 | M55: -2268 | N55: -4840
B56: Other operating items | C56: -14 | D56: -8 | E56: -21 | F56: 0 | G56: 0 | H56: 0 | I56: 0 | J56: 0 | K56: 0 | L56: 0 | M56: 0 | N56: 0
B57: Exceptional CF items | C57: 0 | D57: 0 | E57: -13 | F57: 2 | G57: 0 | H57: -6 | I57: -1 | J57: 3 | K57: 0 | L57: 0 | M57: 0 | N57: 0
... B78: CFO/OP | C78: 0.95 | D78: 1 | E78: 1.11 | F78: 1.11 | G78: 0.96 | H78: 1.03 | I78: 1 | J78: 0.92 | K78: 0.93 | L78: 1.08 | M78: 0.96 | N78: 1.05

Sheet DCF
C2: HINDUSTAN UNILEVER
C3: DCF MODEL
B4: CALCULATION OF ROIC
B5: CURRENT ASSETS | C5: 44276 | D5: 44642 | E5: 45008 | F5: 45374 | G5: 45740 | H5: 46106
B6: =DATAS!B31 -> Inventories | C6: =DATAS!I31 -> 3579 | D6: =DATAS!J31 -> 4096 | E6: =DATAS!K31 -> 4251 | F6: =DATAS!L31 -> 4022 | G6: =DATAS!M31 -> 4415 | H6: =DATAS!N31 -> 4789
B7: =DATAS!B32 -> Trade receivables + | C7: =DATAS!I32 -> 1758 | D7: =DATAS!J32 -> 2236 | E7: =DATAS!K32 -> 3079 | F7: =DATAS!L32 -> 2997 | G7: =DATAS!M32 -> 3819 | H7: =DATAS!N32 -> 3379
B8: =DATAS!B34 -> Loans n Advances | C8: =DATAS!I34 -> 78 | D8: =DATAS!J34 -> 170 | E8: =DATAS!K34 -> 188 | F8: =DATAS!L34 -> 172 | G8: =DATAS!M34 -> 619 | H8: =DATAS!N34 -> 1024
B9: =DATAS!B35 -> Other asset items | C9: =DATAS!I35 -> 3957 | D9: =DATAS!J35 -> 3851 | E9: =DATAS!K35 -> 4189 | F9: =DATAS!L35 -> 4345 | G9: =DATAS!M35 -> 4302 | H9: =DATAS!N35 -> 4631
B10: TOTAL ASSETS | C10: =SUM(C6:C9) -> 9372 | D10: =SUM(D6:D9) -> 10353 | E10: =SUM(E6:E9) -> 11707 | F10: =SUM(F6:F9) -> 11536 | G10: =SUM(G6:G9) -> 13155 | H10: =SUM(H6:H9) -> 13823
B13: CURRENT LIABILITIES | C13: 44276 | D13: 44642 | E13: 45008 | F13: 45374 | G13: 45740 | H13: 46106
B14: =DATAS!B11 -> Trade Payables | C14: =DATAS!I11 -> 8802 | D14: =DATAS!J11 -> 9068 | E14: =DATAS!K11 -> 9574 | F14: =DATAS!L11 -> 10486 | G14: =DATAS!M11 -> 11315 | H14: =DATAS!N11 -> 13325
B15: =DATAS!B12 -> Advance from Customers | C15: =DATAS!I12 -> 96 | D15: =DATAS!J12 -> 119 | E15: =DATAS!K12 -> 98 | F15: =DATAS!L12 -> 91 | G15: =DATAS!M12 -> 0 | H15: =DATAS!N12 -> 0
B16: =DATAS!B13 -> Other liability items | C16: =DATAS!I13 -> 12148 | D16: =DATAS!J13 -> 11189 | E16: =DATAS!K13 -> 11664 | F16: =DATAS!L13 -> 15005 | G16: =DATAS!M13 -> 17291 | H16: =DATAS!N13 -> 15927
B17: TOTAL | C17: =SUM(C14:C16) -> 21046 | D17: =SUM(D14:D16) -> 20376 | E17: =SUM(E14:E16) -> 21336 | F17: =SUM(F14:F16) -> 25582 | G17: =SUM(G14:G16) -> 28606 | H17: =SUM(H14:H16) -> 29252
B20: NETWORKING CAP | C20: =C10-C17 -> -11674 | D20: =D10-D17 -> -10023 | E20: =E10-E17 -> -9629 | F20: =F10-F17 -> -14046 | G20: =G10-G17 -> -15451 | H20: =H10-H17 -> -15429
B23: NON CURRENT ASSETS | C23: 44276 | D23: 44642 | E23: 45008 | F23: 45374 | G23: 45740 | H23: 46106
B24: =DATAS!B17 -> Land | C24: =DATAS!I17 -> 477 | D24: =DATAS!J17 -> 477 | E24: =DATAS!K17 -> 609 | F24: =DATAS!L17 -> 633 | G24: =DATAS!M17 -> 628 | H24: =DATAS!N17 -> 636
B25: =DATAS!B18 -> Building | C25: =DATAS!I18 -> 2602 | D25: =DATAS!J18 -> 2788 | E25: =DATAS!K18 -> 3101 | F25: =DATAS!L18 -> 3590 | G25: =DATAS!M18 -> 3833 | H25: =DATAS!N18 -> 4067
B26: =DATAS!B19 -> Plant Machinery | C26: =DATAS!I19 -> 6097 | D26: =DATAS!J19 -> 6566 | E26: =DATAS!K19 -> 7612 | F26: =DATAS!L19 -> 8946 | G26: =DATAS!M19 -> 9900 | H26: =DATAS!N19 -> 9296
B27: =DATAS!B20 -> Equipments | C27: =DATAS!I20 -> 175 | D27: =DATAS!J20 -> 181 | E27: =DATAS!K20 -> 185 | F27: =DATAS!L20 -> 206 | G27: =DATAS!M20 -> 245 | H27: =DATAS!N20 -> 286
B28: =DATAS!B21 -> Furniture n fittings | C28: =DATAS!I21 -> 156 | D28: =DATAS!J21 -> 152 | E28: =DATAS!K21 -> 161 | F28: =DATAS!L21 -> 165 | G28: =DATAS!M21 -> 174 | H28: =DATAS!N21 -> 220
B29: =DATAS!B22 -> Railway sidings | C29: =DATAS!I22 -> 0 | D29: =DATAS!J22 -> 0 | E29: =DATAS!K22 -> 0 | F29: =DATAS!L22 -> 0 | G29: =DATAS!M22 -> 0 | H29: =DATAS!N22 -> 0
B30: =DATAS!B23 -> Vehicles | C30: =DATAS!I23 -> 0 | D30: =DATAS!J23 -> 0 | E30: =DATAS!K23 -> 33 | F30: =DATAS!L23 -> 39 | G30: =DATAS!M23 -> 102 | H30: =DATAS!N23 -> 103
B31: =DATAS!B24 -> Intangible Assets | C31: =DATAS!I24 -> 45262 | D31: =DATAS!J24 -> 45262 | E31: =DATAS!K24 -> 45692 | F31: =DATAS!L24 -> 45692 | G31: =DATAS!M24 -> 45692 | H31: =DATAS!N24 -> 49195
B32: =DATAS!B25 -> Other fixed assets | C32: =DATAS!I25 -> 155 | D32: =DATAS!J25 -> 152 | E32: =DATAS!K25 -> 171 | F32: =DATAS!L25 -> 180 | G32: =DATAS!M25 -> 190 | H32: =DATAS!N25 -> 210
B33: =DATAS!B26 -> Gross Block | C33: =DATAS!I26 -> 54924 | D33: =DATAS!J26 -> 55578 | E33: =DATAS!K26 -> 57564 | F33: =DATAS!L26 -> 59451 | G33: =DATAS!M26 -> 60764 | H33: =DATAS!N26 -> 64013
B34: =DATAS!B27 -> Accumulated Depreciation | C34: =DATAS!I27 -> 3481 | D34: =DATAS!J27 -> 4105 | E34: =DATAS!K27 -> 4886 | F34: =DATAS!L27 -> 5707 | G34: =DATAS!M27 -> 6429 | H34: =DATAS!N27 -> 6585
B35: NET NON CURRENT ASSETS | C35: =C33-C34 -> 51443 | D35: =D33-D34 -> 51473 | E35: =E33-E34 -> 52678 | F35: =F33-F34 -> 53744 | G35: =G33-G34 -> 54335 | H35: =H33-H34 -> 57428
B38: INVESTED CAP | C38: =C35+C20 -> 39769 | D38: =D35+D20 -> 41450 | E38: =E35+E20 -> 43049 | F38: =F35+F20 -> 39698 | G38: =G35+G20 -> 38884 | H38: =H35+H20 -> 41999
B39: EBIT | C39: =FINANCIALS!G17-FINANCIALS!G23 -> 10552 | D39: =FINANCIALS!H17-FINANCIALS!H23 -> 11766 | E39: =FINANCIALS!I17-FINANCIALS!I23 -> 13010 | F39: =FINANCIALS!J17-FINANCIALS!J23 -> 13443 | G39: =FINANCIALS!K17-FINANCIALS!K23 -> 13445 | H39: =FINANCIALS!L17-FINANCIALS!L23 -> 13706
B41: ROIC | C41: =C39/C38 -> 0.26533229 | D41: =D39/D38 -> 0.28386007 | E41: =E39/E38 -> 0.30221376 | F41: =F39/F38 -> 0.33863167 | G41: =G39/G38 -> 0.34577204 | H41: =H39/H38 -> 0.3263411
B42: MEDIAN | C42: =MEDIAN(C41:H41) -> 0.31427743
B46: CALCULATION OF REINVESTMENT RATE
B47: REINVESTMENT RATE | C47: 44276 | D47: 44642 | E47: 45008 | F47: 45374 | G47: 45740 | H47: 46106
B48: NET CAPEX | C48: =-SUM(DATAS!I59:I60) -> 4066 | D48: =-SUM(DATAS!J59:J60) -> 1053 | E48: =-SUM(DATAS!K59:K60) -> 1011 | F48: =-SUM(DATAS!L59:L60) -> 1457 | G48: =-SUM(DATAS!M59:M60) -> 1262 | H48: =-SUM(DATAS!N59:N60) -> 1332
B49: CHANGE IN WORKING CAP | D49: =D20-C20 -> 1651 | E49: =E20-D20 -> 394 | F49: =F20-E20 -> -4417 | G49: =G20-F20 -> -1405 | H49: =H20-G20 -> 22
B50: EBIT | C50: =C39 -> 10552 | D50: =D39 -> 11766 | E50: =E39 -> 13010 | F50: =F39 -> 13443 | G50: =G39 -> 13445 | H50: =H39 -> 13706
B51: TAX | C51: 0.25 | D51: 0.25 | E51: 0.25 | F51: 0.25 | G51: 0.25 | H51: 0.25 | L51: =22.86% -> 0.2286
B52: EBIT(1-TAX) | C52: =C50*(1-C51) -> 7914 | D52: =D50*(1-D51) -> 8824.5 | E52: =E50*(1-E51) -> 9757.5 | F52: =F50*(1-F51) -> 10082.25 | G52: =G50*(1-G51) -> 10083.75 | H52: =H50*(1-H51) -> 10279.5
B54: REINVESTMENT | D54: =SUM(D48:D49) -> 2704 | E54: =SUM(E48:E49) -> 1405 | F54: =SUM(F48:F49) -> -2960 | G54: =SUM(G48:G49) -> -143 | H54: =SUM(H48:H49) -> 1354
B55: REINVESTMENT RATE | D55: =D54/D52 -> 0.30641963 | E55: =E54/E52 -> 0.1439918 | F55: =F54/F52 -> -0.29358526 | G55: =G54/G52 -> -0.014181232 | H55: =H54/H52 -> 0.13171847 | L55: =(75%*16.7%)+(25%*41.3%) -> 0.2285
B57: MEDIAN | C57: =MEDIAN(D55:H55) -> 0.13171847
B61: GROWTH RATE | C61: 44276 | D61: 44642 | E61: 45008 | F61: 45374 | G61: 45740 | H61: 46106
B62: REINVESTMENT RATE | D62: =D55 -> 0.30641963 | E62: =E55 -> 0.1439918 | F62: =F55 -> -0.29358526 | G62: =G55 -> -0.014181232 | H62: =H55 -> 0.13171847
B63: ROIC | D63: =D41 -> 0.28386007 | E63: =E41 -> 0.30221376 | F63: =F41 -> 0.33863167 | G63: =G41 -> 0.34577204 | H63: =H41 -> 0.3263411
B64: GROWTH RATE | D64: =D63*D62 -> 0.086980298 | E64: =E63*E62 -> 0.043516303 | F64: =F63*F62 -> -0.099417267 | G64: =G63*G62 -> -0.0049034736 | H64: =H63*H62 -> 0.04298515
B66: GROWTH MEDIAN | C66: =MEDIAN(D64:H64) -> 0.04298515
B67: AVERAGE | C67: =AVERAGE(D64:H64) -> 0.013832202
B71: CALCULATION OF FCFF | C71: MAR-26A | D71: 46473 | E71: 46840 | F71: 47206 | G71: 47572 | H71: =wacc!M27 -> 0.085432439
B72: EBIT | C72: =H39 -> 13706 | D72: =C72*(1+$C$66) -> 14295.154 | E72: =D72*(1+$C$66) -> 14909.634 | F72: =E72*(1+$C$66) -> 15550.527 | G72: =F72*(1+$C$66) -> 16218.968
B73: TAX | C73: 0.25 | D73: 0.25 | E73: 0.25 | F73: 0.25 | G73: 0.25
B74: EBIT(1-TAX) | C74: =C72*(1-C73) -> 10279.5 | D74: =D72*(1-D73) -> 10721.366 | E74: =E72*(1-E73) -> 11182.225 | F74: =F72*(1-F73) -> 11662.895 | G74: =G72*(1-G73) -> 12164.226
B76: LESS REINVESTMENT RATE | C76: =C57 -> 0.13171847 | D76: =C76+($G$76-$C$76)/4 -> 0.15591385 | E76: =D76+($G$76-$C$76)/4 -> 0.18010923 | F76: =E76+($G$76-$C$76)/4 -> 0.20430462 | G76: =L55 -> 0.2285
B77: FCFF | C77: =C74*(1-C76) -> 8925.5 | D77: =D74*(1-D76) -> 9049.7564 | E77: =E74*(1-E76) -> 9168.2033 | F77: =F74*(1-F76) -> 9280.1117 | G77: =G74*(1-G76) -> 9384.7006
B78: MID YEAR CONVENTION | C78: 0.5 | D78: 1.5 | E78: 2.5 | F78: 3.5 | G78: 4.5
B79: DISCOUNTING FACTOR | C79: =1/(1+$H$71)^C78 -> 0.95983946 | D79: =1/(1+$H$71)^D78 -> 0.88429222 | E79: =1/(1+$H$71)^E78 -> 0.81469117 | F79: =1/(1+$H$71)^F78 -> 0.75056829 | G79: =1/(1+$H$71)^G78 -> 0.69149241
B81: PV OF FCFF | C81: =C77*C79 -> 8567.0471 | D81: =D77*D79 -> 8002.6292 | E81: =E77*E79 -> 7469.2543 | F81: =F77*F79 -> 6965.3576 | G81: =G77*G79 -> 6489.4492
B85: CALCULATION OF TERMINAL VALUE
B87: FCFF(N +1) | C87: =G72*(1+C66) -> 16916.143
B88: WACC | C88: =H71 -> 0.085432439
B89: TERMINAL GROWTH RATE | C89: 0.0585
B91: TERMINAL VALUE | C91: =C87/(C88-C89) -> 628095.48
B95: CALCULATION OF EQUITY VALUE
B97: PV OF FCFF | C97: =SUM(C81:G81) -> 37493.737
B98: PV OF TERMINAL VALUE | C98: =C91*G79 -> 434323.26
B99: VALUE OF OPERATING ASSETS | C99: =SUM(C97:C98) -> 471816.99
B101: ADD CASH | C101: ='Data Sheet'!K69 -> 3248
B102: LESS DEBT | C102: =DATAS!N8 -> 1478
B103: VALUE OF EQUITY | C103: =C99+C101-C102 -> 473586.99
B104: NO OF SHARES | C104: ='Data Sheet'!B6 -> 234.95912
B105: EQUITY VALUE PER SHARE | C105: =C103/C104 -> 2015.6144
B107: SHARE PRICE | C107: 2145
B108: DISCOUNT/PPREMIUM | C108: =C107/C105-1 -> 0.064191642

Sheet wacc
C5: COST OF DEBT | J5: COST OF EQUITY
C7: PRE TAX COST OF DEBT | G7: =7.5% -> 0.075 | J7: RISK FREE RATE | O7: 0.0672
C8: TAX RATE | G8: =25% -> 0.25 | J8: EQUITY RISK PREMIUM | O8: 0.07
C9: POST TAX COST OF DEBT | G9: =G7*(1-G8) -> 0.05625 | J9: LEVERED BETA 4 | O9: =beta!K9 -> 0.84813043
J10: COST OF EQUITY | O10: =O7+(O9*O8) -> 0.12656913
C14: CAPITAL STRUCTURE | J14: LEVERED BETA
F16: CURRENT | G16: TARGET | J16: COMPS MEDIAN UNLEVERED BETA
C17: TOTAL DEBT | E17: =1478 -> 1478 | F17: =E17/E19 -> 0.0029256703 | G17: =AB21 -> 0.585 | J17: TARGET DEBT/EQUITY | S17: 2 | T17: ITC | U17: 280.7 | V17: 16.83 | W17: 351702.17 | X17: 5469.74 | Y17: 5.3 | Z17: 17824.68 | AA17: 38.91 | AB17: 0.03 | AC17: 2399.06
C18: MARKET CAPITALIZATION | E18: =503705.37 -> 503705.37 | F18: =E18/E19 -> 0.99707433 | G18: =1-G17 -> 0.415 | J18: TAX RATE | S18: 3 | T18: Hindustan Foods | U18: 558.4 | V18: 44.38 | W18: 6765.73 | X18: 41.55 | Y18: 34.17 | Z18: 1116.75 | AA18: 14.2 | AB18: 0.93 | AC18: 1088.26
C19: TOTAL CAPITAL | E19: =SUM(E17:E18) -> 505183.37 | F19: =SUM(F17:F18) -> 1 | J19: LEVERED BETA | S19: 4 | T19: Godavari Bioref. | U19: 256.4 | V19: 39.02 | W19: 1312.15 | X19: 52.88 | Y19: -30.03 | Z19: 564.1 | AA19: 6.55 | AB19: 0.67 | AC19: 530.76
S20: 5 | T20: Davangere Sugar | U20: 3.49 | V20: 58.65 | W20: 499.07 | X20: 1.95 | Y20: 0.52 | Z20: 83.82 | AA20: 5.56 | AB20: 0.5 | AC20: 250.05
AB21: =MEDIAN(AB17:AB20) -> 0.585
C22: DEBT/EQUITY | F22: =F17/F18 -> 0.002934255 | J22: WEIGHTED AVERAGE COST OF CAPITAL
L24: TOTAL COST | M24: TOTAL WEIGHT
J25: DEBT | L25: =G9 -> 0.05625 | M25: =G17 -> 0.585
J26: EQUITY | L26: =O10 -> 0.12656913 | M26: =G18 -> 0.415 | R26: =0.5*100 -> 50
J27: WEIGHTED AVERAGE COST OF CAPITAL | M27: =SUMPRODUCT(L25:L26,M25:M26) -> 0.085432439
