Workbook
Name UPDATE: 'Data Sheet'!$E$1

Sheet FINANCIALS
B2: ="HISTORICAL FINANCIAL STATEMENT - "&'Data Sheet'!B1 -> HISTORICAL FINANCIAL STATEMENT - WIPRO LTD
B3: YEARS | C3: ='Data Sheet'!B16 -> 42825 | D3: ='Data Sheet'!C16 -> 43190 | E3: ='Data Sheet'!D16 -> 43555 | F3: ='Data Sheet'!E16 -> 43921 | G3: ='Data Sheet'!F16 -> 44286 | H3: ='Data Sheet'!G16 -> 44651 | I3: ='Data Sheet'!H16 -> 45016 | J3: ='Data Sheet'!I16 -> 45382 | ... L3: ='Data Sheet'!K16 -> 46112 | M3: LTM
A4: # | B4: INCOME STATEMENT (IN CRORES)
B5: SALES | C5: =IFERROR('Data Sheet'!B17,0) -> 55448.4 | D5: =IFERROR('Data Sheet'!C17,0) -> 54487.1 | E5: =IFERROR('Data Sheet'!D17,0) -> 59018.9 | F5: =IFERROR('Data Sheet'!E17,0) -> 61137.6 | G5: =IFERROR('Data Sheet'!F17,0) -> 61934.9 | H5: =IFERROR('Data Sheet'!G17,0) -> 79312 | I5: =IFERROR('Data Sheet'!H17,0) -> 90487.6 | J5: =IFERROR('Data Sheet'!I17,0) -> 89760.3 | ... L5: =IFERROR('Data Sheet'!K17,0) -> 92624 | M5: =IFERROR(SUM('Data Sheet'!H42:K42),0) -> 94968
B6: SALES GROWTH | C6: - | D6: =D5/C5-1 -> -0.017336839 | E6: =E5/D5-1 -> 0.08317198 | F6: =F5/E5-1 -> 0.03589867 | G6: =G5/F5-1 -> 0.013041075 | H6: =H5/G5-1 -> 0.28057041 | I6: =I5/H5-1 -> 0.1409068 | J6: =J5/I5-1 -> -0.0080375654 | K6: =K5/J5-1 -> -0.0074854919 | ... M6: =M5/L5-1 -> 0.025306616
B8: COGS | C8: =IFERROR(SUM('Data Sheet'!B18,'Data Sheet'!B20,'Data Sheet'!B21,'Data Sheet'!B22-1*'Data Sheet'!B19),0) -> 29505.2 | D8: =IFERROR(SUM('Data Sheet'!C18,'Data Sheet'!C20,'Data Sheet'!C21,'Data Sheet'!C22-1*'Data Sheet'!C19),0) -> 29116.2 | E8: =IFERROR(SUM('Data Sheet'!D18,'Data Sheet'!D20,'Data Sheet'!D21,'Data Sheet'!D22-1*'Data Sheet'!D19),0) -> 31317.4 | F8: =IFERROR(SUM('Data Sheet'!E18,'Data Sheet'!E20,'Data Sheet'!E21,'Data Sheet'!E22-1*'Data Sheet'!E19),0) -> 33795.3 | G8: =IFERROR(SUM('Data Sheet'!F18,'Data Sheet'!F20,'Data Sheet'!F21,'Data Sheet'!F22-1*'Data Sheet'!F19),0) -> 33964.3 | H8: =IFERROR(SUM('Data Sheet'!G18,'Data Sheet'!G20,'Data Sheet'!G21,'Data Sheet'!G22-1*'Data Sheet'!G19),0) -> 46972 | I8: =IFERROR(SUM('Data Sheet'!H18,'Data Sheet'!H20,'Data Sheet'!H21,'Data Sheet'!H22-1*'Data Sheet'!H19),0) -> 56300.5 | J8: =IFERROR(SUM('Data Sheet'!I18,'Data Sheet'!I20,'Data Sheet'!I21,'Data Sheet'!I22-1*'Data Sheet'!I19),0) -> 57178.9 | ... L8: =IFERROR(SUM('Data Sheet'!K18,'Data Sheet'!K20,'Data Sheet'!K21,'Data Sheet'!K22-1*'Data Sheet'!K19),0) -> 58350.1 | M8: =IFERROR(SUM('Data Sheet'!H43:K43),0) -> 76757.2
B9: COGS % SALES | C9: =C8/C5 -> 0.53211995 | D9: =D8/D5 -> 0.53436869 | E9: =E8/E5 -> 0.53063341 | F9: =F8/F5 -> 0.5527744 | G9: =G8/G5 -> 0.5483871 | H9: =H8/H5 -> 0.59224329 | I9: =I8/I5 -> 0.62219022 | J9: =J8/J5 -> 0.6370177 | ... M9: =M8/M5 -> 0.80824278
B11: GROSS PROFIT | C11: =C5-C8 -> 25943.2 | D11: =D5-D8 -> 25370.9 | E11: =E5-E8 -> 27701.5 | F11: =F5-F8 -> 27342.3 | G11: =G5-G8 -> 27970.6 | H11: =H5-H8 -> 32340 | I11: =I5-I8 -> 34187.1 | J11: =J5-J8 -> 32581.4 | ... M11: =M5-M8 -> 18210.8
B12: GROSS PROFIT % SALES | C12: =C11/C5 -> 0.46788005 | D12: =D11/D5 -> 0.46563131 | E12: =E11/E5 -> 0.46936659 | F12: =F11/F5 -> 0.4472256 | G12: =G11/G5 -> 0.4516129 | H12: =H11/H5 -> 0.40775671 | I12: =I11/I5 -> 0.37780978 | J12: =J11/J5 -> 0.3629823 | ... M12: =M11/M5 -> 0.19175722
B14: SELLING &GENERAL EXPENSES | C14: =IFERROR(SUM('Data Sheet'!B23:B24),0) -> 14622.3 | D14: =IFERROR(SUM('Data Sheet'!C23:C24),0) -> 14983.8 | E14: =IFERROR(SUM('Data Sheet'!D23:D24),0) -> 16088.9 | F14: =IFERROR(SUM('Data Sheet'!E23:E24),0) -> 15000 | G14: =IFERROR(SUM('Data Sheet'!F23:F24),0) -> 13199.2 | H14: =IFERROR(SUM('Data Sheet'!G23:G24),0) -> 15655.8 | I14: =IFERROR(SUM('Data Sheet'!H23:H24),0) -> 17348.1 | J14: =IFERROR(SUM('Data Sheet'!I23:I24),0) -> 15828.9 | ... M14: =IFERROR(SUM('Data Sheet'!L23:L24),0) -> 0
B15: SG EXP % SALES | C15: =C14/C5 -> 0.26371004 | D15: =D14/D5 -> 0.2749972 | E15: =E14/E5 -> 0.27260589 | F15: =F14/F5 -> 0.2453482 | G15: =G14/G5 -> 0.21311409 | H15: =H14/H5 -> 0.1973951 | I15: =I14/I5 -> 0.19171798 | J15: =J14/J5 -> 0.17634634 | ... L15: =L14/L5 -> 0.17773687
B17: EBITDA | C17: =C11-C14 -> 11320.9 | D17: =D11-D14 -> 10387.1 | E17: =E11-E14 -> 11612.6 | F17: =F11-F14 -> 12342.3 | G17: =G11-G14 -> 14771.4 | H17: =H11-H14 -> 16684.2 | I17: =I11-I14 -> 16839 | J17: =J11-J14 -> 16752.5 | ... M17: =M11-M14 -> 18210.8
B18: EBITDA % SALES | C18: =C17/C5 -> 0.20417 | D18: =D17/D5 -> 0.19063411 | E18: =E17/E5 -> 0.1967607 | F18: =F17/F5 -> 0.2018774 | G18: =G17/G5 -> 0.23849881 | H18: =H17/H5 -> 0.21036161 | I18: =I17/I5 -> 0.1860918 | J18: =J17/J5 -> 0.18663596 | ... M18: =M17/M5 -> 0.19175722
B20: INTEREST | C20: =IFERROR('Data Sheet'!B27,0) -> 594.2 | D20: =IFERROR('Data Sheet'!C27,0) -> 583 | E20: =IFERROR('Data Sheet'!D27,0) -> 737.5 | F20: =IFERROR('Data Sheet'!E27,0) -> 732.8 | G20: =IFERROR('Data Sheet'!F27,0) -> 508.8 | H20: =IFERROR('Data Sheet'!G27,0) -> 532.5 | I20: =IFERROR('Data Sheet'!H27,0) -> 1007.7 | J20: =IFERROR('Data Sheet'!I27,0) -> 1255.2 | ... L20: =IFERROR('Data Sheet'!K27,0) -> 1457.7 | M20: =IFERROR(SUM('Data Sheet'!H46:K46),0) -> 1569.7
B21: INTEREST % SALES | C21: =C20/C5 -> 0.01071627 | D21: =D20/D5 -> 0.01069978 | E21: =E20/E5 -> 0.012495997 | F21: =F20/F5 -> 0.011986077 | G21: =G20/G5 -> 0.0082150774 | H21: =H20/H5 -> 0.0067139903 | I21: =I20/I5 -> 0.011136332 | J21: =J20/J5 -> 0.01398391 | ... M21: =M20/M5 -> 0.016528725
B23: DEPRECIATION | C23: =IFERROR('Data Sheet'!B26,0) -> 2310 | D23: =IFERROR('Data Sheet'!C26,0) -> 2111.7 | E23: =IFERROR('Data Sheet'!D26,0) -> 1946.7 | F23: =IFERROR('Data Sheet'!E26,0) -> 2085.5 | G23: =IFERROR('Data Sheet'!F26,0) -> 2763.4 | H23: =IFERROR('Data Sheet'!G26,0) -> 3077.8 | I23: =IFERROR('Data Sheet'!H26,0) -> 3340.2 | J23: =IFERROR('Data Sheet'!I26,0) -> 3407.1 | ... L23: =IFERROR('Data Sheet'!K26,0) -> 2910.7 | M23: =IFERROR(SUM('Data Sheet'!H45:K45),0) -> 3029.6
B24: DEPRECIATION% SALES | C24: =C23/C8 -> 0.078291284 | D24: =D23/D8 -> 0.072526635 | E24: =E23/E8 -> 0.062160333 | F24: =F23/F8 -> 0.061709764 | G24: =G23/G8 -> 0.081361901 | H24: =H23/H8 -> 0.065524142 | I24: =I23/I8 -> 0.05932807 | J24: =J23/J8 -> 0.059586666 | ... M24: =M23/M8 -> 0.039469913
B26: EARNINGS BEFORE TAX | C26: =IFERROR(C17-SUM(C20,C23),0) -> 8416.7 | D26: =IFERROR(D17-SUM(D20,D23),0) -> 7692.4 | E26: =IFERROR(E17-SUM(E20,E23),0) -> 8928.4 | F26: =IFERROR(F17-SUM(F20,F23),0) -> 9524 | G26: =IFERROR(G17-SUM(G20,G23),0) -> 11499.2 | H26: =IFERROR(H17-SUM(H20,H23),0) -> 13073.9 | I26: =IFERROR(I17-SUM(I20,I23),0) -> 12491.1 | J26: =IFERROR(J17-SUM(J20,J23),0) -> 12090.2 | ... M26: =IFERROR(M17-SUM(M20,M23),0) -> 13611.5
B27: EBT % SALES | C27: =C26/C5 -> 0.15179338 | D27: =D26/D5 -> 0.14117837 | E27: =E26/E5 -> 0.15128035 | F27: =F26/F5 -> 0.15577975 | G27: =G26/G5 -> 0.18566592 | H27: =H26/H5 -> 0.16484139 | I27: =I26/I5 -> 0.13804212 | J27: =J26/J5 -> 0.13469429 | ... M27: =M26/M5 -> 0.14332723
B29: TAX | C29: =IFERROR('Data Sheet'!B29,0) -> 2521.4 | D29: =IFERROR('Data Sheet'!C29,0) -> 2239.1 | E29: =IFERROR('Data Sheet'!D29,0) -> 2524.3 | F29: =IFERROR('Data Sheet'!E29,0) -> 2480.1 | G29: =IFERROR('Data Sheet'!F29,0) -> 3034.9 | H29: =IFERROR('Data Sheet'!G29,0) -> 2897.4 | I29: =IFERROR('Data Sheet'!H29,0) -> 3399.2 | J29: =IFERROR('Data Sheet'!I29,0) -> 3608.9 | ... L29: =IFERROR('Data Sheet'!K29,0) -> 4076.7 | M29: =IFERROR(SUM('Data Sheet'!H48:K48),0) -> 4133.1
B30: EFFECTIVE TAX RATE | C30: =C29/C26 -> 0.29957109 | D30: =D29/D26 -> 0.29107951 | E30: =E29/E26 -> 0.28272703 | F30: =F29/F26 -> 0.26040529 | G30: =G29/G26 -> 0.26392271 | H30: =H29/H26 -> 0.22161712 | I30: =I29/I26 -> 0.27212976 | J30: =J29/J26 -> 0.29849796 | ... M30: =M29/M26 -> 0.30364765
B32: NET PROFIT | C32: =C26-C29 -> 5895.3 | D32: =D26-D29 -> 5453.3 | E32: =E26-E29 -> 6404.1 | F32: =F26-F29 -> 7043.9 | G32: =G26-G29 -> 8464.3 | H32: =H26-H29 -> 10176.5 | I32: =I26-I29 -> 9091.9 | J32: =J26-J29 -> 8481.3 | ... M32: =M26-M29 -> 9478.4
B33: NET PROFIT % SALES | C33: =IFERROR(C32/C5,0) -> 0.10632047 | D33: =IFERROR(D32/D5,0) -> 0.10008424 | E33: =IFERROR(E32/E5,0) -> 0.10850931 | F33: =IFERROR(F32/F5,0) -> 0.11521388 | G33: =IFERROR(G32/G5,0) -> 0.13666447 | H33: =IFERROR(H32/H5,0) -> 0.12830971 | I33: =IFERROR(I32/I5,0) -> 0.10047675 | J33: =IFERROR(J32/J5,0) -> 0.094488321 | ... M33: =IFERROR(M32/M5,0) -> 0.099806251
B35: NO OF EQUITY SHARES | C35: =IFERROR('Data Sheet'!B93,0) -> 1296.48 | D35: =IFERROR('Data Sheet'!C93,0) -> 1206.35 | E35: =IFERROR('Data Sheet'!D93,0) -> 1206.79 | F35: =IFERROR('Data Sheet'!E93,0) -> 1142.67 | G35: =IFERROR('Data Sheet'!F93,0) -> 1095.83 | H35: =IFERROR('Data Sheet'!G93,0) -> 1096.41 | I35: =IFERROR('Data Sheet'!H93,0) -> 1097.58 | J35: =IFERROR('Data Sheet'!I93,0) -> 1045.03 | ... M35: =IFERROR('Data Sheet'!L93,0) -> 0
B37: EPS | C37: =IFERROR(C32/C35,0) -> 4.5471585 | D37: =IFERROR(D32/D35,0) -> 4.5204957 | E37: =IFERROR(E32/E35,0) -> 5.3067228 | F37: =IFERROR(F32/F35,0) -> 6.1644219 | G37: =IFERROR(G32/G35,0) -> 7.7240995 | H37: =IFERROR(H32/H35,0) -> 9.2816556 | I37: =IFERROR(I32/I35,0) -> 8.2835875 | J37: =IFERROR(J32/J35,0) -> 8.1158436 | ... M37: =IFERROR(M32/M35,0) -> 0
B38: EPS GROWTH % | D38: =IFERROR(D37/C37-1,0) -> -0.0058636069 | E38: =E37/D37-1 -> 0.17392497 | F38: =F37/E37-1 -> 0.16162501 | G38: =G37/F37-1 -> 0.25301279 | H38: =H37/G37-1 -> 0.20164888 | I38: =I37/H37-1 -> -0.10753125 | J38: =J37/I37-1 -> -0.020250159 | K38: =K37/J37-1 -> 0.095259227 | L38: =L37/K37-1 -> 0.0046133859 | M38: =M37/L37-1 -> -1
B40: DIVIDEND PER SHARE | C40: =IFERROR('Data Sheet'!B31/FINANCIALS!C35,0) -> 0.37493829 | D40: =IFERROR('Data Sheet'!C31/FINANCIALS!D35,0) -> 0.37501554 | E40: =IFERROR('Data Sheet'!D31/FINANCIALS!E35,0) -> 0.50000414 | F40: =IFERROR('Data Sheet'!E31/FINANCIALS!F35,0) -> 0.50001313 | G40: =IFERROR('Data Sheet'!F31/FINANCIALS!G35,0) -> 0.49998631 | H40: =IFERROR('Data Sheet'!G31/FINANCIALS!H35,0) -> 2.9999726 | I40: =IFERROR('Data Sheet'!H31/FINANCIALS!I35,0) -> 0.50000911 | J40: =IFERROR('Data Sheet'!I31/FINANCIALS!J35,0) -> 0.49998565 | ... M40: =IFERROR('Data Sheet'!L31/FINANCIALS!M35,0) -> 0
B41: DIVIDEND PAYOUT RATIO | C41: =IFERROR(C40/C37,0) -> 0.082455515 | D41: =IFERROR(D40/D37,0) -> 0.082958942 | E41: =IFERROR(E40/E37,0) -> 0.09422089 | F41: =IFERROR(F40/F37,0) -> 0.081112736 | G41: =IFERROR(G40/G37,0) -> 0.064730692 | H41: =IFERROR(H40/H37,0) -> 0.32321525 | I41: =IFERROR(I40/I37,0) -> 0.060361421 | J41: =IFERROR(J40/J37,0) -> 0.061606122 | ... M41: =IFERROR(M40/M37,0) -> 0
B43: RETAINED EARNINGS | C43: =IFERROR(IF(C37>C40,1-C41,0),0) -> 0.91754448 | D43: =IFERROR(IF(D37>D40,1-D41,0),0) -> 0.91704106 | E43: =IFERROR(IF(E37>E40,1-E41,0),0) -> 0.90577911 | F43: =IFERROR(IF(F37>F40,1-F41,0),0) -> 0.91888726 | G43: =IFERROR(IF(G37>G40,1-G41,0),0) -> 0.93526931 | H43: =IFERROR(IF(H37>H40,1-H41,0),0) -> 0.67678475 | I43: =IFERROR(IF(I37>I40,1-I41,0),0) -> 0.93963858 | J43: =IFERROR(IF(J37>J40,1-J41,0),0) -> 0.93839388 | ... M43: =IFERROR(IF(M37>M40,1-M41,0),0) -> 0
B48: YEARS | C48: 42825 | D48: 43190 | E48: 43555 | F48: 43921 | G48: 44286 | H48: 44651 | I48: 45016 | J48: 45382 | K48: 45747 | L48: 46112 | M48: LTM
A49: # | B49: BALANCE SHEET
B50: Equity Share Capital | C50: =IFERROR('Data Sheet'!B57,0) -> 486.1 | D50: =IFERROR('Data Sheet'!C57,0) -> 904.8 | E50: =IFERROR('Data Sheet'!D57,0) -> 1206.8 | F50: =IFERROR('Data Sheet'!E57,0) -> 1142.7 | G50: =IFERROR('Data Sheet'!F57,0) -> 1095.8 | H50: =IFERROR('Data Sheet'!G57,0) -> 1096.4 | I50: =IFERROR('Data Sheet'!H57,0) -> 1097.6 | J50: =IFERROR('Data Sheet'!I57,0) -> 1045 | ... L50: =IFERROR('Data Sheet'!K57,0) -> 2097.7
B51: Reserves | C51: =IFERROR('Data Sheet'!B58,0) -> 51184.1 | D51: =IFERROR('Data Sheet'!C58,0) -> 47021.5 | E51: =IFERROR('Data Sheet'!D58,0) -> 55215.8 | F51: =IFERROR('Data Sheet'!E58,0) -> 54179 | G51: =IFERROR('Data Sheet'!F58,0) -> 53805.2 | H51: =IFERROR('Data Sheet'!G58,0) -> 64306.6 | I51: =IFERROR('Data Sheet'!H58,0) -> 76570.3 | J51: =IFERROR('Data Sheet'!I58,0) -> 73488 | ... L51: =IFERROR('Data Sheet'!K58,0) -> 85920.6
B52: Borrowings | C52: =IFERROR('Data Sheet'!B59,0) -> 14241.2 | D52: =IFERROR('Data Sheet'!C59,0) -> 13901.2 | E52: =IFERROR('Data Sheet'!D59,0) -> 9946.7 | F52: =IFERROR('Data Sheet'!E59,0) -> 9724 | G52: =IFERROR('Data Sheet'!F59,0) -> 10451.4 | H52: =IFERROR('Data Sheet'!G59,0) -> 17592.9 | I52: =IFERROR('Data Sheet'!H59,0) -> 17466.6 | J52: =IFERROR('Data Sheet'!I59,0) -> 16464.9 | ... L52: =IFERROR('Data Sheet'!K59,0) -> 20291
B53: Other Liabilities | C53: =IFERROR('Data Sheet'!B60,0) -> 12760.8 | D53: =IFERROR('Data Sheet'!C60,0) -> 13563.3 | E53: =IFERROR('Data Sheet'!D60,0) -> 16217.1 | F53: =IFERROR('Data Sheet'!E60,0) -> 15953.9 | G53: =IFERROR('Data Sheet'!F60,0) -> 17213.4 | H53: =IFERROR('Data Sheet'!G60,0) -> 24279.7 | I53: =IFERROR('Data Sheet'!H60,0) -> 21789.2 | J53: =IFERROR('Data Sheet'!I60,0) -> 23611 | ... L53: =IFERROR('Data Sheet'!K60,0) -> 32574.2
B54: Total LIABILITY | C54: =IFERROR('Data Sheet'!B61,0) -> 78672.2 | D54: =IFERROR('Data Sheet'!C61,0) -> 75390.8 | E54: =IFERROR('Data Sheet'!D61,0) -> 82586.4 | F54: =IFERROR('Data Sheet'!E61,0) -> 80999.6 | G54: =IFERROR('Data Sheet'!F61,0) -> 82565.8 | H54: =IFERROR('Data Sheet'!G61,0) -> 107275.6 | I54: =IFERROR('Data Sheet'!H61,0) -> 116923.7 | J54: =IFERROR('Data Sheet'!I61,0) -> 114608.9 | ... L54: =IFERROR('Data Sheet'!K61,0) -> 140883.5
B56: FIXED ASSETS NET BLOCK | C56: =IFERROR('Data Sheet'!B62,0) -> 19886.5 | D56: =IFERROR('Data Sheet'!C62,0) -> 18126.7 | E56: =IFERROR('Data Sheet'!D62,0) -> 17464.7 | F56: =IFERROR('Data Sheet'!E62,0) -> 22062.1 | G56: =IFERROR('Data Sheet'!F62,0) -> 23040.3 | H56: =IFERROR('Data Sheet'!G62,0) -> 37989.6 | I56: =IFERROR('Data Sheet'!H62,0) -> 44756.8 | J56: =IFERROR('Data Sheet'!I62,0) -> 43628 | ... L56: =IFERROR('Data Sheet'!K62,0) -> 51690.1
B57: Capital Work in Progress | C57: =IFERROR('Data Sheet'!B63,0) -> 737.7 | D57: =IFERROR('Data Sheet'!C63,0) -> 1377.7 | E57: =IFERROR('Data Sheet'!D63,0) -> 2141.8 | F57: =IFERROR('Data Sheet'!E63,0) -> 1881.1 | G57: =IFERROR('Data Sheet'!F63,0) -> 1853.2 | H57: =IFERROR('Data Sheet'!G63,0) -> 1601.5 | I57: =IFERROR('Data Sheet'!H63,0) -> 617.1 | J57: =IFERROR('Data Sheet'!I63,0) -> 723.4 | ... L57: =IFERROR('Data Sheet'!K63,0) -> 412.2
B58: Investments | C58: =IFERROR('Data Sheet'!B64,0) -> 29913.3 | D58: =IFERROR('Data Sheet'!C64,0) -> 25796.8 | E58: =IFERROR('Data Sheet'!D64,0) -> 22886.7 | F58: =IFERROR('Data Sheet'!E64,0) -> 20032 | G58: =IFERROR('Data Sheet'!F64,0) -> 18774.7 | H58: =IFERROR('Data Sheet'!G64,0) -> 26153.8 | I58: =IFERROR('Data Sheet'!H64,0) -> 33073.2 | J58: =IFERROR('Data Sheet'!I64,0) -> 33384.4 | ... L58: =IFERROR('Data Sheet'!K64,0) -> 46785.9
B59: Other Assets | C59: =IFERROR('Data Sheet'!B65-SUM('Data Sheet'!B67:B69),0) -> 12987.6 | D59: =IFERROR('Data Sheet'!C65-SUM('Data Sheet'!C67:C69),0) -> 15161.1 | E59: =IFERROR('Data Sheet'!D65-SUM('Data Sheet'!D67:D69),0) -> 13796.3 | F59: =IFERROR('Data Sheet'!E65-SUM('Data Sheet'!E67:E69),0) -> 11940.6 | G59: =IFERROR('Data Sheet'!F65-SUM('Data Sheet'!F67:F69),0) -> 12382.1 | H59: =IFERROR('Data Sheet'!G65-SUM('Data Sheet'!G67:G69),0) -> 19491.8 | I59: =IFERROR('Data Sheet'!H65-SUM('Data Sheet'!H67:H69),0) -> 16534.8 | J59: =IFERROR('Data Sheet'!I65-SUM('Data Sheet'!I67:I69),0) -> 15539.4 | ... L59: =IFERROR('Data Sheet'!K65-SUM('Data Sheet'!K67:K69),0) -> 17798
B60: Total Assets Non current | C60: =IFERROR(SUM(C56:C59),0) -> 63525.1 | D60: =IFERROR(SUM(D56:D59),0) -> 60462.3 | E60: =IFERROR(SUM(E56:E59),0) -> 56289.5 | F60: =IFERROR(SUM(F56:F59),0) -> 55915.8 | G60: =IFERROR(SUM(G56:G59),0) -> 56050.3 | H60: =IFERROR(SUM(H56:H59),0) -> 85236.7 | I60: =IFERROR(SUM(I56:I59),0) -> 94981.9 | J60: =IFERROR(SUM(J56:J59),0) -> 93275.2 | ... L60: =IFERROR(SUM(L56:L59),0) -> 116686.2
B62: Receivables | C62: =IFERROR('Data Sheet'!B67,0) -> 9484.6 | D62: =IFERROR('Data Sheet'!C67,0) -> 10099 | E62: =IFERROR('Data Sheet'!D67,0) -> 10048.9 | F62: =IFERROR('Data Sheet'!E67,0) -> 10447.4 | G62: =IFERROR('Data Sheet'!F67,0) -> 9429.8 | H62: =IFERROR('Data Sheet'!G67,0) -> 11521.9 | I62: =IFERROR('Data Sheet'!H67,0) -> 12635 | J62: =IFERROR('Data Sheet'!I67,0) -> 11547.7 | ... L62: =IFERROR('Data Sheet'!K67,0) -> 13590.1
B63: Inventory | C63: =IFERROR('Data Sheet'!B68,0) -> 391.5 | D63: =IFERROR('Data Sheet'!C68,0) -> 337 | E63: =IFERROR('Data Sheet'!D68,0) -> 395.1 | F63: =IFERROR('Data Sheet'!E68,0) -> 186.5 | G63: =IFERROR('Data Sheet'!F68,0) -> 106.4 | H63: =IFERROR('Data Sheet'!G68,0) -> 133.4 | I63: =IFERROR('Data Sheet'!H68,0) -> 118.8 | J63: =IFERROR('Data Sheet'!I68,0) -> 90.7 | ... L63: =IFERROR('Data Sheet'!K68,0) -> 51.7
B64: Cash & Bank | C64: =IFERROR('Data Sheet'!B69,0) -> 5271 | D64: =IFERROR('Data Sheet'!C69,0) -> 4492.5 | E64: =IFERROR('Data Sheet'!D69,0) -> 15852.9 | F64: =IFERROR('Data Sheet'!E69,0) -> 14449.9 | G64: =IFERROR('Data Sheet'!F69,0) -> 16979.3 | H64: =IFERROR('Data Sheet'!G69,0) -> 10383.6 | I64: =IFERROR('Data Sheet'!H69,0) -> 9188 | J64: =IFERROR('Data Sheet'!I69,0) -> 9695.3 | ... L64: =IFERROR('Data Sheet'!K69,0) -> 10555.5
B65: Total current assets | C65: =IFERROR(SUM(C62:C64),0) -> 15147.1 | D65: =IFERROR(SUM(D62:D64),0) -> 14928.5 | E65: =IFERROR(SUM(E62:E64),0) -> 26296.9 | F65: =IFERROR(SUM(F62:F64),0) -> 25083.8 | G65: =IFERROR(SUM(G62:G64),0) -> 26515.5 | H65: =IFERROR(SUM(H62:H64),0) -> 22038.9 | I65: =IFERROR(SUM(I62:I64),0) -> 21941.8 | J65: =IFERROR(SUM(J62:J64),0) -> 21333.7 | ... L65: =IFERROR(SUM(L62:L64),0) -> 24197.3
B67: Total assets | C67: =IFERROR(SUM(C65,C60),0) -> 78672.2 | D67: =IFERROR(SUM(D65,D60),0) -> 75390.8 | E67: =IFERROR(SUM(E65,E60),0) -> 82586.4 | F67: =IFERROR(SUM(F65,F60),0) -> 80999.6 | G67: =IFERROR(SUM(G65,G60),0) -> 82565.8 | H67: =IFERROR(SUM(H65,H60),0) -> 107275.6 | I67: =IFERROR(SUM(I65,I60),0) -> 116923.7 | J67: =IFERROR(SUM(J65,J60),0) -> 114608.9 | ... L67: =IFERROR(SUM(L65,L60),0) -> 140883.5
B68: CHECK | C68: =C67=C54 -> TRUE | D68: =D67=D54 -> TRUE | E68: =E67=E54 -> TRUE | F68: =F67=F54 -> TRUE | G68: =G67=G54 -> TRUE | H68: =H67=H54 -> TRUE | I68: =I67=I54 -> TRUE | J68: =J67=J54 -> TRUE | ... L68: =L67=L54 -> TRUE
A72: # | B72: CASH FLOW STATEMENT
B73: operating activities
B74: Profit from operations | C74: =IFERROR('HISTORICAL FS'!V6,0) -> 28840 | D74: =IFERROR('HISTORICAL FS'!W6,0) -> 33312 | E74: =IFERROR('HISTORICAL FS'!X6,0) -> 28771 | F74: =IFERROR('HISTORICAL FS'!Y6,0) -> 23352 | G74: =IFERROR('HISTORICAL FS'!Z6,0) -> 31198 | H74: =IFERROR('HISTORICAL FS'!AA6,0) -> 26943 | I74: =IFERROR('HISTORICAL FS'!AB6,0) -> 41694 | J74: =IFERROR('HISTORICAL FS'!AC6,0) -> 65106 | ... L74: =IFERROR('HISTORICAL FS'!AE6,0) -> 25393
B75: Receivables | C75: =IFERROR('HISTORICAL FS'!V7,0) -> -4152 | D75: =IFERROR('HISTORICAL FS'!W7,0) -> -10688 | E75: =IFERROR('HISTORICAL FS'!X7,0) -> -9109 | F75: =IFERROR('HISTORICAL FS'!Y7,0) -> 9950 | G75: =IFERROR('HISTORICAL FS'!Z7,0) -> -5505 | H75: =IFERROR('HISTORICAL FS'!AA7,0) -> 185 | I75: =IFERROR('HISTORICAL FS'!AB7,0) -> -2213 | J75: =IFERROR('HISTORICAL FS'!AC7,0) -> -1876 | ... L75: =IFERROR('HISTORICAL FS'!AE7,0) -> -1587
B76: Inventory | C76: =IFERROR('HISTORICAL FS'!V8,0) -> -6621 | D76: =IFERROR('HISTORICAL FS'!W8,0) -> -3560 | E76: =IFERROR('HISTORICAL FS'!X8,0) -> 2069 | F76: =IFERROR('HISTORICAL FS'!Y8,0) -> 2326 | G76: =IFERROR('HISTORICAL FS'!Z8,0) -> 3814 | H76: =IFERROR('HISTORICAL FS'!AA8,0) -> 472 | I76: =IFERROR('HISTORICAL FS'!AB8,0) -> -5665 | J76: =IFERROR('HISTORICAL FS'!AC8,0) -> -7265 | ... L76: =IFERROR('HISTORICAL FS'!AE8,0) -> -4318
B77: Payables | C77: =IFERROR('HISTORICAL FS'!V9,0) -> 9301 | D77: =IFERROR('HISTORICAL FS'!W9,0) -> 7320 | E77: =IFERROR('HISTORICAL FS'!X9,0) -> -4692 | F77: =IFERROR('HISTORICAL FS'!Y9,0) -> -8085 | G77: =IFERROR('HISTORICAL FS'!Z9,0) -> 5748 | H77: =IFERROR('HISTORICAL FS'!AA9,0) -> -7012 | I77: =IFERROR('HISTORICAL FS'!AB9,0) -> 6945 | J77: =IFERROR('HISTORICAL FS'!AC9,0) -> 13706 | ... L77: =IFERROR('HISTORICAL FS'!AE9,0) -> -1973
B78: Loans Advances | C78: =IFERROR('HISTORICAL FS'!V10,0) -> 0 | D78: =IFERROR('HISTORICAL FS'!W10,0) -> 0 | E78: =IFERROR('HISTORICAL FS'!X10,0) -> 0 | F78: =IFERROR('HISTORICAL FS'!Y10,0) -> 0 | G78: =IFERROR('HISTORICAL FS'!Z10,0) -> 0 | H78: =IFERROR('HISTORICAL FS'!AA10,0) -> 0 | I78: =IFERROR('HISTORICAL FS'!AB10,0) -> 0 | J78: =IFERROR('HISTORICAL FS'!AC10,0) -> 0 | ... L78: =IFERROR('HISTORICAL FS'!AE10,0) -> -815
B79: Other WC items | C79: =IFERROR('HISTORICAL FS'!V11,0) -> 4727 | D79: =IFERROR('HISTORICAL FS'!W11,0) -> 494 | E79: =IFERROR('HISTORICAL FS'!X11,0) -> 4512 | F79: =IFERROR('HISTORICAL FS'!Y11,0) -> 875 | G79: =IFERROR('HISTORICAL FS'!Z11,0) -> -4150 | H79: =IFERROR('HISTORICAL FS'!AA11,0) -> -4396 | I79: =IFERROR('HISTORICAL FS'!AB11,0) -> -2194 | J79: =IFERROR('HISTORICAL FS'!AC11,0) -> 2760 | ... L79: =IFERROR('HISTORICAL FS'!AE11,0) -> -345
B80: Working capital changes | C80: =IFERROR('HISTORICAL FS'!V12,0) -> 3254 | D80: =IFERROR('HISTORICAL FS'!W12,0) -> -6434 | E80: =IFERROR('HISTORICAL FS'!X12,0) -> -7221 | F80: =IFERROR('HISTORICAL FS'!Y12,0) -> 5065 | G80: =IFERROR('HISTORICAL FS'!Z12,0) -> -93 | H80: =IFERROR('HISTORICAL FS'!AA12,0) -> -10750 | I80: =IFERROR('HISTORICAL FS'!AB12,0) -> -3127 | J80: =IFERROR('HISTORICAL FS'!AC12,0) -> 7325 | ... L80: =IFERROR('HISTORICAL FS'!AE12,0) -> -9038
B81: Direct taxes | C81: =IFERROR('HISTORICAL FS'!V13,0) -> -1895 | D81: =IFERROR('HISTORICAL FS'!W13,0) -> -3021 | E81: =IFERROR('HISTORICAL FS'!X13,0) -> -2659 | F81: =IFERROR('HISTORICAL FS'!Y13,0) -> -1785 | G81: =IFERROR('HISTORICAL FS'!Z13,0) -> -2105 | H81: =IFERROR('HISTORICAL FS'!AA13,0) -> -1910 | I81: =IFERROR('HISTORICAL FS'!AB13,0) -> -3179 | J81: =IFERROR('HISTORICAL FS'!AC13,0) -> -4516 | ... L81: =IFERROR('HISTORICAL FS'!AE13,0) -> -3314
B82: Cash from operating activities | C82: =SUM(C74:C81) -> 33454 | D82: =SUM(D74:D81) -> 17423 | E82: =SUM(E74:E81) -> 11671 | F82: =SUM(F74:F81) -> 31698 | G82: =SUM(G74:G81) -> 28907 | H82: =SUM(H74:H81) -> 3532 | I82: =SUM(I74:I81) -> 32261 | J82: =SUM(J74:J81) -> 75240 | ... L82: =SUM(L74:L81) -> 4003
B85: Investing activities
B86: Fixed assets purchased | C86: =IFERROR('HISTORICAL FS'!V15,0) -> -16072 | D86: =IFERROR('HISTORICAL FS'!W15,0) -> -35079 | E86: =IFERROR('HISTORICAL FS'!X15,0) -> -35304 | F86: =IFERROR('HISTORICAL FS'!Y15,0) -> -29702 | G86: =IFERROR('HISTORICAL FS'!Z15,0) -> -20205 | H86: =IFERROR('HISTORICAL FS'!AA15,0) -> -15168 | I86: =IFERROR('HISTORICAL FS'!AB15,0) -> -19230 | J86: =IFERROR('HISTORICAL FS'!AC15,0) -> -31414 | ... L86: =IFERROR('HISTORICAL FS'!AE15,0) -> -36282
B87: Fixed assets sold | C87: =IFERROR('HISTORICAL FS'!V16,0) -> 53 | D87: =IFERROR('HISTORICAL FS'!W16,0) -> 30 | E87: =IFERROR('HISTORICAL FS'!X16,0) -> 67 | F87: =IFERROR('HISTORICAL FS'!Y16,0) -> 171 | G87: =IFERROR('HISTORICAL FS'!Z16,0) -> 351 | H87: =IFERROR('HISTORICAL FS'!AA16,0) -> 230 | I87: =IFERROR('HISTORICAL FS'!AB16,0) -> 285 | J87: =IFERROR('HISTORICAL FS'!AC16,0) -> 231 | ... L87: =IFERROR('HISTORICAL FS'!AE16,0) -> 46
B88: Investments purchased | C88: =IFERROR('HISTORICAL FS'!V17,0) -> -6 | D88: =IFERROR('HISTORICAL FS'!W17,0) -> -329 | E88: =IFERROR('HISTORICAL FS'!X17,0) -> -130 | F88: =IFERROR('HISTORICAL FS'!Y17,0) -> -1439 | G88: =IFERROR('HISTORICAL FS'!Z17,0) -> -7530 | H88: =IFERROR('HISTORICAL FS'!AA17,0) -> -3008 | I88: =IFERROR('HISTORICAL FS'!AB17,0) -> -50 | J88: =IFERROR('HISTORICAL FS'!AC17,0) -> -74 | ... L88: =IFERROR('HISTORICAL FS'!AE17,0) -> -102
B89: Investments sold | C89: =IFERROR('HISTORICAL FS'!V18,0) -> 1965 | D89: =IFERROR('HISTORICAL FS'!W18,0) -> 2381 | E89: =IFERROR('HISTORICAL FS'!X18,0) -> 5644 | F89: =IFERROR('HISTORICAL FS'!Y18,0) -> 21 | G89: =IFERROR('HISTORICAL FS'!Z18,0) -> 226 | H89: =IFERROR('HISTORICAL FS'!AA18,0) -> 104 | I89: =IFERROR('HISTORICAL FS'!AB18,0) -> 6895 | J89: =IFERROR('HISTORICAL FS'!AC18,0) -> 10821 | ... L89: =IFERROR('HISTORICAL FS'!AE18,0) -> 10704
B90: Interest received | C90: =IFERROR('HISTORICAL FS'!V19,0) -> 638 | D90: =IFERROR('HISTORICAL FS'!W19,0) -> 690 | E90: =IFERROR('HISTORICAL FS'!X19,0) -> 761 | F90: =IFERROR('HISTORICAL FS'!Y19,0) -> 1104 | G90: =IFERROR('HISTORICAL FS'!Z19,0) -> 428 | H90: =IFERROR('HISTORICAL FS'!AA19,0) -> 653 | I90: =IFERROR('HISTORICAL FS'!AB19,0) -> 973 | J90: =IFERROR('HISTORICAL FS'!AC19,0) -> 2493 | ... L90: =IFERROR('HISTORICAL FS'!AE19,0) -> 1940
B91: Dividends received | C91: =IFERROR('HISTORICAL FS'!V20,0) -> 620 | D91: =IFERROR('HISTORICAL FS'!W20,0) -> 1797 | E91: =IFERROR('HISTORICAL FS'!X20,0) -> 232 | F91: =IFERROR('HISTORICAL FS'!Y20,0) -> 21 | G91: =IFERROR('HISTORICAL FS'!Z20,0) -> 18 | H91: =IFERROR('HISTORICAL FS'!AA20,0) -> 32 | I91: =IFERROR('HISTORICAL FS'!AB20,0) -> 46 | J91: =IFERROR('HISTORICAL FS'!AC20,0) -> 47 | ... L91: =IFERROR('HISTORICAL FS'!AE20,0) -> 199
B92: Investment in group cos | C92: =IFERROR('HISTORICAL FS'!V21,0) -> -107 | D92: =IFERROR('HISTORICAL FS'!W21,0) -> -4 | E92: =IFERROR('HISTORICAL FS'!X21,0) -> -9 | F92: =IFERROR('HISTORICAL FS'!Y21,0) -> -606 | G92: =IFERROR('HISTORICAL FS'!Z21,0) -> -10 | H92: =IFERROR('HISTORICAL FS'!AA21,0) -> 0 | I92: =IFERROR('HISTORICAL FS'!AB21,0) -> 0 | J92: =IFERROR('HISTORICAL FS'!AC21,0) -> -150 | ... L92: =IFERROR('HISTORICAL FS'!AE21,0) -> -5
B93: Redemp n Canc of Shares | C93: =IFERROR('HISTORICAL FS'!V22,0) -> 0 | D93: =IFERROR('HISTORICAL FS'!W22,0) -> 14 | E93: =IFERROR('HISTORICAL FS'!X22,0) -> 533 | F93: =IFERROR('HISTORICAL FS'!Y22,0) -> 0 | G93: =IFERROR('HISTORICAL FS'!Z22,0) -> 0 | H93: =IFERROR('HISTORICAL FS'!AA22,0) -> 0 | I93: =IFERROR('HISTORICAL FS'!AB22,0) -> 19 | J93: =IFERROR('HISTORICAL FS'!AC22,0) -> 107 | ... L93: =IFERROR('HISTORICAL FS'!AE22,0) -> 0
B94: Acquisition of companies | C94: =IFERROR('HISTORICAL FS'!V23,0) -> 0 | D94: =IFERROR('HISTORICAL FS'!W23,0) -> 0 | E94: =IFERROR('HISTORICAL FS'!X23,0) -> -8 | F94: =IFERROR('HISTORICAL FS'!Y23,0) -> -27 | G94: =IFERROR('HISTORICAL FS'!Z23,0) -> 0 | H94: =IFERROR('HISTORICAL FS'!AA23,0) -> -98 | I94: =IFERROR('HISTORICAL FS'!AB23,0) -> 0 | J94: =IFERROR('HISTORICAL FS'!AC23,0) -> 0 | ... L94: =IFERROR('HISTORICAL FS'!AE23,0) -> -512
B95: Inter corporate deposits | C95: =IFERROR('HISTORICAL FS'!V24,0) -> 0 | D95: =IFERROR('HISTORICAL FS'!W24,0) -> 0 | E95: =IFERROR('HISTORICAL FS'!X24,0) -> 0 | F95: =IFERROR('HISTORICAL FS'!Y24,0) -> 0 | G95: =IFERROR('HISTORICAL FS'!Z24,0) -> 0 | H95: =IFERROR('HISTORICAL FS'!AA24,0) -> 0 | I95: =IFERROR('HISTORICAL FS'!AB24,0) -> 0 | J95: =IFERROR('HISTORICAL FS'!AC24,0) -> -25 | ... L95: =IFERROR('HISTORICAL FS'!AE24,0) -> -83
B96: Other investing items | C96: =IFERROR('HISTORICAL FS'!V25,0) -> -26663 | D96: =IFERROR('HISTORICAL FS'!W25,0) -> 5360 | E96: =IFERROR('HISTORICAL FS'!X25,0) -> 7335 | F96: =IFERROR('HISTORICAL FS'!Y25,0) -> -2659 | G96: =IFERROR('HISTORICAL FS'!Z25,0) -> 1051 | H96: =IFERROR('HISTORICAL FS'!AA25,0) -> 12813 | I96: =IFERROR('HISTORICAL FS'!AB25,0) -> -4357 | J96: =IFERROR('HISTORICAL FS'!AC25,0) -> -4817 | ... L96: =IFERROR('HISTORICAL FS'!AE25,0) -> -715
B97: Cash From Investing Activities | C97: =SUM(C86:C95) -> -12909 | D97: =SUM(D86:D95) -> -30500 | E97: =SUM(E86:E95) -> -28214 | F97: =SUM(F86:F95) -> -30457 | G97: =SUM(G86:G95) -> -26722 | H97: =SUM(H86:H95) -> -17255 | I97: =SUM(I86:I95) -> -11062 | J97: =SUM(J86:J95) -> -17964 | ... L97: =SUM(L86:L95) -> -24095
B100: Financing Activities
B101: Proceeds from shares | C101: =IFERROR('HISTORICAL FS'!V27,0) -> 5 | D101: =IFERROR('HISTORICAL FS'!W27,0) -> 0 | E101: =IFERROR('HISTORICAL FS'!X27,0) -> 0 | F101: =IFERROR('HISTORICAL FS'!Y27,0) -> 3889 | G101: =IFERROR('HISTORICAL FS'!Z27,0) -> 2603 | H101: =IFERROR('HISTORICAL FS'!AA27,0) -> 19 | I101: =IFERROR('HISTORICAL FS'!AB27,0) -> 20 | J101: =IFERROR('HISTORICAL FS'!AC27,0) -> 82 | ... L101: =IFERROR('HISTORICAL FS'!AE27,0) -> 18
B102: Redemption of debentures | C102: =IFERROR('HISTORICAL FS'!V28,0) -> 0 | D102: =IFERROR('HISTORICAL FS'!W28,0) -> 0 | E102: =IFERROR('HISTORICAL FS'!X28,0) -> 0 | F102: =IFERROR('HISTORICAL FS'!Y28,0) -> 0 | G102: =IFERROR('HISTORICAL FS'!Z28,0) -> 0 | H102: =IFERROR('HISTORICAL FS'!AA28,0) -> 0 | I102: =IFERROR('HISTORICAL FS'!AB28,0) -> 0 | J102: =IFERROR('HISTORICAL FS'!AC28,0) -> 0 | ... L102: =IFERROR('HISTORICAL FS'!AE28,0) -> 0
B103: Proceeds from borrowings | C103: =IFERROR('HISTORICAL FS'!V29,0) -> 33390 | D103: =IFERROR('HISTORICAL FS'!W29,0) -> 37482 | E103: =IFERROR('HISTORICAL FS'!X29,0) -> 51128 | F103: =IFERROR('HISTORICAL FS'!Y29,0) -> 38297 | G103: =IFERROR('HISTORICAL FS'!Z29,0) -> 46641 | H103: =IFERROR('HISTORICAL FS'!AA29,0) -> 46578 | I103: =IFERROR('HISTORICAL FS'!AB29,0) -> 43934 | J103: =IFERROR('HISTORICAL FS'!AC29,0) -> 18829 | ... L103: =IFERROR('HISTORICAL FS'!AE29,0) -> 26425
B104: Repayment of borrowings | C104: =IFERROR('HISTORICAL FS'!V30,0) -> -21732 | D104: =IFERROR('HISTORICAL FS'!W30,0) -> -29964 | E104: =IFERROR('HISTORICAL FS'!X30,0) -> -35198 | F104: =IFERROR('HISTORICAL FS'!Y30,0) -> -29847 | G104: =IFERROR('HISTORICAL FS'!Z30,0) -> -29709 | H104: =IFERROR('HISTORICAL FS'!AA30,0) -> -42816 | I104: =IFERROR('HISTORICAL FS'!AB30,0) -> -62557 | J104: =IFERROR('HISTORICAL FS'!AC30,0) -> -47414 | ... L104: =IFERROR('HISTORICAL FS'!AE30,0) -> -18110
B105: Interest paid fin | C105: =IFERROR('HISTORICAL FS'!V31,0) -> -5336 | D105: =IFERROR('HISTORICAL FS'!W31,0) -> -5411 | E105: =IFERROR('HISTORICAL FS'!X31,0) -> -7005 | F105: =IFERROR('HISTORICAL FS'!Y31,0) -> -7518 | G105: =IFERROR('HISTORICAL FS'!Z31,0) -> -8123 | H105: =IFERROR('HISTORICAL FS'!AA31,0) -> -9251 | I105: =IFERROR('HISTORICAL FS'!AB31,0) -> -9336 | J105: =IFERROR('HISTORICAL FS'!AC31,0) -> -9332 | ... L105: =IFERROR('HISTORICAL FS'!AE31,0) -> -5111
B106: Dividends paid | C106: =IFERROR('HISTORICAL FS'!V32,0) -> -121 | D106: =IFERROR('HISTORICAL FS'!W32,0) -> -96 | E106: =IFERROR('HISTORICAL FS'!X32,0) -> -95 | F106: =IFERROR('HISTORICAL FS'!Y32,0) -> -57 | G106: =IFERROR('HISTORICAL FS'!Z32,0) -> -30 | H106: =IFERROR('HISTORICAL FS'!AA32,0) -> -100 | I106: =IFERROR('HISTORICAL FS'!AB32,0) -> -141 | J106: =IFERROR('HISTORICAL FS'!AC32,0) -> -1059 | ... L106: =IFERROR('HISTORICAL FS'!AE32,0) -> -2203
B107: Financial liabilities | C107: =IFERROR('HISTORICAL FS'!V33,0) -> 0 | D107: =IFERROR('HISTORICAL FS'!W33,0) -> 0 | E107: =IFERROR('HISTORICAL FS'!X33,0) -> 0 | F107: =IFERROR('HISTORICAL FS'!Y33,0) -> -1346 | G107: =IFERROR('HISTORICAL FS'!Z33,0) -> -1477 | H107: =IFERROR('HISTORICAL FS'!AA33,0) -> -1559 | I107: =IFERROR('HISTORICAL FS'!AB33,0) -> -1517 | J107: =IFERROR('HISTORICAL FS'!AC33,0) -> -1924 | ... L107: =IFERROR('HISTORICAL FS'!AE33,0) -> -2145
B108: Other financing items | C108: =IFERROR('HISTORICAL FS'!V34,0) -> 0 | D108: =IFERROR('HISTORICAL FS'!W34,0) -> 0 | E108: =IFERROR('HISTORICAL FS'!X34,0) -> 0 | F108: =IFERROR('HISTORICAL FS'!Y34,0) -> -29 | G108: =IFERROR('HISTORICAL FS'!Z34,0) -> 0 | H108: =IFERROR('HISTORICAL FS'!AA34,0) -> 3750 | I108: =IFERROR('HISTORICAL FS'!AB34,0) -> 3355 | J108: =IFERROR('HISTORICAL FS'!AC34,0) -> 3812 | ... L108: =IFERROR('HISTORICAL FS'!AE34,0) -> -218
B110: Cash Financing Activities | C110: =SUM(C101:C108) -> 6206 | D110: =SUM(D101:D108) -> 2011 | E110: =SUM(E101:E108) -> 8830 | F110: =SUM(F101:F108) -> 3389 | G110: =SUM(G101:G108) -> 9905 | H110: =SUM(H101:H108) -> -3379 | I110: =SUM(I101:I108) -> -26242 | J110: =SUM(J101:J108) -> -37006 | ... L110: =SUM(L101:L108) -> -1344
B112: Net Cash Flow | C112: =SUM(C110+C97+C82) -> 26751 | D112: =SUM(D110+D97+D82) -> -11066 | E112: =SUM(E110+E97+E82) -> -7713 | F112: =SUM(F110+F97+F82) -> 4630 | G112: =SUM(G110+G97+G82) -> 12090 | H112: =SUM(H110+H97+H82) -> -17102 | I112: =SUM(I110+I97+I82) -> -5043 | J112: =SUM(J110+J97+J82) -> 20270 | ... L112: =SUM(L110+L97+L82) -> -21436
A118: #Cash Flow Statement
B119: Cash from Operating Activity | C119: 30199.25 | D119: 23857.42 | E119: 18890.75 | F119: 26632.94 | G119: 29000.51 | H119: 14282.83 | I119: 35388.01 | J119: 67915 | K119: 63102 | L119: 13041
B121: Cash from Investing Activity | C121: -39571.4 | D121: -25139.14 | E121: -20878.07 | F121: -33114.55 | G121: -25672.5 | H121: -4443.66 | I121: -15417.17 | J121: -22781 | K121: -49982 | L121: -24810
B123: Cash from Financing Activity | C123: 6205.3 | D123: 2011.71 | E123: 8830.37 | F123: 3389.61 | G123: 9904.2 | H123: -3380.17 | I123: -26242.9 | J123: -37006 | K123: -18786 | L123: -1344
B125: Net Cash Flow | C125: -3166.85 | D125: 729.99 | E125: 6843.05 | F125: -3092 | G125: 13232.21 | H125: 6459 | I125: -6272.06 | J125: 8128 | K125: -5666 | L125: -13113

Sheet Sheet1
B2: ="RATIO ANALYSIS - "&'Data Sheet'!B1 -> RATIO ANALYSIS - WIPRO LTD
B3: YEARS | C3: ='Data Sheet'!B16 -> 42825 | D3: ='Data Sheet'!C16 -> 43190 | E3: ='Data Sheet'!D16 -> 43555 | F3: ='Data Sheet'!E16 -> 43921 | G3: ='Data Sheet'!F16 -> 44286 | H3: ='Data Sheet'!G16 -> 44651 | I3: ='Data Sheet'!H16 -> 45016 | J3: ='Data Sheet'!I16 -> 45382 | ... L3: ='Data Sheet'!K16 -> 46112
B5: SALES GROWTH | D5: =IFERROR(FINANCIALS!D6,0) -> -0.017336839 | E5: =IFERROR(FINANCIALS!E6,0) -> 0.08317198 | F5: =IFERROR(FINANCIALS!F6,0) -> 0.03589867 | G5: =IFERROR(FINANCIALS!G6,0) -> 0.013041075 | H5: =IFERROR(FINANCIALS!H6,0) -> 0.28057041 | I5: =IFERROR(FINANCIALS!I6,0) -> 0.1409068 | J5: =IFERROR(FINANCIALS!J6,0) -> -0.0080375654 | K5: =IFERROR(FINANCIALS!K6,0) -> -0.0074854919 | L5: =IFERROR(FINANCIALS!L6,0) -> 0.039686424
B6: EBITDA GROWTH | D6: =IFERROR(FINANCIALS!D17/FINANCIALS!C17-1,0) -> -0.082484608 | E6: =IFERROR(FINANCIALS!E17/FINANCIALS!D17-1,0) -> 0.11798288 | F6: =IFERROR(FINANCIALS!F17/FINANCIALS!E17-1,0) -> 0.062836919 | G6: =IFERROR(FINANCIALS!G17/FINANCIALS!F17-1,0) -> 0.19681097 | H6: =IFERROR(FINANCIALS!H17/FINANCIALS!G17-1,0) -> 0.12949348 | I6: =IFERROR(FINANCIALS!I17/FINANCIALS!H17-1,0) -> 0.0092782393 | J6: =IFERROR(FINANCIALS!J17/FINANCIALS!I17-1,0) -> -0.0051368846 | K6: =IFERROR(FINANCIALS!K17/FINANCIALS!J17-1,0) -> 0.07573198 | L6: =IFERROR(FINANCIALS!L17/FINANCIALS!K17-1,0) -> -0.011652942
B7: EBIT GROWTH | D7: =IFERROR(FINANCIALS!D26/FINANCIALS!C26-1,0) -> -0.086055105 | E7: =IFERROR(FINANCIALS!E26/FINANCIALS!D26-1,0) -> 0.16067807 | F7: =IFERROR(FINANCIALS!F26/FINANCIALS!E26-1,0) -> 0.066708481 | G7: =IFERROR(FINANCIALS!G26/FINANCIALS!F26-1,0) -> 0.20739185 | H7: =IFERROR(FINANCIALS!H26/FINANCIALS!G26-1,0) -> 0.13693996 | I7: =IFERROR(FINANCIALS!I26/FINANCIALS!H26-1,0) -> -0.044577364 | J7: =IFERROR(FINANCIALS!J26/FINANCIALS!I26-1,0) -> -0.032094852 | K7: =IFERROR(FINANCIALS!K26/FINANCIALS!J26-1,0) -> 0.12374485 | L7: =IFERROR(FINANCIALS!L26/FINANCIALS!K26-1,0) -> -0.01056211
B8: NET PROFIT GROWTH | D8: =IFERROR(FINANCIALS!D32/FINANCIALS!C32-1,0) -> -0.07497498 | E8: =IFERROR(FINANCIALS!E32/FINANCIALS!D32-1,0) -> 0.17435314 | F8: =IFERROR(FINANCIALS!F32/FINANCIALS!E32-1,0) -> 0.099904749 | G8: =IFERROR(FINANCIALS!G32/FINANCIALS!F32-1,0) -> 0.20164965 | H8: =IFERROR(FINANCIALS!H32/FINANCIALS!G32-1,0) -> 0.20228489 | I8: =IFERROR(FINANCIALS!I32/FINANCIALS!H32-1,0) -> -0.10657888 | J8: =IFERROR(FINANCIALS!J32/FINANCIALS!I32-1,0) -> -0.06715868 | K8: =IFERROR(FINANCIALS!K32/FINANCIALS!J32-1,0) -> 0.097544009 | L8: =IFERROR(FINANCIALS!L32/FINANCIALS!K32-1,0) -> 0.0061770836
B9: DIVIDENED GROWTH | D9: =IFERROR(FINANCIALS!D40/FINANCIALS!C40-1,0) -> 0.00020602935 | E9: =IFERROR(FINANCIALS!E40/FINANCIALS!D40-1,0) -> 0.33328912 | F9: =IFERROR(FINANCIALS!F40/FINANCIALS!E40-1,0) -> 1.7967704e-05 | G9: =IFERROR(FINANCIALS!G40/FINANCIALS!F40-1,0) -> -5.36294e-05 | H9: =IFERROR(FINANCIALS!H40/FINANCIALS!G40-1,0) -> 5.0001095 | I9: =IFERROR(FINANCIALS!I40/FINANCIALS!H40-1,0) -> -0.83332878 | J9: =IFERROR(FINANCIALS!J40/FINANCIALS!I40-1,0) -> -4.6928361e-05 | K9: =IFERROR(FINANCIALS!K40/FINANCIALS!J40-1,0) -> 11.00023 | L9: =IFERROR(FINANCIALS!L40/FINANCIALS!K40-1,0) -> 0.83336832
B11: GROSS MARGIN | C11: =IFERROR(FINANCIALS!C12,0) -> 0.46788005 | D11: =IFERROR(FINANCIALS!D12,0) -> 0.46563131 | E11: =IFERROR(FINANCIALS!E12,0) -> 0.46936659 | F11: =IFERROR(FINANCIALS!F12,0) -> 0.4472256 | G11: =IFERROR(FINANCIALS!G12,0) -> 0.4516129 | H11: =IFERROR(FINANCIALS!H12,0) -> 0.40775671 | I11: =IFERROR(FINANCIALS!I12,0) -> 0.37780978 | J11: =IFERROR(FINANCIALS!J12,0) -> 0.3629823 | ... L11: =IFERROR(FINANCIALS!L12,0) -> 0.3700326
B12: EDITDA MARGIN | C12: =IFERROR(FINANCIALS!C18,0) -> 0.20417 | D12: =IFERROR(FINANCIALS!D18,0) -> 0.19063411 | E12: =IFERROR(FINANCIALS!E18,0) -> 0.1967607 | F12: =IFERROR(FINANCIALS!F18,0) -> 0.2018774 | G12: =IFERROR(FINANCIALS!G18,0) -> 0.23849881 | H12: =IFERROR(FINANCIALS!H18,0) -> 0.21036161 | I12: =IFERROR(FINANCIALS!I18,0) -> 0.1860918 | J12: =IFERROR(FINANCIALS!J18,0) -> 0.18663596 | ... L12: =IFERROR(FINANCIALS!L18,0) -> 0.19229573
B13: EBIT MARGIN | C13: =IFERROR((FINANCIALS!C17-FINANCIALS!C23)/FINANCIALS!C5,0) -> 0.16250965 | D13: =IFERROR((FINANCIALS!D17-FINANCIALS!D23)/FINANCIALS!D5,0) -> 0.15187815 | E13: =IFERROR((FINANCIALS!E17-FINANCIALS!E23)/FINANCIALS!E5,0) -> 0.16377635 | F13: =IFERROR((FINANCIALS!F17-FINANCIALS!F23)/FINANCIALS!F5,0) -> 0.16776583 | G13: =IFERROR((FINANCIALS!G17-FINANCIALS!G23)/FINANCIALS!G5,0) -> 0.19388099 | H13: =IFERROR((FINANCIALS!H17-FINANCIALS!H23)/FINANCIALS!H5,0) -> 0.17155538 | I13: =IFERROR((FINANCIALS!I17-FINANCIALS!I23)/FINANCIALS!I5,0) -> 0.14917845 | J13: =IFERROR((FINANCIALS!J17-FINANCIALS!J23)/FINANCIALS!J5,0) -> 0.1486782 | ... L13: =IFERROR((FINANCIALS!L17-FINANCIALS!L23)/FINANCIALS!L5,0) -> 0.16087083
B14: EBT MARGIN | C14: =IFERROR(FINANCIALS!C27,0) -> 0.15179338 | D14: =IFERROR(FINANCIALS!D27,0) -> 0.14117837 | E14: =IFERROR(FINANCIALS!E27,0) -> 0.15128035 | F14: =IFERROR(FINANCIALS!F27,0) -> 0.15577975 | G14: =IFERROR(FINANCIALS!G27,0) -> 0.18566592 | H14: =IFERROR(FINANCIALS!H27,0) -> 0.16484139 | I14: =IFERROR(FINANCIALS!I27,0) -> 0.13804212 | J14: =IFERROR(FINANCIALS!J27,0) -> 0.13469429 | ... L14: =IFERROR(FINANCIALS!L27,0) -> 0.14513301
B15: NET PROFIT MARGIN | C15: =IFERROR(FINANCIALS!C33,0) -> 0.10632047 | D15: =IFERROR(FINANCIALS!D33,0) -> 0.10008424 | E15: =IFERROR(FINANCIALS!E33,0) -> 0.10850931 | F15: =IFERROR(FINANCIALS!F33,0) -> 0.11521388 | G15: =IFERROR(FINANCIALS!G33,0) -> 0.13666447 | H15: =IFERROR(FINANCIALS!H33,0) -> 0.12830971 | I15: =IFERROR(FINANCIALS!I33,0) -> 0.10047675 | J15: =IFERROR(FINANCIALS!J33,0) -> 0.094488321 | ... L15: =IFERROR(FINANCIALS!L33,0) -> 0.10111958
B18: SALESEXPENSES%SALES | C18: =IFERROR(FINANCIALS!C15,0) -> 0.26371004 | D18: =IFERROR(FINANCIALS!D15,0) -> 0.2749972 | E18: =IFERROR(FINANCIALS!E15,0) -> 0.27260589 | F18: =IFERROR(FINANCIALS!F15,0) -> 0.2453482 | G18: =IFERROR(FINANCIALS!G15,0) -> 0.21311409 | H18: =IFERROR(FINANCIALS!H15,0) -> 0.1973951 | I18: =IFERROR(FINANCIALS!I15,0) -> 0.19171798 | J18: =IFERROR(FINANCIALS!J15,0) -> 0.17634634 | ... L18: =IFERROR(FINANCIALS!L15,0) -> 0.17773687
B19: DEPRECIATION%SALES | C19: =IFERROR(FINANCIALS!C24,0) -> 0.078291284 | D19: =IFERROR(FINANCIALS!D24,0) -> 0.072526635 | E19: =IFERROR(FINANCIALS!E24,0) -> 0.062160333 | F19: =IFERROR(FINANCIALS!F24,0) -> 0.061709764 | G19: =IFERROR(FINANCIALS!G24,0) -> 0.081361901 | H19: =IFERROR(FINANCIALS!H24,0) -> 0.065524142 | I19: =IFERROR(FINANCIALS!I24,0) -> 0.05932807 | J19: =IFERROR(FINANCIALS!J24,0) -> 0.059586666 | ... L19: =IFERROR(FINANCIALS!L24,0) -> 0.049883376
B20: OPERATINGINCOME%SALES | C20: =C13 -> 0.16250965 | D20: =D13 -> 0.15187815 | E20: =E13 -> 0.16377635 | F20: =F13 -> 0.16776583 | G20: =G13 -> 0.19388099 | H20: =H13 -> 0.17155538 | I20: =I13 -> 0.14917845 | J20: =J13 -> 0.1486782 | ... L20: =L13 -> 0.16087083
B22: RETURN ON CAPITAL EMPLOYED | C22: =(FINANCIALS!C17-FINANCIALS!C23)/(SUM(FINANCIALS!C50:C52)) -> 0.13671231 | D22: =(FINANCIALS!D17-FINANCIALS!D23)/(SUM(FINANCIALS!D50:D52)) -> 0.13384659 | E22: =(FINANCIALS!E17-FINANCIALS!E23)/(SUM(FINANCIALS!E50:E52)) -> 0.14563812 | F22: =(FINANCIALS!F17-FINANCIALS!F23)/(SUM(FINANCIALS!F50:F52)) -> 0.15768606 | G22: =(FINANCIALS!G17-FINANCIALS!G23)/(SUM(FINANCIALS!G50:G52)) -> 0.1837423 | H22: =(FINANCIALS!H17-FINANCIALS!H23)/(SUM(FINANCIALS!H50:H52)) -> 0.16394063 | I22: =(FINANCIALS!I17-FINANCIALS!I23)/(SUM(FINANCIALS!I50:I52)) -> 0.14189174 | J22: =(FINANCIALS!J17-FINANCIALS!J23)/(SUM(FINANCIALS!J50:J52)) -> 0.14665613 | ... L22: =(FINANCIALS!L17-FINANCIALS!L23)/(SUM(FINANCIALS!L50:L52)) -> 0.1375736
B23: RETAINED EARNING% | C23: =IFERROR(FINANCIALS!C43,0) -> 0.91754448 | D23: =IFERROR(FINANCIALS!D43,0) -> 0.91704106 | E23: =IFERROR(FINANCIALS!E43,0) -> 0.90577911 | F23: =IFERROR(FINANCIALS!F43,0) -> 0.91888726 | G23: =IFERROR(FINANCIALS!G43,0) -> 0.93526931 | H23: =IFERROR(FINANCIALS!H43,0) -> 0.67678475 | I23: =IFERROR(FINANCIALS!I43,0) -> 0.93963858 | J23: =IFERROR(FINANCIALS!J43,0) -> 0.93839388 | ... L23: =IFERROR(FINANCIALS!L43,0) -> 0
B24: RETURN ON EQUITY % | C24: =IFERROR(FINANCIALS!C32/SUM(FINANCIALS!C50:C51),0) -> 0.11409478 | D24: =IFERROR(FINANCIALS!D32/SUM(FINANCIALS!D50:D51),0) -> 0.11378512 | E24: =IFERROR(FINANCIALS!E32/SUM(FINANCIALS!E50:E51),0) -> 0.11350239 | F24: =IFERROR(FINANCIALS!F32/SUM(FINANCIALS!F50:F51),0) -> 0.12732617 | G24: =IFERROR(FINANCIALS!G32/SUM(FINANCIALS!G50:G51),0) -> 0.15417388 | H24: =IFERROR(FINANCIALS!H32/SUM(FINANCIALS!H50:H51),0) -> 0.15559684 | I24: =IFERROR(FINANCIALS!I32/SUM(FINANCIALS!I50:I51),0) -> 0.11706123 | J24: =IFERROR(FINANCIALS!J32/SUM(FINANCIALS!J50:J51),0) -> 0.11379255 | ... L24: =IFERROR(FINANCIALS!L32/SUM(FINANCIALS!L50:L51),0) -> 0.10641083
B25: SELF SUSTAINED GROWTH RATE | C25: =IFERROR(C23*C24,0) -> 0.10468703 | D25: =IFERROR(D23*D24,0) -> 0.10434563 | E25: =IFERROR(E23*E24,0) -> 0.10280809 | F25: =IFERROR(F23*F24,0) -> 0.11699839 | G25: =IFERROR(G23*G24,0) -> 0.14419409 | H25: =IFERROR(H23*H24,0) -> 0.10530557 | I25: =IFERROR(I23*I24,0) -> 0.10999525 | J25: =IFERROR(J23*J24,0) -> 0.10678223 | ... L25: =IFERROR(L23*L24,0) -> 0
B26: INTEREST COVERAGE RATIO | C26: =(FINANCIALS!C17-FINANCIALS!C23)/FINANCIALS!C20 -> 15.164759 | D26: =(FINANCIALS!D17-FINANCIALS!D23)/FINANCIALS!D20 -> 14.194511 | E26: =(FINANCIALS!E17-FINANCIALS!E23)/FINANCIALS!E20 -> 13.106305 | F26: =(FINANCIALS!F17-FINANCIALS!F23)/FINANCIALS!F20 -> 13.996725 | G26: =(FINANCIALS!G17-FINANCIALS!G23)/FINANCIALS!G20 -> 23.600629 | H26: =(FINANCIALS!H17-FINANCIALS!H23)/FINANCIALS!H20 -> 25.551925 | I26: =(FINANCIALS!I17-FINANCIALS!I23)/FINANCIALS!I20 -> 13.395653 | J26: =(FINANCIALS!J17-FINANCIALS!J23)/FINANCIALS!J20 -> 10.632091 | ... L26: =(FINANCIALS!L17-FINANCIALS!L23)/FINANCIALS!L20 -> 10.221925
B28: Debtor Turnover Ratio | C28: =FINANCIALS!C5/FINANCIALS!C62 -> 5.8461506 | D28: =FINANCIALS!D5/FINANCIALS!D62 -> 5.3952966 | E28: =FINANCIALS!E5/FINANCIALS!E62 -> 5.8731702 | F28: =FINANCIALS!F5/FINANCIALS!F62 -> 5.851944 | G28: =FINANCIALS!G5/FINANCIALS!G62 -> 6.5679972 | H28: =FINANCIALS!H5/FINANCIALS!H62 -> 6.8835869 | I28: =FINANCIALS!I5/FINANCIALS!I62 -> 7.161662 | J28: =FINANCIALS!J5/FINANCIALS!J62 -> 7.7730024 | ... L28: =FINANCIALS!L5/FINANCIALS!L62 -> 6.8155496
B29: Credit Turnover Ratio | C29: =IFERROR(FINANCIALS!C5/FINANCIALS!C53,0) -> 4.3452135 | D29: =IFERROR(FINANCIALS!D5/FINANCIALS!D53,0) -> 4.0172451 | E29: =IFERROR(FINANCIALS!E5/FINANCIALS!E53,0) -> 3.6393005 | F29: =IFERROR(FINANCIALS!F5/FINANCIALS!F53,0) -> 3.8321414 | G29: =IFERROR(FINANCIALS!G5/FINANCIALS!G53,0) -> 3.5980631 | H29: =IFERROR(FINANCIALS!H5/FINANCIALS!H53,0) -> 3.2665972 | I29: =IFERROR(FINANCIALS!I5/FINANCIALS!I53,0) -> 4.1528647 | J29: =IFERROR(FINANCIALS!J5/FINANCIALS!J53,0) -> 3.8016306 | ... L29: =IFERROR(FINANCIALS!L5/FINANCIALS!L53,0) -> 2.8434774
B30: Inventory Turnoover ratio | C30: =IFERROR(FINANCIALS!C5/FINANCIALS!C63,0) -> 141.63065 | D30: =IFERROR(FINANCIALS!D5/FINANCIALS!D63,0) -> 161.68279 | E30: =IFERROR(FINANCIALS!E5/FINANCIALS!E63,0) -> 149.37712 | F30: =IFERROR(FINANCIALS!F5/FINANCIALS!F63,0) -> 327.81555 | G30: =IFERROR(FINANCIALS!G5/FINANCIALS!G63,0) -> 582.09492 | H30: =IFERROR(FINANCIALS!H5/FINANCIALS!H63,0) -> 594.54273 | I30: =IFERROR(FINANCIALS!I5/FINANCIALS!I63,0) -> 761.68013 | J30: =IFERROR(FINANCIALS!J5/FINANCIALS!J63,0) -> 989.63947 | ... L30: =IFERROR(FINANCIALS!L5/FINANCIALS!L63,0) -> 1791.5667
B31: Fixed Asset Turnover | C31: =IFERROR(FINANCIALS!C5/FINANCIALS!C52,0) -> 3.8935202 | D31: =IFERROR(FINANCIALS!D5/FINANCIALS!D52,0) -> 3.9195969 | E31: =IFERROR(FINANCIALS!E5/FINANCIALS!E52,0) -> 5.9335156 | F31: =IFERROR(FINANCIALS!F5/FINANCIALS!F52,0) -> 6.2872892 | G31: =IFERROR(FINANCIALS!G5/FINANCIALS!G52,0) -> 5.9259908 | H31: =IFERROR(FINANCIALS!H5/FINANCIALS!H52,0) -> 4.5081823 | I31: =IFERROR(FINANCIALS!I5/FINANCIALS!I52,0) -> 5.1806076 | J31: =IFERROR(FINANCIALS!J5/FINANCIALS!J52,0) -> 5.4516153 | ... L31: =IFERROR(FINANCIALS!L5/FINANCIALS!L52,0) -> 4.5647824
B32: Capital Turnover Ratio | C32: =IFERROR(FINANCIALS!C5/SUM(FINANCIALS!C50:C51),) -> 1.0731215 | D32: =IFERROR(FINANCIALS!D5/SUM(FINANCIALS!D50:D51),) -> 1.1368935 | E32: =IFERROR(FINANCIALS!E5/SUM(FINANCIALS!E50:E51),) -> 1.0460152 | F32: =IFERROR(FINANCIALS!F5/SUM(FINANCIALS!F50:F51),) -> 1.1051287 | G32: =IFERROR(FINANCIALS!G5/SUM(FINANCIALS!G50:G51),) -> 1.1281197 | H32: =IFERROR(FINANCIALS!H5/SUM(FINANCIALS!H50:H51),) -> 1.2126661 | I32: =IFERROR(FINANCIALS!I5/SUM(FINANCIALS!I50:I51),) -> 1.1650579 | J32: =IFERROR(FINANCIALS!J5/SUM(FINANCIALS!J50:J51),) -> 1.2043028 | ... L32: =IFERROR(FINANCIALS!L5/SUM(FINANCIALS!L50:L51),) -> 1.0523266
B34: debtor days | C34: =IFERROR(365/C28,0) -> 62.434245
B35: Payable days | C35: =IFERROR(365/C29,0) -> 84.000476
B36: Inventory Days | C36: =IFERROR(365/C30,0) -> 2.5771258
B37: Cash Conversion cycle

Sheet HISTORICAL FS
N3: 13041
T4: 42064 | U4: 42430 | V4: 42795 | W4: 43160 | X4: 43525 | Y4: 43891 | Z4: 44256 | AA4: 44621 | AB4: 44986 | AC4: 45352 | AD4: 45717 | AE4: 46082
S5: Cash from Operating Activity - | T5: 35531 | U5: 37900 | V5: 30199 | W5: 23857 | X5: 18891 | Y5: 26633 | Z5: 29001 | AA5: 14283 | AB5: 35388 | AC5: 67915 | AD5: 63102 | AE5: 13041
S6: Profit from operations | T6: 43397 | U6: 38626 | V6: 28840 | W6: 33312 | X6: 28771 | Y6: 23352 | Z6: 31198 | AA6: 26943 | AB6: 41694 | AC6: 65106 | AD6: 58937 | AE6: 25393
S7: Receivables | T7: -3179 | U7: -2223 | V7: -4152 | W7: -10688 | X7: -9109 | Y7: 9950 | Z7: -5505 | AA7: 185 | AB7: -2213 | AC7: -1876 | AD7: 3573 | AE7: -1587
S8: Inventory | T8: -3692 | U8: -5743 | V8: -6621 | W8: -3560 | X8: 2069 | Y8: 2326 | Z8: 3814 | AA8: 472 | AB8: -5665 | AC8: -7265 | AD8: 2127 | AE8: -4318
S9: Payables | T9: 3598 | U9: 3947 | V9: 9301 | W9: 7320 | X9: -4692 | Y9: -8085 | Z9: 5748 | AA9: -7012 | AB9: 6945 | AC9: 13706 | AD9: 1303 | AE9: -1973
S10: Loans Advances | T10: 0 | U10: -520 | V10: 0 | W10: 0 | X10: 0 | Y10: 0 | Z10: 0 | AA10: 0 | AB10: 0 | AC10: 0 | AD10: 0 | AE10: -815
S11: Other WC items | T11: -398 | U11: 5852 | V11: 4727 | W11: 494 | X11: 4512 | Y11: 875 | Z11: -4150 | AA11: -4396 | AB11: -2194 | AC11: 2760 | AD11: 1153 | AE11: -345
S12: Working capital changes | T12: -3672 | U12: 1313 | V12: 3254 | W12: -6434 | X12: -7221 | Y12: 5065 | Z12: -93 | AA12: -10750 | AB12: -3127 | AC12: 7325 | AD12: 8156 | AE12: -9038
S13: Direct taxes | T13: -4194 | U13: -2040 | V13: -1895 | W13: -3021 | X13: -2659 | Y13: -1785 | Z13: -2105 | AA13: -1910 | AB13: -3179 | AC13: -4516 | AD13: -3991 | AE13: -3314
S14: Cash from Investing Activity - | T14: -36232 | U14: -36694 | V14: -39571 | W14: -25139 | X14: -20878 | Y14: -33115 | Z14: -25672 | AA14: -4444 | AB14: -15417 | AC14: -22781 | AD14: -49982 | AE14: -24810
S15: Fixed assets purchased | T15: -31962 | U15: -31503 | V15: -16072 | W15: -35079 | X15: -35304 | Y15: -29702 | Z15: -20205 | AA15: -15168 | AB15: -19230 | AC15: -31414 | AD15: -38042 | AE15: -36282
S16: Fixed assets sold | T16: 74 | U16: 59 | V16: 53 | W16: 30 | X16: 67 | Y16: 171 | Z16: 351 | AA16: 230 | AB16: 285 | AC16: 231 | AD16: 974 | AE16: 46
... S19: Interest received | T19: 698 | U19: 731 | V19: 638 | W19: 690 | X19: 761 | Y19: 1104 | Z19: 428 | AA19: 653 | AB19: 973 | AC19: 2493 | AD19: 2420 | AE19: 1940
N20: 0 | S20: Dividends received | T20: 80 | U20: 58 | V20: 620 | W20: 1797 | X20: 232 | Y20: 21 | Z20: 18 | AA20: 32 | AB20: 46 | AC20: 47 | AD20: 64 | AE20: 199
N21: -512 | S21: Investment in group cos | T21: -160 | U21: 0 | V21: -107 | W21: -4 | X21: -9 | Y21: -606 | Z21: -10 | AA21: 0 | AB21: 0 | AC21: -150 | AD21: 0 | AE21: -5
N22: -83 | S22: Redemp n Canc of Shares | T22: 0 | U22: 0 | V22: 0 | W22: 14 | X22: 533 | Y22: 0 | Z22: 0 | AA22: 0 | AB22: 19 | AC22: 107 | AD22: 765 | AE22: 0
N23: -715 | S23: Acquisition of companies | T23: 0 | U23: -111 | V23: 0 | W23: 0 | X23: -8 | Y23: -27 | Z23: 0 | AA23: -98 | AB23: 0 | AC23: 0 | AD23: -688 | AE23: -512
N24: -1344 | S24: Inter corporate deposits | T24: 0 | U24: 0 | V24: 0 | W24: 0 | X24: 0 | Y24: 0 | Z24: 0 | AA24: 0 | AB24: 0 | AC24: -25 | AD24: -20 | AE24: -83
N25: 18 | S25: Other investing items | T25: 456 | U25: -1289 | V25: -26663 | W25: 5360 | X25: 7335 | Y25: -2659 | Z25: 1051 | AA25: 12813 | AB25: -4357 | AC25: -4817 | AD25: -2889 | AE25: -715
N26: 0 | S26: Cash from Financing Activity - | T26: 5201 | U26: -3795 | V26: 6205 | W26: 2012 | X26: 8830 | Y26: 3390 | Z26: 9904 | AA26: -3380 | AB26: -26243 | AC26: -37006 | AD26: -18786 | AE26: -1344
N27: 26425 | S27: Proceeds from shares | T27: 0 | U27: 7433 | V27: 5 | W27: 0 | X27: 0 | Y27: 3889 | Z27: 2603 | AA27: 19 | AB27: 20 | AC27: 82 | AD27: 1108 | AE27: 18
N28: -18110 | S28: Redemption of debentures | T28: -744 | U28: 0 | V28: 0 | W28: 0 | X28: 0 | Y28: 0 | Z28: 0 | AA28: 0 | AB28: 0 | AC28: 0 | AD28: 0 | AE28: 0
N29: -5111 | S29: Proceeds from borrowings | T29: 36363 | U29: 19519 | V29: 33390 | W29: 37482 | X29: 51128 | Y29: 38297 | Z29: 46641 | AA29: 46578 | AB29: 43934 | AC29: 18829 | AD29: 13384 | AE29: 26425
N30: -2203 | S30: Repayment of borrowings | T30: -23332 | U30: -24924 | V30: -21732 | W30: -29964 | X30: -35198 | Y30: -29847 | Z30: -29709 | AA30: -42816 | AB30: -62557 | AC30: -47414 | AD30: -21443 | AE30: -18110
N31: -2145 | S31: Interest paid fin | T31: -6307 | U31: -5716 | V31: -5336 | W31: -5411 | X31: -7005 | Y31: -7518 | Z31: -8123 | AA31: -9251 | AB31: -9336 | AC31: -9332 | AD31: -5814 | AE31: -5111
... N35: 0.87 | S35: Net Cash Flow | T35: 4500 | U35: -2589 | V35: -3167 | W35: 730 | X35: 6843 | Y35: -3092 | Z35: 13232 | AA35: 6459 | AB35: -6272 | AC35: 8128 | AD35: -5666 | AE35: -13113
S36: Free Cash Flow | T36: 3643 | U36: 6455 | V36: 14181 | W36: -11191 | X36: -16346 | Y36: -2898 | Z36: 9146 | AA36: -655 | AB36: 16443 | AC36: 36732 | AD36: 26034 | AE36: -23195
S37: CFO/OP | T37: 1.01 | U37: 1.04 | V37: 1.08 | W37: 0.85 | X37: 0.87 | Y37: 1.58 | Z37: 0.96 | AA37: 0.66 | AB37: 1.21 | AC37: 1.25 | AD37: 1.2 | AE37: 0.87

Sheet DCF
D1: WIPRO LTD
D2: DCF VALUATION
B4: CURRENT ASSETS | C4: 44276 | D4: 44642 | E4: 45008 | F4: 45374 | G4: 45740 | H4: 46106
B5: =DATA!B32 -> Inventories | C5: =DATA!I32 -> 106 | D5: =DATA!J32 -> 133 | E5: =DATA!K32 -> 119 | F5: =DATA!L32 -> 91 | G5: =DATA!M32 -> 69 | H5: =DATA!N32 -> 52
B6: =DATA!B33 -> Trade receivables + | C6: =DATA!I33 -> 9430 | D6: =DATA!J33 -> 11522 | E6: =DATA!K33 -> 12635 | F6: =DATA!L33 -> 11548 | G6: =DATA!M33 -> 11774 | H6: =DATA!N33 -> 13590
B7: =DATA!B35 -> Loans n Advances | C7: =DATA!I35 -> 1830 | D7: =DATA!J35 -> 2294 | E7: =DATA!K35 -> 2830 | F7: =DATA!L35 -> 2826 | G7: =DATA!M35 -> 2668 | H7: =DATA!N35 -> 3340
B8: =DATA!B36 -> Other asset items | C8: =DATA!I36 -> 10552 | D8: =DATA!J36 -> 17198 | E8: =DATA!K36 -> 13705 | F8: =DATA!L36 -> 12713 | G8: =DATA!M36 -> 11910 | H8: =DATA!N36 -> 14458
B9: TOTAL | C9: =SUM(C5:C8) -> 21918 | D9: =SUM(D5:D8) -> 31147 | E9: =SUM(E5:E8) -> 29289 | F9: =SUM(F5:F8) -> 27178 | G9: =SUM(G5:G8) -> 26421 | H9: =SUM(H5:H8) -> 31440
B11: CURRENT LIABILITIES | C11: 44276 | D11: 44642 | E11: 45008 | F11: 45374 | G11: 45740 | H11: 46106
B12: =DATA!B12 -> Trade Payables | C12: =DATA!I12 -> 5182 | D12: =DATA!J12 -> 6252 | E12: =DATA!K12 -> 5972 | F12: =DATA!L12 -> 5766 | G12: =DATA!M12 -> 5867 | H12: =DATA!N12 -> 6289
B13: =DATA!B13 -> Advance from Customers | C13: =DATA!I13 -> 36 | D13: =DATA!J13 -> 63 | E13: =DATA!K13 -> 64 | F13: =DATA!L13 -> 119 | G13: =DATA!M13 -> 79 | H13: =DATA!N13 -> 82
B14: =DATA!B14 -> Other liability items | C14: =DATA!I14 -> 11846 | D14: =DATA!J14 -> 17913 | E14: =DATA!K14 -> 15694 | F14: =DATA!L14 -> 17592 | G14: =DATA!M14 -> 20202 | H14: =DATA!N14 -> 25952
B15: TOTAL | C15: =SUM(C12:C14) -> 17064 | D15: =SUM(D12:D14) -> 24228 | E15: =SUM(E12:E14) -> 21730 | F15: =SUM(F12:F14) -> 23477 | G15: =SUM(G12:G14) -> 26148 | H15: =SUM(H12:H14) -> 32323
B17: TOTAL WORKING CAP | C17: =C9-C15 -> 4854 | D17: =D9-D15 -> 6919 | E17: =E9-E15 -> 7559 | F17: =F9-F15 -> 3701 | G17: =G9-G15 -> 273 | H17: =H9-H15 -> -883
B19: NON CURRENT ASSETS | C19: 44276 | D19: 44642 | E19: 45008 | F19: 45374 | G19: 45740 | H19: 46106
B20: =DATA!B17 -> Land | C20: =DATA!I17 -> 590 | D20: =DATA!J17 -> 609 | E20: =DATA!K17 -> 614 | F20: =DATA!L17 -> 572 | G20: =DATA!M17 -> 550 | H20: =DATA!N17 -> 553
B21: =DATA!B18 -> Building | C21: =DATA!I18 -> 5806 | D21: =DATA!J18 -> 6648 | E21: =DATA!K18 -> 7545 | F21: =DATA!L18 -> 7528 | G21: =DATA!M18 -> 8740 | H21: =DATA!N18 -> 9351
B22: =DATA!B19 -> Plant Machinery | C22: =DATA!I19 -> 9618 | D22: =DATA!J19 -> 10074 | E22: =DATA!K19 -> 12023 | F22: =DATA!L19 -> 10468 | G22: =DATA!M19 -> 10492 | H22: =DATA!N19 -> 10212
B23: =DATA!B20 -> Equipments | C23: =DATA!I20 -> 686 | D23: =DATA!J20 -> 726 | E23: =DATA!K20 -> 782 | F23: =DATA!L20 -> 751 | G23: =DATA!M20 -> 766 | H23: =DATA!N20 -> 793
B24: =DATA!B21 -> Computers | C24: =DATA!I21 -> 1851 | D24: =DATA!J21 -> 2516 | E24: =DATA!K21 -> 0 | F24: =DATA!L21 -> 0 | G24: =DATA!M21 -> 0 | H24: =DATA!N21 -> 0
B25: =DATA!B22 -> Furniture n fittings | C25: =DATA!I22 -> 1373 | D25: =DATA!J22 -> 1529 | E25: =DATA!K22 -> 1799 | F25: =DATA!L22 -> 1814 | G25: =DATA!M22 -> 1948 | H25: =DATA!N22 -> 2012
B26: =DATA!B23 -> Vehicles | C26: =DATA!I23 -> 134 | D26: =DATA!J23 -> 122 | E26: =DATA!K23 -> 103 | F26: =DATA!L23 -> 88 | G26: =DATA!M23 -> 77 | H26: =DATA!N23 -> 94
B27: =DATA!B24 -> Intangible Assets | C27: =DATA!I24 -> 13515 | D27: =DATA!J24 -> 24286 | E27: =DATA!K24 -> 30348 | F27: =DATA!L24 -> 31145 | G27: =DATA!M24 -> 32035 | H27: =DATA!N24 -> 38221
B28: =DATA!B25 -> Other fixed assets | C28: =DATA!I25 -> 2794 | D28: =DATA!J25 -> 5479 | E28: =DATA!K25 -> 6174 | F28: =DATA!L25 -> 5564 | G28: =DATA!M25 -> 5218 | H28: =DATA!N25 -> 6002
B29: =DATA!B26 -> Gross Block | C29: =SUM(C20:C28) -> 36367 | D29: =SUM(D20:D28) -> 51989 | E29: =SUM(E20:E28) -> 59388 | F29: =SUM(F20:F28) -> 57930 | G29: =SUM(G20:G28) -> 59826 | H29: =SUM(H20:H28) -> 67238
B30: =DATA!B27 -> Accumulated Depreciation | C30: =DATA!I27 -> 13327 | D30: =DATA!J27 -> 14000 | E30: =DATA!K27 -> 14631 | F30: =DATA!L27 -> 14302 | G30: =DATA!M27 -> 14639 | H30: =DATA!N27 -> 15547
B31: NET CURRENT ASSETS | C31: =C29-C30 -> 23040 | D31: =D29-D30 -> 37989 | E31: =E29-E30 -> 44757 | F31: =F29-F30 -> 43628 | G31: =G29-G30 -> 45187 | H31: =H29-H30 -> 51691
B33: INVESTED CAP | C33: =C31+C17 -> 27894 | D33: =D31+D17 -> 44908 | E33: =E31+E17 -> 52316 | F33: =F31+F17 -> 47329 | G33: =G31+G17 -> 45460 | H33: =H31+H17 -> 50808
B35: EBIT | C35: =FINANCIALS!G17-FINANCIALS!G23 -> 12008 | D35: =FINANCIALS!H17-FINANCIALS!H23 -> 13606.4 | E35: =FINANCIALS!I17-FINANCIALS!I23 -> 13498.8 | F35: =FINANCIALS!J17-FINANCIALS!J23 -> 13345.4 | G35: =FINANCIALS!K17-FINANCIALS!K23 -> 15063.3 | H35: =FINANCIALS!L17-FINANCIALS!L23 -> 14900.5
B37: ROCE | C37: =C35/C33 -> 0.43048684 | D37: =D35/D33 -> 0.30298388 | E37: =E35/E33 -> 0.25802431 | F37: =F35/F33 -> 0.28197088 | G37: =G35/G33 -> 0.33135284 | H37: =H35/H33 -> 0.29327074
B38: AVERAGE | C38: =AVERAGE(C37:H37) -> 0.31634825
B39: MEDIAN | C39: =MEDIAN(C37:H37) -> 0.29812731
B42: CALCULATION OF REINVESTMENT RATE | C42: 44276 | D42: 44642 | E42: 45008 | F42: 45374 | G42: 45740 | H42: 46106
B44: NET CAP EX | C44: =-SUM(DATA!I50:I51) -> 1883 | D44: =-SUM(DATA!J50:J51) -> 1941 | E44: =-SUM(DATA!K50:K51) -> 1428 | F44: =-SUM(DATA!L50:L51) -> 649 | G44: =-SUM(DATA!M50:M51) -> 1322 | H44: =-SUM(DATA!N50:N51) -> 1484
B45: CHANGES IN WORKING CAP | D45: =D17-C17 -> 2065 | E45: =E17-D17 -> 640 | F45: =F17-E17 -> -3858 | G45: =G17-F17 -> -3428 | H45: =H17-G17 -> -1156
B46: EBIT | D46: =D35 -> 13606.4 | E46: =E35 -> 13498.8 | F46: =F35 -> 13345.4 | G46: =G35 -> 15063.3 | H46: =H35 -> 14900.5
B47: TAX | D47: 0.25 | E47: 0.25 | F47: 0.25 | G47: 0.25 | H47: 0.25
B48: EBIT(1-TAX) | D48: =D46*(1-D47) -> 10204.8 | E48: =E46*(1-E47) -> 10124.1 | F48: =F46*(1-F47) -> 10009.05 | G48: =G46*(1-G47) -> 11297.475 | H48: =H46*(1-H47) -> 11175.375
B50: REINVESTMENT | D50: =D44+D45 -> 4006 | E50: =E44+E45 -> 2068 | F50: =F44+F45 -> -3209 | G50: =G44+G45 -> -2106 | H50: =H44+H45 -> 328
B51: REINVESTMENT RATE | D51: =D50/D46 -> 0.29442027 | E51: =E50/E46 -> 0.1531988 | F51: =F50/F46 -> -0.24045739 | G51: =G50/G46 -> -0.13981 | H51: =H50/H46 -> 0.022012684
B52: AVERAGE | C52: =AVERAGE(D51:H51) -> 0.017872874
B53: MEDIAN | C53: =MEDIAN(D51:H51) -> 0.022012684
B54: ASHWATH DAMODARAN SIRS RATE | C54: 0.075
B56: CALCULATION OF GROWTH RATE | C56: 44276 | D56: 44642 | E56: 45008 | F56: 45374 | G56: 45740 | H56: 46106
B57: =B51 -> REINVESTMENT RATE | D57: =D37 -> 0.30298388 | E57: =E37 -> 0.25802431 | F57: =F37 -> 0.28197088 | G57: =G37 -> 0.33135284 | H57: =H37 -> 0.29327074
B58: =B37 -> ROCE | D58: =D51 -> 0.29442027 | E58: =E51 -> 0.1531988 | F58: =F51 -> -0.24045739 | G58: =G51 -> -0.13981 | H58: =H51 -> 0.022012684
B59: GROWTH RATE | D59: =D58*D57 -> 0.089204596 | E59: =E58*E57 -> 0.039529016 | F59: =F58*F57 -> -0.067801982 | G59: =G58*G57 -> -0.046326441 | H59: =H58*H57 -> 0.0064556763
B61: GROWTH AVERAGE | C61: =AVERAGE(D59:H59) -> 0.0042121731
B62: GROWTH MEDIAN | C62: =MEDIAN(D59:H59) -> 0.0064556763 | D62: =2% -> 0.02
B63: WACC | C63: =12.95% -> 0.1295
B65: CALCULATION OF FCFF | C65: 46102 | D65: 46468 | E65: 46834 | F65: 47200 | G65: 47566 | H65: 47932
B66: EBIT | C66: =H46 -> 14900.5 | D66: =C66*(1+$D$62) -> 15198.51 | E66: =D66*(1+$D$62) -> 15502.48 | F66: =E66*(1+$D$62) -> 15812.53 | G66: =F66*(1+$D$62) -> 16128.78 | H66: =G66*(1+$D$62) -> 16451.356
B67: TAX | C67: 0.25 | D67: 0.25 | E67: 0.25 | F67: 0.25 | G67: 0.25 | H67: 0.25
B68: EBIT(1-TAX) | C68: =C66*(1-C67) -> 11175.375 | D68: =D66*(1-D67) -> 11398.882 | E68: =E66*(1-E67) -> 11626.86 | F68: =F66*(1-F67) -> 11859.397 | G68: =G66*(1-G67) -> 12096.585 | H68: =H66*(1-H67) -> 12338.517
B69: LESS REINVESTMENT RATE | C69: =C53 -> 0.022012684 | D69: =C69+($H$69-$C$69)/5 -> 0.032610147 | E69: =D69+($H$69-$C$69)/5 -> 0.04320761 | F69: =E69+($H$69-$C$69)/5 -> 0.053805074 | G69: =F69+($H$69-$C$69)/5 -> 0.064402537 | H69: =C54 -> 0.075
B70: FCFF | C70: =C68*(1-C69) -> 10929.375 | D70: =D68*(1-D69) -> 11027.163 | E70: =E68*(1-E69) -> 11124.491 | F70: =F68*(1-F69) -> 11221.302 | G70: =G68*(1-G69) -> 11317.535 | H70: =H68*(1-H69) -> 11413.128
B71: MID YEAR CONVENTION | C71: 0.5 | D71: 1.5 | E71: 2.5 | F71: 3.5 | G71: 4.5 | H71: 5.5
B72: DISCOUNTING FACTOR | C72: =1/(1+$C$63)^C71 -> 0.94092906 | D72: =1/(1+$C$63)^D71 -> 0.83304919 | E72: =1/(1+$C$63)^E71 -> 0.73753802 | F72: =1/(1+$C$63)^F71 -> 0.65297744 | G72: =1/(1+$C$63)^G71 -> 0.57811194 | H72: =1/(1+$C$63)^H71 -> 0.51182996
B73: PV OF FCFF | C73: =C70*C72 -> 10283.767 | D73: =D70*D72 -> 9186.1694 | E73: =E70*E72 -> 8204.7353 | F73: =F70*F72 -> 7327.2568 | G73: =G70*G72 -> 6542.8019 | H73: =H70*H72 -> 5841.581
B76: CALCULATION OF TERMINAL VALUE
B78: FCFF(N +1) | C78: =H66*(1+C63) -> 18581.807
B79: WACC | C79: =C63 -> 0.1295
B80: TERMINAL GROWTH RATE | C80: 0.0585
B81: TERMINAL VALUE | C81: =C78/(C79-C80) -> 261715.59
B83: CALCULATION OF EQUITY VALUE
B85: PV OF FCFF | C85: =SUM(C73:H73) -> 47386.311
B86: PV OF TERMINAL VALUE | C86: =C81*H72 -> 133953.88
B87: VALUE OF OPERATING ASSETS | C87: =SUM(C85:C86) -> 181340.19
B89: ADD CASH | C89: ='Data Sheet'!K69 -> 10555.5
B90: LESS DEBT | C90: =20291 -> 20291
B91: VALUE OF EQUITY | C91: =C87+C89-C90 -> 171604.69
B92: NO OF SHARES | C92: ='Data Sheet'!B6 -> 987.51052
B93: EQUITY VALUE PER SHARE | C93: =C91/C92 -> 173.77505
B95: SHARE PRICE | C95: =167 -> 167
B96: DISCOUNT/PPREMIUM | C96: =C95/C93-1 -> -0.038987467

Sheet DATA
C2: 42064 | D2: 42430 | E2: 42795 | F2: 43160 | G2: 43525 | H2: 43891 | I2: 44256 | J2: 44621 | K2: 44986 | L2: 45352 | M2: 45717 | N2: 46082
B3: Equity Capital | C3: 494 | D3: 494 | E3: 486 | F3: 905 | G3: 1207 | H3: 1143 | I3: 1096 | J3: 1096 | K3: 1098 | L3: 1045 | M3: 2094 | N3: 2098
B4: Reserves | C4: 36598 | D4: 45651 | E4: 51184 | F4: 47022 | G4: 55216 | H4: 54179 | I4: 53805 | J4: 64307 | K4: 76570 | L4: 73488 | M4: 80270 | N4: 85921
B5: Borrowings -
B6: Long term Borrowings | C6: 1271 | D6: 1736 | E6: 1961 | F6: 4527 | G6: 2837 | H6: 484 | I6: 746 | J6: 5646 | K6: 6127 | L6: 6230 | M6: 6395 | N6: 196
B7: Short term Borrowings | C7: 6444 | D7: 10265 | E7: 11674 | F7: 7960 | G7: 6808 | H7: 5402 | I7: 7587 | J7: 9523 | K7: 8882 | L7: 7917 | M7: 9786 | N7: 16591
B8: Lease Liabilities | C8: 0 | D8: 0 | E8: 0 | F8: 0 | G8: 0 | H8: 1920 | I8: 2118 | J8: 2423 | K8: 2457 | L8: 2318 | M8: 3022 | N8: 3504
B9: Other Borrowings | C9: 176 | D9: 521 | E9: 606 | F9: 1415 | G9: 301 | H9: 1918 | I9: 0 | J9: 0 | K9: 0 | L9: 0 | M9: 0 | N9: 0
B10: Other Liabilities -
B11: Non controlling int | C11: 165 | D11: 221 | E11: 239 | F11: 241 | G11: 264 | H11: 188 | I11: 150 | J11: 52 | K11: 59 | L11: 134 | M11: 214 | N11: 251
B12: Trade Payables | C12: 5849 | D12: 4902 | E12: 4867 | F12: 5120 | G12: 6266 | H12: 5840 | I12: 5182 | J12: 6252 | K12: 5972 | L12: 5766 | M12: 5867 | N12: 6289
B13: Advance from Customers | C13: 220 | D13: 238 | E13: 239 | F13: 190 | G13: 136 | H13: 146 | I13: 36 | J13: 63 | K13: 64 | L13: 119 | M13: 79 | N13: 82
B14: Other liability items | C14: 7134 | D14: 7562 | E14: 7415 | F14: 8012 | G14: 9551 | H14: 9780 | I14: 11846 | J14: 17913 | K14: 15694 | L14: 17592 | M14: 20202 | N14: 25952
B15: Total Liabilities | C15: 58350 | D15: 71590 | E15: 78672 | F15: 75391 | G15: 82586 | H15: 81000 | I15: 82566 | J15: 107276 | K15: 116924 | L15: 114609 | M15: 127929 | N15: 140884
B16: Fixed Assets -
B17: Land | C17: 587 | D17: 370 | E17: 381 | F17: 364 | G17: 370 | H17: 576 | I17: 590 | J17: 609 | K17: 614 | L17: 572 | M17: 550 | N17: 553 | O17: =C26-C27 -> 10837
B18: Building | C18: 2437 | D18: 2589 | E18: 2738 | F18: 2495 | G18: 2729 | H18: 5194 | I18: 5806 | J18: 6648 | K18: 7545 | L18: 7528 | M18: 8740 | N18: 9351
B19: Plant Machinery | C19: 7979 | D19: 9950 | E19: 10889 | F19: 6938 | G19: 9229 | H19: 8801 | I19: 9618 | J19: 10074 | K19: 12023 | L19: 10468 | M19: 10492 | N19: 10212 | O19: =C26-SUM(C17:C25) -> 0
B20: Equipments | C20: 422 | D20: 441 | E20: 543 | F20: 582 | G20: 591 | H20: 687 | I20: 686 | J20: 726 | K20: 782 | L20: 751 | M20: 766 | N20: 793
B21: Computers | C21: 0 | D21: 0 | E21: 0 | F21: 1776 | G21: 0 | H21: 1684 | I21: 1851 | J21: 2516 | K21: 0 | L21: 0 | M21: 0 | N21: 0
B22: Furniture n fittings | C22: 857 | D22: 961 | E22: 1022 | F22: 986 | G22: 1050 | H22: 1290 | I22: 1373 | J22: 1529 | K22: 1799 | L22: 1814 | M22: 1948 | N22: 2012
B23: Vehicles | C23: 85 | D23: 59 | E23: 43 | F23: 114 | G23: 95 | H23: 163 | I23: 134 | J23: 122 | K23: 103 | L23: 88 | M23: 77 | N23: 94
B24: Intangible Assets | C24: 5895 | D24: 10098 | E24: 12228 | F24: 11405 | G24: 0 | H24: 0 | I24: 13515 | J24: 24286 | K24: 30348 | L24: 31145 | M24: 32035 | N24: 38221
B25: Other fixed assets | C25: 43 | D25: 1836 | E25: 2681 | F25: 3314 | G25: 14609 | H25: 16608 | I25: 2794 | J25: 5479 | K25: 6174 | L25: 5564 | M25: 5218 | N25: 6002
B26: Gross Block | C26: 18305 | D26: 26304 | E26: 30525 | F26: 27972 | G26: 28672 | H26: 35004 | I26: 36368 | J26: 51990 | K26: 59388 | L26: 57930 | M26: 59826 | N26: 67237
B27: Accumulated Depreciation | C27: 7468 | D27: 9024 | E27: 10639 | F27: 9846 | G27: 11208 | H27: 12942 | I27: 13327 | J27: 14000 | K27: 14631 | L27: 14302 | M27: 14639 | N27: 15547
B28: NET FIXED ASSETS | C28: =C26-C27 -> 10837 | D28: =D26-D27 -> 17280 | E28: =E26-E27 -> 19886 | F28: =F26-F27 -> 18126 | G28: =G26-G27 -> 17464 | H28: =H26-H27 -> 22062 | I28: =I26-I27 -> 23041 | J28: =J26-J27 -> 37990 | ... N28: =N26-N27 -> 51690
B29: CWIP | C29: 395 | D29: 381 | E29: 738 | F29: 1378 | G29: 2142 | H29: 1881 | I29: 1853 | J29: 1602 | K29: 617 | L29: 723 | M29: 196 | N29: 412
B30: Investments | C30: 5532 | D30: 20915 | E30: 29913 | F30: 25797 | G30: 22887 | H30: 20032 | I30: 18775 | J30: 26154 | K30: 33073 | L30: 33384 | M30: 43926 | N30: 46786
B31: Other Assets -
B32: Inventories | C32: 485 | D32: 539 | E32: 392 | F32: 337 | G32: 395 | H32: 186 | I32: 106 | J32: 133 | K32: 119 | L32: 91 | M32: 69 | N32: 52
B33: Trade receivables + | C33: 9155 | D33: 9961 | E33: 9485 | F33: 10099 | G33: 10049 | H33: 10447 | I33: 9430 | J33: 11522 | K33: 12635 | L33: 11548 | M33: 11774 | N33: 13590 | O33: =SUM(C29:C36) -> 47513
B34: Cash Equivalents | C34: 16619 | D34: 9905 | E34: 5271 | F34: 4492 | G34: 15853 | H34: 14450 | I34: 16979 | J34: 10384 | K34: 9188 | L34: 9695 | M34: 12197 | N34: 10556 | O34: =O33+C28 -> 58350
B35: Loans n Advances | C35: 1326 | D35: 2612 | E35: 1613 | F35: 2354 | G35: 2358 | H35: 1625 | I35: 1830 | J35: 2294 | K35: 2830 | L35: 2826 | M35: 2668 | N35: 3340
B36: Other asset items | C36: 14001 | D36: 9998 | E36: 11374 | F36: 12807 | G36: 11438 | H36: 10315 | I36: 10552 | J36: 17198 | K36: 13705 | L36: 12713 | M36: 11910 | N36: 14458
B37: Total Assets | C37: 58350 | D37: 71590 | E37: 78672 | F37: 75391 | G37: 82586 | H37: 81000 | I37: 82566 | J37: 107276 | K37: 116924 | L37: 114609 | M37: 127929 | N37: 140884
C39: 42064 | D39: 42430 | E39: 42795 | F39: 43160 | G39: 43525 | H39: 43891 | I39: 44256 | J39: 44621 | K39: 44986 | L39: 45352 | M39: 45717 | N39: 46082
B40: Cash from Operating Activity - | C40: 7840 | D40: 7887 | E40: 9277 | F40: 8423 | G40: 11632 | H40: 10064 | I40: 14755 | J40: 11080 | K40: 13060 | L40: 17622 | M40: 16943 | N40: 14932
B41: Profit from operations | C41: 10990 | D41: 11180 | E41: 11374 | F41: 11322 | G41: 11430 | H41: 13088 | I41: 14954 | J41: 17297 | K41: 17538 | L41: 17416 | M41: 18533 | N41: 18948
B42: Receivables | C42: -888 | D42: -532 | E42: 335 | F42: -974 | G42: 139 | H42: -333 | I42: 1285 | J42: -4323 | K42: -98 | L42: 782 | M42: 189 | N42: -1144
B43: Inventory | C43: -256 | D43: -54 | E43: 148 | F43: 54 | G43: -57 | H43: 208 | I43: 80 | J43: -26 | K43: 16 | L43: 29 | M43: 21 | N43: 18
B44: Payables | C44: 0 | D44: 468 | E44: -523 | F44: 450 | G44: 2084 | H44: -1240 | I44: 570 | J44: 970 | K44: -982 | L44: -44 | M44: 55 | N44: 848
B45: Loans Advances | C45: -363 | D45: 0 | E45: 0 | F45: 0 | G45: 0 | H45: 0 | I45: 0 | J45: 0 | K45: 0 | L45: 0 | M45: 0 | N45: 0
B46: Other WC items | C46: 783 | D46: -481 | E46: 492 | F46: 381 | G46: 550 | H46: -1021 | I46: 357 | J46: -270 | K46: -391 | L46: 974 | M46: 762 | N46: -1115
B47: Working capital changes | C47: -723 | D47: -599 | E47: 451 | F47: -88 | G47: 2716 | H47: -2386 | I47: 2292 | J47: -3649 | K47: -1456 | L47: 1741 | M47: 1027 | N47: -1392
B48: Direct taxes | C48: -2427 | D48: -2694 | E48: -2548 | F48: -2810 | G48: -2515 | H48: -638 | I48: -2492 | J48: -2569 | K48: -3022 | L48: -1536 | M48: -2618 | N48: -2624
B49: Cash from Investing Activity - | C49: -2537 | D49: -13761 | E49: -11770 | F49: 3595 | G49: 5065 | H49: 3593 | I49: 685 | J49: -22321 | K49: -8169 | L49: 1144 | M49: -8044 | N49: -2448
B50: Fixed assets purchased | C50: -1285 | D50: -1395 | E50: -2085 | F50: -2187 | G50: -2278 | H50: -2350 | I50: -1958 | J50: -2015 | K50: -1483 | L50: -1051 | M50: -1504 | N50: -1560
B51: Fixed assets sold | C51: 143 | D51: 78 | E51: 558 | F51: 117 | G51: 194 | H51: 127 | I51: 75 | J51: 74 | K51: 55 | L51: 402 | M51: 182 | N51: 76
... B71: CFO/OP | C71: 1 | D71: 0.98 | E71: 1.04 | F71: 1.08 | G71: 1.22 | H71: 0.87 | I71: 1.17 | J71: 0.82 | K71: 0.96 | L71: 1.14 | M71: 1.09 | N71: 0.99

Sheet BETA 
C1: WIPRO | H1: NIFTY 50
B2: Date | C2: Price | D2: RETURNS | G2: Date | H2: Price | I2: =H2/H1-1 -> #VALUE!
B3: 46266 | C3: 166.3 | G3: 46266 | H3: 23431.5 | I3: =H3/H2-1 -> #VALUE!
B4: 46235 | C4: 184.5 | D4: =C4/C3-1 -> 0.10944077 | G4: 46235 | H4: 24080.4 | I4: =H4/H3-1 -> 0.02769349 | K4: =SLOPE(D4:D62,I4:I62) -> 0.91215021
B5: 46204 | C5: 183.65 | D5: =C5/C4-1 -> -0.0046070461 | G5: 46204 | H5: 24383.6 | I5: =H5/H4-1 -> 0.012591153 | K5: =N27 -> 0.91215021
B6: 46174 | C6: 170.39 | D6: =C6/C5-1 -> -0.072202559 | G6: 46174 | H6: 23865.75 | I6: =H6/H5-1 -> -0.021237635
B7: 46143 | C7: 204.25 | D7: =C7/C6-1 -> 0.19872058 | G7: 46143 | H7: 23547.75 | I7: =H7/H6-1 -> -0.013324534 | K7: 0.75
B8: 46113 | C8: 200.65 | D8: =C8/C7-1 -> -0.017625459 | G8: 46113 | H8: 23997.55 | I8: =H8/H7-1 -> 0.019101613 | K8: 0.25
B9: 46082 | C9: 187.64 | D9: =C9/C8-1 -> -0.064839272 | G9: 46082 | H9: 22331.4 | I9: =H9/H8-1 -> -0.069430004 | K9: 1
B10: 46054 | C10: 200.96 | D10: =C10/C9-1 -> 0.070986996 | G10: 46054 | H10: 25178.65 | I10: =H10/H9-1 -> 0.12749984 | K10: =K5 -> 0.91215021 | M10: SUMMARY OUTPUT
B11: 46023 | C11: 236.9 | D11: =C11/C10-1 -> 0.17884156 | G11: 46023 | H11: 25320.65 | I11: =H11/H10-1 -> 0.0056396987 | K11: =(K7*K10)+(K8*K9) -> 0.93411266
B12: 45992 | C12: 263.28 | D12: =C12/C11-1 -> 0.111355 | G12: 45992 | H12: 26129.6 | I12: =H12/H11-1 -> 0.031948232 | M12: Regression Statistics
B13: 45962 | C13: 249.53 | D13: =C13/C12-1 -> -0.052225767 | G13: 45962 | H13: 26202.95 | I13: =H13/H12-1 -> 0.0028071612 | M13: Multiple R | N13: 0.4437517
B14: 45931 | C14: 240.67 | D14: =C14/C13-1 -> -0.035506753 | G14: 45931 | H14: 25722.1 | I14: =H14/H13-1 -> -0.018350987 | M14: R Square | N14: 0.19691557
B15: 45901 | C15: 239.37 | D15: =C15/C14-1 -> -0.0054015872 | G15: 45901 | H15: 24611.1 | I15: =H15/H14-1 -> -0.04319243 | M15: Adjusted R Square | N15: 0.18282637
B16: 45870 | C16: 249.41 | D16: =C16/C15-1 -> 0.041943435 | G16: 45870 | H16: 24426.85 | I16: =H16/H15-1 -> -0.0074864594 | M16: Standard Error | N16: 0.071533826
B17: 45839 | C17: 248.3 | D17: =C17/C16-1 -> -0.0044505032 | G17: 45839 | H17: 24768.35 | I17: =H17/H16-1 -> 0.013980517 | M17: Observations | N17: 59
B18: 45809 | C18: 265.98 | D18: =C18/C17-1 -> 0.071204188 | G18: 45809 | H18: 25517.05 | I18: =H18/H17-1 -> 0.030228094
B19: 45778 | C19: 249.67 | D19: =C19/C18-1 -> -0.0613204 | G19: 45778 | H19: 24750.7 | I19: =H19/H18-1 -> -0.03003286 | M19: ANOVA
B20: 45748 | C20: 241.5 | D20: =C20/C19-1 -> -0.032723195 | G20: 45748 | H20: 24334.2 | I20: =H20/H19-1 -> -0.016827807 | N20: df | O20: SS | P20: MS | Q20: F | R20: Significance F
B21: 45717 | C21: 262.25 | D21: =C21/C20-1 -> 0.085921325 | G21: 45717 | H21: 23519.35 | I21: =H21/H20-1 -> -0.033485794 | M21: Regression | N21: 1 | O21: 0.071518206 | P21: 0.071518206 | Q21: 13.976348 | R21: 0.00043102045
B22: 45689 | C22: 277.65 | D22: =C22/C21-1 -> 0.058722593 | G22: 45689 | H22: 22124.7 | I22: =H22/H21-1 -> -0.059297982 | M22: Residual | N22: 57 | O22: 0.29167403 | P22: 0.0051170883
B23: 45658 | C23: 311.9 | D23: =C23/C22-1 -> 0.12335674 | G23: 45658 | H23: 23508.4 | I23: =H23/H22-1 -> 0.062540961 | M23: Total | N23: 58 | O23: 0.36319224
B24: 45627 | C24: 301.85 | D24: =C24/C23-1 -> -0.032221866 | G24: 45627 | H24: 23644.8 | I24: =H24/H23-1 -> 0.0058021813
B25: 45597 | C25: 288.92 | D25: =C25/C24-1 -> -0.042835846 | G25: 45597 | H25: 24131.1 | I25: =H25/H24-1 -> 0.02056689 | N25: Coefficients | O25: Standard Error | P25: t Stat | Q25: P-value | R25: Lower 95% | S25: Upper 95% | T25: Lower 95.0% | U25: Upper 95.0%
B26: 45566 | C26: 275.9 | D26: =C26/C25-1 -> -0.045064378 | G26: 45566 | H26: 24205.35 | I26: =H26/H25-1 -> 0.0030769422 | M26: Intercept | N26: 0.017979145 | O26: 0.0093651035 | P26: 1.9198021 | Q26: 0.05989259 | R26: -0.0007741513 | S26: 0.036732441 | T26: -0.0007741513 | U26: 0.036732441
B27: 45536 | C27: 270.73 | D27: =C27/C26-1 -> -0.018738673 | G27: 45536 | H27: 25810.85 | I27: =H27/H26-1 -> 0.066328312 | M27: X Variable 1 | N27: 0.91215021 | O27: 0.24398859 | P27: 3.7384954 | Q27: 0.00043102045 | R27: 0.42357149 | S27: 1.4007289 | T27: 0.42357149 | U27: 1.4007289
B28: 45505 | C28: 269.2 | D28: =C28/C27-1 -> -0.005651387 | G28: 45505 | H28: 25235.9 | I28: =H28/H27-1 -> -0.022275516
B29: 45474 | C29: 261 | D29: =C29/C28-1 -> -0.030460624 | G29: 45474 | H29: 24951.15 | I29: =H29/H28-1 -> -0.011283529
B30: 45444 | C30: 257.43 | D30: =C30/C29-1 -> -0.013678161 | G30: 45444 | H30: 24010.6 | I30: =H30/H29-1 -> -0.037695657
B31: 45413 | C31: 219.1 | D31: =C31/C30-1 -> -0.14889485 | G31: 45413 | H31: 22530.7 | I31: =H31/H30-1 -> -0.061635278
B32: 45383 | C32: 231.2 | D32: =C32/C31-1 -> 0.055225924 | G32: 45383 | H32: 22604.85 | I32: =H32/H31-1 -> 0.0032910651
B33: 45352 | C33: 240.05 | D33: =C33/C32-1 -> 0.038278547 | G33: 45352 | H33: 22326.9 | I33: =H33/H32-1 -> -0.012296034
B34: 45323 | C34: 259.3 | D34: =C34/C33-1 -> 0.080191627 | G34: 45323 | H34: 21982.8 | I34: =H34/H33-1 -> -0.015411902
B35: 45292 | C35: 239.07 | D35: =C35/C34-1 -> -0.07801774 | G35: 45292 | H35: 21725.7 | I35: =H35/H34-1 -> -0.011695507
B36: 45261 | C36: 235.65 | D36: =C36/C35-1 -> -0.014305434 | G36: 45261 | H36: 21731.4 | I36: =H36/H35-1 -> 0.00026236209
B37: 45231 | C37: 206.53 | D37: =C37/C36-1 -> -0.1235731 | G37: 45231 | H37: 20133.15 | I37: =H37/H36-1 -> -0.073545653
B38: 45200 | C38: 190.9 | D38: =C38/C37-1 -> -0.075679078 | G38: 45200 | H38: 19079.6 | I38: =H38/H37-1 -> -0.052329119
B39: 45170 | C39: 203.03 | D39: =C39/C38-1 -> 0.063541121 | G39: 45170 | H39: 19638.3 | I39: =H39/H38-1 -> 0.029282585
... B62: 44470 | C62: 323.38 | D62: =C62/C61-1 -> 0.014939426 | G62: 44470 | H62: 17671.65 | I62: =H62/H61-1 -> 0.040537119

Sheet Data Sheet
A1: COMPANY NAME | B1: WIPRO LTD | E1: =IF(B2<>B3, "A NEW VERSION OF THE WORKSHEET IS AVAILABLE", "")
A2: LATEST VERSION | B2: 2.1 | E2: PLEASE DO NOT MAKE ANY CHANGES TO THIS SHEET
A3: CURRENT VERSION | B3: 2.1
A5: META
A6: Number of shares | B6: =IF(B9>0, B9/B8, 0) -> 987.51052
A7: Face Value | B7: 2
A8: Current Price | B8: 166.3
A9: Market Capitalization | B9: 164223
A15: PROFIT & LOSS
A16: Report Date | B16: 42825 | C16: 43190 | D16: 43555 | E16: 43921 | F16: 44286 | G16: 44651 | H16: 45016 | I16: 45382 | J16: 45747 | K16: 46112
A17: Sales | B17: 55448.4 | C17: 54487.1 | D17: 59018.9 | E17: 61137.6 | F17: 61934.9 | G17: 79312 | H17: 90487.6 | I17: 89760.3 | J17: 89088.4 | K17: 92624
A18: Raw Material Cost | B18: 2556 | C18: 1843.4 | D18: 1407.3 | E18: 936 | F18: 695.7 | G18: 673.5 | H18: 649.4 | I18: 383.2 | J18: 296.7 | K18: 575.5
A19: Change in Inventory | B19: -141.1 | C19: -50.5 | D19: 67.3 | E19: -202.2 | F19: -31.5 | G19: 36.9 | H19: -15 | I19: -27.8 | J19: -19.5 | K19: -17.1
A20: Power and Fuel
A21: Other Mfr. Exp | G21: 1327.9 | H21: 1871.7 | I21: 1837.8 | J21: 1933.8 | K21: 2172
A22: Employee Cost | B22: 26808.1 | C22: 27222.3 | D22: 29977.4 | E22: 32657.1 | F22: 33237.1 | G22: 45007.5 | H22: 53764.4 | I22: 54930.1 | J22: 53347.7 | K22: 55585.5
A23: Selling and admin | B23: 13775.7 | C23: 13853.3 | D23: 14796.3 | E23: 14350.4 | F23: 12523.8 | G23: 15524.3 | H23: 17123.9 | I23: 15667.3 | J23: 15481.7 | K23: 16038.7
A24: Other Expenses | B24: 846.6 | C24: 1130.5 | D24: 1292.6 | E24: 649.6 | F24: 675.4 | G24: 131.5 | H24: 224.2 | I24: 161.6 | J24: -12.2 | K24: 424
A25: Other Income | B25: 2622.6 | C25: 2549.8 | D25: 2613.8 | E25: 2727.9 | F25: 2403.7 | G25: 2066.9 | H25: 2274.6 | I25: 2630.8 | J25: 3909.4 | K25: 3899.4
A26: Depreciation | B26: 2310 | C26: 2111.7 | D26: 1946.7 | E26: 2085.5 | F26: 2763.4 | G26: 3077.8 | H26: 3340.2 | I26: 3407.1 | J26: 2957.9 | K26: 2910.7
A27: Interest | B27: 594.2 | C27: 583 | D27: 737.5 | E27: 732.8 | F27: 508.8 | G27: 532.5 | H27: 1007.7 | I27: 1255.2 | J27: 1477 | K27: 1457.7
A28: Profit before tax | B28: 11039.3 | C28: 10242.2 | D28: 11542.2 | E28: 12251.9 | F28: 13902.9 | G28: 15140.8 | H28: 14765.7 | I28: 14721 | J28: 17495.7 | K28: 17342.2
A29: Tax | B29: 2521.4 | C29: 2239.1 | D29: 2524.3 | E29: 2480.1 | F29: 3034.9 | G29: 2897.4 | H29: 3399.2 | I29: 3608.9 | J29: 4277.7 | K29: 4076.7
A30: Net profit | B30: 8493.1 | C30: 8002.8 | D30: 9003.7 | E30: 9722.3 | F30: 10796.4 | G30: 12229.6 | H30: 11350 | I30: 11045.2 | J30: 13135.4 | K30: 13197.4
A31: Dividend Amount | B31: 486.1 | C31: 452.4 | D31: 603.4 | E31: 571.35 | F31: 547.9 | G31: 3289.2 | H31: 548.8 | I31: 522.5 | J31: 6283.2 | K31: 11537.35
A40: Quarters
A41: Report Date | B41: 45382 | C41: 45473 | D41: 45565 | E41: 45657 | F41: 45747 | G41: 45838 | H41: 45930 | I41: 46022 | J41: 46112 | K41: 46203
A42: Sales | B42: 22208.3 | C42: 21963.8 | D42: 22301.6 | E42: 22318.8 | F42: 22504.2 | G42: 22134.6 | H42: 22697.3 | I42: 23555.8 | J42: 24236.3 | K42: 24478.6
A43: Expenses | B43: 17827.7 | C43: 17614.2 | D43: 17798.3 | E43: 17779 | F43: 17880.2 | G43: 17901.5 | H43: 18324.9 | I43: 19259.4 | J43: 19327 | K43: 19845.9
A44: Other Income | B44: 652.9 | C44: 729.7 | D44: 962.2 | E44: 1004.6 | F44: 1217.4 | G44: 1071.5 | H44: 962.9 | I44: 1008.1 | J44: 856.9 | K44: 979
A45: Depreciation | B45: 840.5 | C45: 728.9 | D45: 830.8 | E45: 676.5 | F45: 721.7 | G45: 685.5 | H45: 691.7 | I45: 805 | J45: 728.5 | K45: 804.4
A46: Interest | B46: 330.8 | C46: 328.8 | D46: 356.9 | E46: 414.6 | F46: 376.7 | G46: 360.8 | H46: 361.2 | I46: 365.6 | J46: 370.1 | K46: 472.8
A47: Profit before tax | B47: 3862.2 | C47: 4021.6 | D47: 4277.8 | E47: 4453.3 | F47: 4743 | G47: 4258.3 | H47: 4282.4 | I47: 4133.9 | J47: 4667.6 | K47: 4334.5
A48: Tax | B48: 1004 | C48: 985 | D48: 1051.2 | E48: 1086.6 | F48: 1154.9 | G48: 921.8 | H48: 1020 | I48: 988.9 | J48: 1146 | K48: 978.2
A49: Net profit | B49: 2834.6 | C49: 3003.2 | D49: 3208.8 | E49: 3353.8 | F49: 3569.6 | G49: 3330.4 | H49: 3246.2 | I49: 3119 | J49: 3501.8 | K49: 3352
A50: Operating Profit | B50: 4380.6 | C50: 4349.6 | D50: 4503.3 | E50: 4539.8 | F50: 4624 | G50: 4233.1 | H50: 4372.4 | I50: 4296.4 | J50: 4909.3 | K50: 4632.7
A55: BALANCE SHEET
A56: Report Date | B56: 42825 | C56: 43190 | D56: 43555 | E56: 43921 | F56: 44286 | G56: 44651 | H56: 45016 | I56: 45382 | J56: 45747 | K56: 46112
A57: Equity Share Capital | B57: 486.1 | C57: 904.8 | D57: 1206.8 | E57: 1142.7 | F57: 1095.8 | G57: 1096.4 | H57: 1097.6 | I57: 1045 | J57: 2094.4 | K57: 2097.7
A58: Reserves | B58: 51184.1 | C58: 47021.5 | D58: 55215.8 | E58: 54179 | F58: 53805.2 | G58: 64306.6 | H58: 76570.3 | I58: 73488 | J58: 80269.7 | K58: 85920.6
A59: Borrowings | B59: 14241.2 | C59: 13901.2 | D59: 9946.7 | E59: 9724 | F59: 10451.4 | G59: 17592.9 | H59: 17466.6 | I59: 16464.9 | J59: 19203.5 | K59: 20291
A60: Other Liabilities | B60: 12760.8 | C60: 13563.3 | D60: 16217.1 | E60: 15953.9 | F60: 17213.4 | G60: 24279.7 | H60: 21789.2 | I60: 23611 | J60: 26361.5 | K60: 32574.2
A61: Total | B61: 78672.2 | C61: 75390.8 | D61: 82586.4 | E61: 80999.6 | F61: 82565.8 | G61: 107275.6 | H61: 116923.7 | I61: 114608.9 | J61: 127929.1 | K61: 140883.5
A62: Net Block | B62: 19886.5 | C62: 18126.7 | D62: 17464.7 | E62: 22062.1 | F62: 23040.3 | G62: 37989.6 | H62: 44756.8 | I62: 43628 | J62: 45186.7 | K62: 51690.1
A63: Capital Work in Progress | B63: 737.7 | C63: 1377.7 | D63: 2141.8 | E63: 1881.1 | F63: 1853.2 | G63: 1601.5 | H63: 617.1 | I63: 723.4 | J63: 196.4 | K63: 412.2
A64: Investments | B64: 29913.3 | C64: 25796.8 | D64: 22886.7 | E64: 20032 | F64: 18774.7 | G64: 26153.8 | H64: 33073.2 | I64: 33384.4 | J64: 43925.9 | K64: 46785.9
A65: Other Assets | B65: 28134.7 | C65: 30089.6 | D65: 40093.2 | E65: 37024.4 | F65: 38897.6 | G65: 41530.7 | H65: 38476.6 | I65: 36873.1 | J65: 38620.1 | K65: 41995.3
A66: Total | B66: 78672.2 | C66: 75390.8 | D66: 82586.4 | E66: 80999.6 | F66: 82565.8 | G66: 107275.6 | H66: 116923.7 | I66: 114608.9 | J66: 127929.1 | K66: 140883.5
A67: Receivables | B67: 9484.6 | C67: 10099 | D67: 10048.9 | E67: 10447.4 | F67: 9429.8 | G67: 11521.9 | H67: 12635 | I67: 11547.7 | J67: 11774.5 | K67: 13590.1
... A70: No. of Equity Shares | B70: 2430900565 | C70: 4523784491 | D70: 6033935388 | E70: 5713357390 | F70: 5479138555 | G70: 5482070115 | H70: 5487917741 | I70: 5225138246 | J70: 10472136049 | K70: 10488412458
A71: New Bonus Shares | C71: 2433074327 | D71: 1508469180
A72: Face value | B72: 2 | C72: 2 | D72: 2 | E72: 2 | F72: 2 | G72: 2 | H72: 2 | I72: 2 | J72: 2 | K72: 2
A80: CASH FLOW:
A81: Report Date | B81: 42825 | C81: 43190 | D81: 43555 | E81: 43921 | F81: 44286 | G81: 44651 | H81: 45016 | I81: 45382 | J81: 45747 | K81: 46112
A82: Cash from Operating Activity | B82: 9277.3 | C82: 8423.3 | D82: 11631.6 | E82: 10064.3 | F82: 14755 | G82: 11079.7 | H82: 13060.1 | I82: 17621.6 | J82: 16942.6 | K82: 14931.6
A83: Cash from Investing Activity | B83: -11769.5 | C83: 3595.3 | D83: 5065.2 | E83: 3593.4 | F83: 684.9 | G83: -22321.3 | H83: -8169.2 | I83: 1144.1 | J83: -8044 | K83: -2447.5
A84: Cash from Financing Activity | B84: -2275.2 | C84: -12997.8 | D84: -4936.9 | E84: -15099.8 | F84: -12884 | G84: 4658.6 | H84: -6088.1 | I84: -18256.7 | J84: -6396.3 | K84: -14126
A85: Net Cash Flow | B85: -4767.4 | C85: -979.2 | D85: 11759.9 | E85: -1442.1 | F85: 2555.9 | G85: -6583 | H85: -1197.2 | I85: 509 | J85: 2502.3 | K85: -1641.9
A90: PRICE: | B90: 96.7 | C90: 105.44 | D90: 127.4 | E90: 98.35 | F90: 207.08 | G90: 295.95 | H90: 182.63 | I90: 240.05 | J90: 262.25 | K90: 187.64
A92: DERIVED:
A93: Adjusted Equity Shares in Cr | B93: 1296.48 | C93: 1206.35 | D93: 1206.79 | E93: 1142.67 | F93: 1095.83 | G93: 1096.41 | H93: 1097.58 | I93: 1045.03 | J93: 1047.21 | K93: 1048.84

Sheet Profit & Loss
A1: ='Data Sheet'!B1 -> WIPRO LTD | H1: =UPDATE | M1: SCREENER.IN
A3: Narration | B3: ='Data Sheet'!B16 -> 42825 | C3: ='Data Sheet'!C16 -> 43190 | D3: ='Data Sheet'!D16 -> 43555 | E3: ='Data Sheet'!E16 -> 43921 | F3: ='Data Sheet'!F16 -> 44286 | G3: ='Data Sheet'!G16 -> 44651 | H3: ='Data Sheet'!H16 -> 45016 | I3: ='Data Sheet'!I16 -> 45382 | ... K3: ='Data Sheet'!K16 -> 46112 | L3: Trailing | M3: Best Case | N3: Worst Case
A4: Sales | B4: ='Data Sheet'!B17 -> 55448.4 | C4: ='Data Sheet'!C17 -> 54487.1 | D4: ='Data Sheet'!D17 -> 59018.9 | E4: ='Data Sheet'!E17 -> 61137.6 | F4: ='Data Sheet'!F17 -> 61934.9 | G4: ='Data Sheet'!G17 -> 79312 | H4: ='Data Sheet'!H17 -> 90487.6 | I4: ='Data Sheet'!I17 -> 89760.3 | ... K4: ='Data Sheet'!K17 -> 92624 | L4: =SUM(Quarters!H4:K4) -> 94968 | M4: =$K4+M23*K4 -> 96299.915 | N4: =$K4+N23*L4 -> 93365.588
A5: Expenses | B5: =SUM('Data Sheet'!B18,'Data Sheet'!B20:B24, -1*'Data Sheet'!B19) -> 44127.5 | C5: =SUM('Data Sheet'!C18,'Data Sheet'!C20:C24, -1*'Data Sheet'!C19) -> 44100 | D5: =SUM('Data Sheet'!D18,'Data Sheet'!D20:D24, -1*'Data Sheet'!D19) -> 47406.3 | E5: =SUM('Data Sheet'!E18,'Data Sheet'!E20:E24, -1*'Data Sheet'!E19) -> 48795.3 | F5: =SUM('Data Sheet'!F18,'Data Sheet'!F20:F24, -1*'Data Sheet'!F19) -> 47163.5 | G5: =SUM('Data Sheet'!G18,'Data Sheet'!G20:G24, -1*'Data Sheet'!G19) -> 62627.8 | H5: =SUM('Data Sheet'!H18,'Data Sheet'!H20:H24, -1*'Data Sheet'!H19) -> 73648.6 | I5: =SUM('Data Sheet'!I18,'Data Sheet'!I20:I24, -1*'Data Sheet'!I19) -> 73007.8 | ... K5: =SUM('Data Sheet'!K18,'Data Sheet'!K20:K24, -1*'Data Sheet'!K19) -> 74812.8 | L5: =SUM(Quarters!H5:K5) -> 76757.2 | M5: =M4-M6 -> 77646.395 | N5: =N4-N6 -> 75462.062
A6: Operating Profit | B6: =B4-B5 -> 11320.9 | C6: =C4-C5 -> 10387.1 | D6: =D4-D5 -> 11612.6 | E6: =E4-E5 -> 12342.3 | F6: =F4-F5 -> 14771.4 | G6: =G4-G5 -> 16684.2 | H6: =H4-H5 -> 16839 | I6: =I4-I5 -> 16752.5 | ... K6: =K4-K5 -> 17811.2 | L6: =SUM(Quarters!H6:K6) -> 18210.8 | M6: =M4*M24 -> 18653.52 | N6: =N4*N24 -> 17903.526
A7: Other Income | B7: ='Data Sheet'!B25 -> 2622.6 | C7: ='Data Sheet'!C25 -> 2549.8 | D7: ='Data Sheet'!D25 -> 2613.8 | E7: ='Data Sheet'!E25 -> 2727.9 | F7: ='Data Sheet'!F25 -> 2403.7 | G7: ='Data Sheet'!G25 -> 2066.9 | H7: ='Data Sheet'!H25 -> 2274.6 | I7: ='Data Sheet'!I25 -> 2630.8 | ... K7: ='Data Sheet'!K25 -> 3899.4 | L7: =SUM(Quarters!H7:K7) -> 3806.9 | M7: 0 | N7: 0
A8: Depreciation | B8: ='Data Sheet'!B26 -> 2310 | C8: ='Data Sheet'!C26 -> 2111.7 | D8: ='Data Sheet'!D26 -> 1946.7 | E8: ='Data Sheet'!E26 -> 2085.5 | F8: ='Data Sheet'!F26 -> 2763.4 | G8: ='Data Sheet'!G26 -> 3077.8 | H8: ='Data Sheet'!H26 -> 3340.2 | I8: ='Data Sheet'!I26 -> 3407.1 | ... K8: ='Data Sheet'!K26 -> 2910.7 | L8: =SUM(Quarters!H8:K8) -> 3029.6 | M8: =+$L8 -> 3029.6 | N8: =+$L8 -> 3029.6
A9: Interest | B9: ='Data Sheet'!B27 -> 594.2 | C9: ='Data Sheet'!C27 -> 583 | D9: ='Data Sheet'!D27 -> 737.5 | E9: ='Data Sheet'!E27 -> 732.8 | F9: ='Data Sheet'!F27 -> 508.8 | G9: ='Data Sheet'!G27 -> 532.5 | H9: ='Data Sheet'!H27 -> 1007.7 | I9: ='Data Sheet'!I27 -> 1255.2 | ... K9: ='Data Sheet'!K27 -> 1457.7 | L9: =SUM(Quarters!H9:K9) -> 1569.7 | M9: =+$L9 -> 1569.7 | N9: =+$L9 -> 1569.7
A10: Profit before tax | B10: ='Data Sheet'!B28 -> 11039.3 | C10: ='Data Sheet'!C28 -> 10242.2 | D10: ='Data Sheet'!D28 -> 11542.2 | E10: ='Data Sheet'!E28 -> 12251.9 | F10: ='Data Sheet'!F28 -> 13902.9 | G10: ='Data Sheet'!G28 -> 15140.8 | H10: ='Data Sheet'!H28 -> 14765.7 | I10: ='Data Sheet'!I28 -> 14721 | ... K10: ='Data Sheet'!K28 -> 17342.2 | L10: =SUM(Quarters!H10:K10) -> 17418.4 | M10: =M6+M7-SUM(M8:M9) -> 14054.22 | N10: =N6+N7-SUM(N8:N9) -> 13304.226
A11: Tax | B11: ='Data Sheet'!B29 -> 2521.4 | C11: ='Data Sheet'!C29 -> 2239.1 | D11: ='Data Sheet'!D29 -> 2524.3 | E11: ='Data Sheet'!E29 -> 2480.1 | F11: ='Data Sheet'!F29 -> 3034.9 | G11: ='Data Sheet'!G29 -> 2897.4 | H11: ='Data Sheet'!H29 -> 3399.2 | I11: ='Data Sheet'!I29 -> 3608.9 | ... K11: ='Data Sheet'!K29 -> 4076.7 | L11: =SUM(Quarters!H11:K11) -> 4133.1 | M11: =IF($L10>0,$L11/$L10,0) -> 0.23728356 | N11: =IF($L10>0,$L11/$L10,0) -> 0.23728356
A12: Net profit | B12: ='Data Sheet'!B30 -> 8493.1 | C12: ='Data Sheet'!C30 -> 8002.8 | D12: ='Data Sheet'!D30 -> 9003.7 | E12: ='Data Sheet'!E30 -> 9722.3 | F12: ='Data Sheet'!F30 -> 10796.4 | G12: ='Data Sheet'!G30 -> 12229.6 | H12: ='Data Sheet'!H30 -> 11350 | I12: ='Data Sheet'!I30 -> 11045.2 | ... K12: ='Data Sheet'!K30 -> 13197.4 | L12: =SUM(Quarters!H12:K12) -> 13219 | M12: =M10-M11*M10 -> 10719.385 | N12: =N10-N11*N10 -> 10147.352
A13: EPS | B13: =IF('Data Sheet'!B93>0,B12/'Data Sheet'!B93,0) -> 6.5508916 | C13: =IF('Data Sheet'!C93>0,C12/'Data Sheet'!C93,0) -> 6.6338956 | D13: =IF('Data Sheet'!D93>0,D12/'Data Sheet'!D93,0) -> 7.4608673 | E13: =IF('Data Sheet'!E93>0,E12/'Data Sheet'!E93,0) -> 8.5084058 | F13: =IF('Data Sheet'!F93>0,F12/'Data Sheet'!F93,0) -> 9.8522581 | G13: =IF('Data Sheet'!G93>0,G12/'Data Sheet'!G93,0) -> 11.154222 | H13: =IF('Data Sheet'!H93>0,H12/'Data Sheet'!H93,0) -> 10.340932 | I13: =IF('Data Sheet'!I93>0,I12/'Data Sheet'!I93,0) -> 10.569266 | ... K13: =IF('Data Sheet'!K93>0,K12/'Data Sheet'!K93,0) -> 12.582853 | L13: =IF('Data Sheet'!$B6>0,'Profit & Loss'!L12/'Data Sheet'!$B6,0) -> 13.386186 | M13: =IF('Data Sheet'!$B6>0,'Profit & Loss'!M12/'Data Sheet'!$B6,0) -> 10.854957 | N13: =IF('Data Sheet'!$B6>0,'Profit & Loss'!N12/'Data Sheet'!$B6,0) -> 10.27569
A14: Price to earning | B14: =IF(B15>0,B15/B13,"") -> 14.761349 | C14: =IF(C15>0,C15/C13,"") -> 15.89413 | D14: =IF(D15>0,D15/D13,"") -> 17.075763 | E14: =IF(E15>0,E15/E13,"") -> 11.559157 | F14: =IF(F15>0,F15/F13,"") -> 21.018532 | G14: =IF(G15>0,G15/G13,"") -> 26.532555 | H14: =IF(H15>0,H15/H13,"") -> 17.660884 | I14: =IF(I15>0,I15/I13,"") -> 22.712079 | ... K14: =IF(K15>0,K15/K13,"") -> 14.912357 | L14: =IF(L13>0,L15/L13,0) -> 12.423254 | M14: =M25 -> 17.738844 | N14: =N25 -> 12.423254
A15: Price | B15: ='Data Sheet'!B90 -> 96.7 | C15: ='Data Sheet'!C90 -> 105.44 | D15: ='Data Sheet'!D90 -> 127.4 | E15: ='Data Sheet'!E90 -> 98.35 | F15: ='Data Sheet'!F90 -> 207.08 | G15: ='Data Sheet'!G90 -> 295.95 | H15: ='Data Sheet'!H90 -> 182.63 | I15: ='Data Sheet'!I90 -> 240.05 | ... K15: ='Data Sheet'!K90 -> 187.64 | L15: ='Data Sheet'!B8 -> 166.3 | M15: =M13*M14 -> 192.55439 | N15: =N13*N14 -> 127.65751
A17: RATIOS:
A18: Dividend Payout | B18: =IF('Data Sheet'!B30>0, 'Data Sheet'!B31/'Data Sheet'!B30, 0) -> 0.057234696 | C18: =IF('Data Sheet'!C30>0, 'Data Sheet'!C31/'Data Sheet'!C30, 0) -> 0.056530214 | D18: =IF('Data Sheet'!D30>0, 'Data Sheet'!D31/'Data Sheet'!D30, 0) -> 0.067016893 | E18: =IF('Data Sheet'!E30>0, 'Data Sheet'!E31/'Data Sheet'!E30, 0) -> 0.058766958 | F18: =IF('Data Sheet'!F30>0, 'Data Sheet'!F31/'Data Sheet'!F30, 0) -> 0.050748398 | G18: =IF('Data Sheet'!G30>0, 'Data Sheet'!G31/'Data Sheet'!G30, 0) -> 0.26895401 | H18: =IF('Data Sheet'!H30>0, 'Data Sheet'!H31/'Data Sheet'!H30, 0) -> 0.048352423 | I18: =IF('Data Sheet'!I30>0, 'Data Sheet'!I31/'Data Sheet'!I30, 0) -> 0.047305617 | ... K18: =IF('Data Sheet'!K30>0, 'Data Sheet'!K31/'Data Sheet'!K30, 0) -> 0.87421386
A19: OPM | B19: =IF(B6>0,B6/B4,0) -> 0.20417 | C19: =IF(C6>0,C6/C4,0) -> 0.19063411 | D19: =IF(D6>0,D6/D4,0) -> 0.1967607 | E19: =IF(E6>0,E6/E4,0) -> 0.2018774 | F19: =IF(F6>0,F6/F4,0) -> 0.23849881 | G19: =IF(G6>0,G6/G4,0) -> 0.21036161 | H19: =IF(H6>0,H6/H4,0) -> 0.1860918 | I19: =IF(I6>0,I6/I4,0) -> 0.18663596 | ... L19: =IF(L6>0,L6/L4,0) -> 0.19175722
G22: TRENDS: | H22: 10 YEARS | I22: 7 YEARS | J22: 5 YEARS | K22: 3 YEARS | L22: RECENT | M22: BEST | N22: WORST
G23: Sales Growth | H23: =IF(B4=0,"",POWER($K4/B4,1/9)-1) -> 0.058667036 | I23: =IF(D4=0,"",POWER($K4/D4,1/7)-1) -> 0.066502246 | J23: =IF(F4=0,"",POWER($K4/F4,1/5)-1) -> 0.083821141 | K23: =IF(H4=0,"",POWER($K4/H4, 1/3)-1) -> 0.0078088186 | L23: =IF(ISERROR(MAX(IF(J4=0,"",(K4-J4)/J4),IF(K4=0,"",(L4-K4)/K4))),"",MAX(IF(J4=0,"",(K4-J4)/J4),IF(K4=0,"",(L4-K4)/K4))) -> 0.039686424 | M23: =MAX(K23:L23) -> 0.039686424 | N23: =MIN(H23:L23) -> 0.0078088186
G24: OPM | H24: =IF(SUM(B4:$K$4)=0,"",SUMPRODUCT(B19:$K$19,B4:$K$4)/SUM(B4:$K$4)) -> 0.19983985 | I24: =IF(SUM(E4:$K$4)=0,"",SUMPRODUCT(E19:$K$19,E4:$K$4)/SUM(E4:$K$4)) -> 0.20062522 | J24: =IF(SUM(G4:$K$4)=0,"",SUMPRODUCT(G19:$K$19,G4:$K$4)/SUM(G4:$K$4)) -> 0.19513597 | K24: =IF(SUM(I4:$K$4)=0, "", SUMPRODUCT(I19:$K$19,I4:$K$4)/SUM(I4:$K$4)) -> 0.19370235 | L24: =L19 -> 0.19175722 | M24: =MAX(K24:L24) -> 0.19370235 | N24: =MIN(H24:L24) -> 0.19175722
G25: Price to Earning | H25: =IF(ISERROR(AVERAGEIF(B14:$L14,">0")),"",AVERAGEIF(B14:$L14,">0")) -> 17.768886 | I25: =IF(ISERROR(AVERAGEIF(E14:$L14,">0")),"",AVERAGEIF(E14:$L14,">0")) -> 18.465813 | J25: =IF(ISERROR(AVERAGEIF(G14:$L14,">0")),"",AVERAGEIF(G14:$L14,">0")) -> 19.191469 | K25: =IF(ISERROR(AVERAGEIF(I14:$L14,">0")),"",AVERAGEIF(I14:$L14,">0")) -> 17.738844 | L25: =L14 -> 12.423254 | M25: =MAX(K25:L25) -> 17.738844 | N25: =MIN(H25:L25) -> 12.423254

Sheet Quarters
A1: ='Profit & Loss'!A1 -> WIPRO LTD | E1: =UPDATE | J1: SCREENER.IN
A3: Narration | B3: ='Data Sheet'!B41 -> 45382 | C3: ='Data Sheet'!C41 -> 45473 | D3: ='Data Sheet'!D41 -> 45565 | E3: ='Data Sheet'!E41 -> 45657 | F3: ='Data Sheet'!F41 -> 45747 | G3: ='Data Sheet'!G41 -> 45838 | H3: ='Data Sheet'!H41 -> 45930 | I3: ='Data Sheet'!I41 -> 46022 | ... K3: ='Data Sheet'!K41 -> 46203
A4: Sales | B4: ='Data Sheet'!B42 -> 22208.3 | C4: ='Data Sheet'!C42 -> 21963.8 | D4: ='Data Sheet'!D42 -> 22301.6 | E4: ='Data Sheet'!E42 -> 22318.8 | F4: ='Data Sheet'!F42 -> 22504.2 | G4: ='Data Sheet'!G42 -> 22134.6 | H4: ='Data Sheet'!H42 -> 22697.3 | I4: ='Data Sheet'!I42 -> 23555.8 | ... K4: ='Data Sheet'!K42 -> 24478.6
A5: Expenses | B5: ='Data Sheet'!B43 -> 17827.7 | C5: ='Data Sheet'!C43 -> 17614.2 | D5: ='Data Sheet'!D43 -> 17798.3 | E5: ='Data Sheet'!E43 -> 17779 | F5: ='Data Sheet'!F43 -> 17880.2 | G5: ='Data Sheet'!G43 -> 17901.5 | H5: ='Data Sheet'!H43 -> 18324.9 | I5: ='Data Sheet'!I43 -> 19259.4 | ... K5: ='Data Sheet'!K43 -> 19845.9
A6: Operating Profit | B6: ='Data Sheet'!B50 -> 4380.6 | C6: ='Data Sheet'!C50 -> 4349.6 | D6: ='Data Sheet'!D50 -> 4503.3 | E6: ='Data Sheet'!E50 -> 4539.8 | F6: ='Data Sheet'!F50 -> 4624 | G6: ='Data Sheet'!G50 -> 4233.1 | H6: ='Data Sheet'!H50 -> 4372.4 | I6: ='Data Sheet'!I50 -> 4296.4 | ... K6: ='Data Sheet'!K50 -> 4632.7
A7: Other Income | B7: ='Data Sheet'!B44 -> 652.9 | C7: ='Data Sheet'!C44 -> 729.7 | D7: ='Data Sheet'!D44 -> 962.2 | E7: ='Data Sheet'!E44 -> 1004.6 | F7: ='Data Sheet'!F44 -> 1217.4 | G7: ='Data Sheet'!G44 -> 1071.5 | H7: ='Data Sheet'!H44 -> 962.9 | I7: ='Data Sheet'!I44 -> 1008.1 | ... K7: ='Data Sheet'!K44 -> 979
A8: Depreciation | B8: ='Data Sheet'!B45 -> 840.5 | C8: ='Data Sheet'!C45 -> 728.9 | D8: ='Data Sheet'!D45 -> 830.8 | E8: ='Data Sheet'!E45 -> 676.5 | F8: ='Data Sheet'!F45 -> 721.7 | G8: ='Data Sheet'!G45 -> 685.5 | H8: ='Data Sheet'!H45 -> 691.7 | I8: ='Data Sheet'!I45 -> 805 | ... K8: ='Data Sheet'!K45 -> 804.4
A9: Interest | B9: ='Data Sheet'!B46 -> 330.8 | C9: ='Data Sheet'!C46 -> 328.8 | D9: ='Data Sheet'!D46 -> 356.9 | E9: ='Data Sheet'!E46 -> 414.6 | F9: ='Data Sheet'!F46 -> 376.7 | G9: ='Data Sheet'!G46 -> 360.8 | H9: ='Data Sheet'!H46 -> 361.2 | I9: ='Data Sheet'!I46 -> 365.6 | ... K9: ='Data Sheet'!K46 -> 472.8
A10: Profit before tax | B10: ='Data Sheet'!B47 -> 3862.2 | C10: ='Data Sheet'!C47 -> 4021.6 | D10: ='Data Sheet'!D47 -> 4277.8 | E10: ='Data Sheet'!E47 -> 4453.3 | F10: ='Data Sheet'!F47 -> 4743 | G10: ='Data Sheet'!G47 -> 4258.3 | H10: ='Data Sheet'!H47 -> 4282.4 | I10: ='Data Sheet'!I47 -> 4133.9 | ... K10: ='Data Sheet'!K47 -> 4334.5
A11: Tax | B11: ='Data Sheet'!B48 -> 1004 | C11: ='Data Sheet'!C48 -> 985 | D11: ='Data Sheet'!D48 -> 1051.2 | E11: ='Data Sheet'!E48 -> 1086.6 | F11: ='Data Sheet'!F48 -> 1154.9 | G11: ='Data Sheet'!G48 -> 921.8 | H11: ='Data Sheet'!H48 -> 1020 | I11: ='Data Sheet'!I48 -> 988.9 | ... K11: ='Data Sheet'!K48 -> 978.2
A12: Net profit | B12: ='Data Sheet'!B49 -> 2834.6 | C12: ='Data Sheet'!C49 -> 3003.2 | D12: ='Data Sheet'!D49 -> 3208.8 | E12: ='Data Sheet'!E49 -> 3353.8 | F12: ='Data Sheet'!F49 -> 3569.6 | G12: ='Data Sheet'!G49 -> 3330.4 | H12: ='Data Sheet'!H49 -> 3246.2 | I12: ='Data Sheet'!I49 -> 3119 | ... K12: ='Data Sheet'!K49 -> 3352
A14: OPM | B14: =IF(B4>0,B6/B4,"") -> 0.19725058 | C14: =IF(C4>0,C6/C4,"") -> 0.19803495 | D14: =IF(D4>0,D6/D4,"") -> 0.20192722 | E14: =IF(E4>0,E6/E4,"") -> 0.20340699 | F14: =IF(F4>0,F6/F4,"") -> 0.20547276 | G14: =IF(G4>0,G6/G4,"") -> 0.19124357 | H14: =IF(H4>0,H6/H4,"") -> 0.19263965 | I14: =IF(I4>0,I6/I4,"") -> 0.18239245 | ... K14: =IF(K4>0,K6/K4,"") -> 0.1892551

Sheet Balance Sheet
A1: ='Profit & Loss'!A1 -> WIPRO LTD | E1: =UPDATE | J1: SCREENER.IN
A3: Narration | B3: ='Data Sheet'!B56 -> 42825 | C3: ='Data Sheet'!C56 -> 43190 | D3: ='Data Sheet'!D56 -> 43555 | E3: ='Data Sheet'!E56 -> 43921 | F3: ='Data Sheet'!F56 -> 44286 | G3: ='Data Sheet'!G56 -> 44651 | H3: ='Data Sheet'!H56 -> 45016 | I3: ='Data Sheet'!I56 -> 45382 | ... K3: ='Data Sheet'!K56 -> 46112
A4: Equity Share Capital | B4: ='Data Sheet'!B57 -> 486.1 | C4: ='Data Sheet'!C57 -> 904.8 | D4: ='Data Sheet'!D57 -> 1206.8 | E4: ='Data Sheet'!E57 -> 1142.7 | F4: ='Data Sheet'!F57 -> 1095.8 | G4: ='Data Sheet'!G57 -> 1096.4 | H4: ='Data Sheet'!H57 -> 1097.6 | I4: ='Data Sheet'!I57 -> 1045 | ... K4: ='Data Sheet'!K57 -> 2097.7
A5: Reserves | B5: ='Data Sheet'!B58 -> 51184.1 | C5: ='Data Sheet'!C58 -> 47021.5 | D5: ='Data Sheet'!D58 -> 55215.8 | E5: ='Data Sheet'!E58 -> 54179 | F5: ='Data Sheet'!F58 -> 53805.2 | G5: ='Data Sheet'!G58 -> 64306.6 | H5: ='Data Sheet'!H58 -> 76570.3 | I5: ='Data Sheet'!I58 -> 73488 | ... K5: ='Data Sheet'!K58 -> 85920.6
A6: Borrowings | B6: ='Data Sheet'!B59 -> 14241.2 | C6: ='Data Sheet'!C59 -> 13901.2 | D6: ='Data Sheet'!D59 -> 9946.7 | E6: ='Data Sheet'!E59 -> 9724 | F6: ='Data Sheet'!F59 -> 10451.4 | G6: ='Data Sheet'!G59 -> 17592.9 | H6: ='Data Sheet'!H59 -> 17466.6 | I6: ='Data Sheet'!I59 -> 16464.9 | ... K6: ='Data Sheet'!K59 -> 20291
A7: Other Liabilities | B7: ='Data Sheet'!B60 -> 12760.8 | C7: ='Data Sheet'!C60 -> 13563.3 | D7: ='Data Sheet'!D60 -> 16217.1 | E7: ='Data Sheet'!E60 -> 15953.9 | F7: ='Data Sheet'!F60 -> 17213.4 | G7: ='Data Sheet'!G60 -> 24279.7 | H7: ='Data Sheet'!H60 -> 21789.2 | I7: ='Data Sheet'!I60 -> 23611 | ... K7: ='Data Sheet'!K60 -> 32574.2
A8: Total | B8: ='Data Sheet'!B61 -> 78672.2 | C8: ='Data Sheet'!C61 -> 75390.8 | D8: ='Data Sheet'!D61 -> 82586.4 | E8: ='Data Sheet'!E61 -> 80999.6 | F8: ='Data Sheet'!F61 -> 82565.8 | G8: ='Data Sheet'!G61 -> 107275.6 | H8: ='Data Sheet'!H61 -> 116923.7 | I8: ='Data Sheet'!I61 -> 114608.9 | ... K8: ='Data Sheet'!K61 -> 140883.5
A10: Net Block | B10: ='Data Sheet'!B62 -> 19886.5 | C10: ='Data Sheet'!C62 -> 18126.7 | D10: ='Data Sheet'!D62 -> 17464.7 | E10: ='Data Sheet'!E62 -> 22062.1 | F10: ='Data Sheet'!F62 -> 23040.3 | G10: ='Data Sheet'!G62 -> 37989.6 | H10: ='Data Sheet'!H62 -> 44756.8 | I10: ='Data Sheet'!I62 -> 43628 | ... K10: ='Data Sheet'!K62 -> 51690.1
A11: Capital Work in Progress | B11: ='Data Sheet'!B63 -> 737.7 | C11: ='Data Sheet'!C63 -> 1377.7 | D11: ='Data Sheet'!D63 -> 2141.8 | E11: ='Data Sheet'!E63 -> 1881.1 | F11: ='Data Sheet'!F63 -> 1853.2 | G11: ='Data Sheet'!G63 -> 1601.5 | H11: ='Data Sheet'!H63 -> 617.1 | I11: ='Data Sheet'!I63 -> 723.4 | ... K11: ='Data Sheet'!K63 -> 412.2
A12: Investments | B12: ='Data Sheet'!B64 -> 29913.3 | C12: ='Data Sheet'!C64 -> 25796.8 | D12: ='Data Sheet'!D64 -> 22886.7 | E12: ='Data Sheet'!E64 -> 20032 | F12: ='Data Sheet'!F64 -> 18774.7 | G12: ='Data Sheet'!G64 -> 26153.8 | H12: ='Data Sheet'!H64 -> 33073.2 | I12: ='Data Sheet'!I64 -> 33384.4 | ... K12: ='Data Sheet'!K64 -> 46785.9
A13: Other Assets | B13: ='Data Sheet'!B65 -> 28134.7 | C13: ='Data Sheet'!C65 -> 30089.6 | D13: ='Data Sheet'!D65 -> 40093.2 | E13: ='Data Sheet'!E65 -> 37024.4 | F13: ='Data Sheet'!F65 -> 38897.6 | G13: ='Data Sheet'!G65 -> 41530.7 | H13: ='Data Sheet'!H65 -> 38476.6 | I13: ='Data Sheet'!I65 -> 36873.1 | ... K13: ='Data Sheet'!K65 -> 41995.3
A14: Total | B14: ='Data Sheet'!B66 -> 78672.2 | C14: ='Data Sheet'!C66 -> 75390.8 | D14: ='Data Sheet'!D66 -> 82586.4 | E14: ='Data Sheet'!E66 -> 80999.6 | F14: ='Data Sheet'!F66 -> 82565.8 | G14: ='Data Sheet'!G66 -> 107275.6 | H14: ='Data Sheet'!H66 -> 116923.7 | I14: ='Data Sheet'!I66 -> 114608.9 | ... K14: ='Data Sheet'!K66 -> 140883.5
A16: Working Capital | B16: =B13-B7 -> 15373.9 | C16: =C13-C7 -> 16526.3 | D16: =D13-D7 -> 23876.1 | E16: =E13-E7 -> 21070.5 | F16: =F13-F7 -> 21684.2 | G16: =G13-G7 -> 17251 | H16: =H13-H7 -> 16687.4 | I16: =I13-I7 -> 13262.1 | ... K16: =K13-K7 -> 9421.1
A17: Debtors | B17: ='Data Sheet'!B67 -> 9484.6 | C17: ='Data Sheet'!C67 -> 10099 | D17: ='Data Sheet'!D67 -> 10048.9 | E17: ='Data Sheet'!E67 -> 10447.4 | F17: ='Data Sheet'!F67 -> 9429.8 | G17: ='Data Sheet'!G67 -> 11521.9 | H17: ='Data Sheet'!H67 -> 12635 | I17: ='Data Sheet'!I67 -> 11547.7 | ... K17: ='Data Sheet'!K67 -> 13590.1
A18: Inventory | B18: ='Data Sheet'!B68 -> 391.5 | C18: ='Data Sheet'!C68 -> 337 | D18: ='Data Sheet'!D68 -> 395.1 | E18: ='Data Sheet'!E68 -> 186.5 | F18: ='Data Sheet'!F68 -> 106.4 | G18: ='Data Sheet'!G68 -> 133.4 | H18: ='Data Sheet'!H68 -> 118.8 | I18: ='Data Sheet'!I68 -> 90.7 | ... K18: ='Data Sheet'!K68 -> 51.7
A20: Debtor Days | B20: =IF('Profit & Loss'!B4>0,'Balance Sheet'!B17/('Profit & Loss'!B4/365),0) -> 62.434245 | C20: =IF('Profit & Loss'!C4>0,'Balance Sheet'!C17/('Profit & Loss'!C4/365),0) -> 67.651518 | D20: =IF('Profit & Loss'!D4>0,'Balance Sheet'!D17/('Profit & Loss'!D4/365),0) -> 62.147016 | E20: =IF('Profit & Loss'!E4>0,'Balance Sheet'!E17/('Profit & Loss'!E4/365),0) -> 62.372435 | F20: =IF('Profit & Loss'!F4>0,'Balance Sheet'!F17/('Profit & Loss'!F4/365),0) -> 55.572496 | G20: =IF('Profit & Loss'!G4>0,'Balance Sheet'!G17/('Profit & Loss'!G4/365),0) -> 53.024681 | H20: =IF('Profit & Loss'!H4>0,'Balance Sheet'!H17/('Profit & Loss'!H4/365),0) -> 50.965823 | I20: =IF('Profit & Loss'!I4>0,'Balance Sheet'!I17/('Profit & Loss'!I4/365),0) -> 46.957402 | ... K20: =IF('Profit & Loss'!K4>0,'Balance Sheet'!K17/('Profit & Loss'!K4/365),0) -> 53.554009
A21: Inventory Turnover | B21: =IF('Balance Sheet'!B18>0,'Profit & Loss'!B4/'Balance Sheet'!B18,0) -> 141.63065 | C21: =IF('Balance Sheet'!C18>0,'Profit & Loss'!C4/'Balance Sheet'!C18,0) -> 161.68279 | D21: =IF('Balance Sheet'!D18>0,'Profit & Loss'!D4/'Balance Sheet'!D18,0) -> 149.37712 | E21: =IF('Balance Sheet'!E18>0,'Profit & Loss'!E4/'Balance Sheet'!E18,0) -> 327.81555 | F21: =IF('Balance Sheet'!F18>0,'Profit & Loss'!F4/'Balance Sheet'!F18,0) -> 582.09492 | G21: =IF('Balance Sheet'!G18>0,'Profit & Loss'!G4/'Balance Sheet'!G18,0) -> 594.54273 | H21: =IF('Balance Sheet'!H18>0,'Profit & Loss'!H4/'Balance Sheet'!H18,0) -> 761.68013 | I21: =IF('Balance Sheet'!I18>0,'Profit & Loss'!I4/'Balance Sheet'!I18,0) -> 989.63947 | ... K21: =IF('Balance Sheet'!K18>0,'Profit & Loss'!K4/'Balance Sheet'!K18,0) -> 1791.5667
A23: Return on Equity | B23: =IF(SUM('Balance Sheet'!B4:B5)>0,'Profit & Loss'!B12/SUM('Balance Sheet'!B4:B5),"") -> 0.16437134 | C23: =IF(SUM('Balance Sheet'!C4:C5)>0,'Profit & Loss'!C12/SUM('Balance Sheet'!C4:C5),"") -> 0.16698139 | D23: =IF(SUM('Balance Sheet'!D4:D5)>0,'Profit & Loss'!D12/SUM('Balance Sheet'!D4:D5),"") -> 0.15957613 | E23: =IF(SUM('Balance Sheet'!E4:E5)>0,'Profit & Loss'!E12/SUM('Balance Sheet'!E4:E5),"") -> 0.17574116 | F23: =IF(SUM('Balance Sheet'!F4:F5)>0,'Profit & Loss'!F12/SUM('Balance Sheet'!F4:F5),"") -> 0.19665216 | G23: =IF(SUM('Balance Sheet'!G4:G5)>0,'Profit & Loss'!G12/SUM('Balance Sheet'!G4:G5),"") -> 0.18698836 | H23: =IF(SUM('Balance Sheet'!H4:H5)>0,'Profit & Loss'!H12/SUM('Balance Sheet'!H4:H5),"") -> 0.14613502 | I23: =IF(SUM('Balance Sheet'!I4:I5)>0,'Profit & Loss'!I12/SUM('Balance Sheet'!I4:I5),"") -> 0.14819208 | ... K23: =IF(SUM('Balance Sheet'!K4:K5)>0,'Profit & Loss'!K12/SUM('Balance Sheet'!K4:K5),"") -> 0.14993927
A24: Return on Capital Emp | C24: =IF((B4+B5+B6+C4+C5+C6)>0,('Profit & Loss'!C10+'Profit & Loss'!C9)*2/(B4+B5+B6+C4+C5+C6),"") -> 0.16948948 | D24: =IF((C4+C5+C6+D4+D5+D6)>0,('Profit & Loss'!D10+'Profit & Loss'!D9)*2/(C4+C5+C6+D4+D5+D6),"") -> 0.19157576 | E24: =IF((D4+D5+D6+E4+E5+E6)>0,('Profit & Loss'!E10+'Profit & Loss'!E9)*2/(D4+D5+D6+E4+E5+E6),"") -> 0.19761367 | F24: =IF((E4+E5+E6+F4+F5+F6)>0,('Profit & Loss'!F10+'Profit & Loss'!F9)*2/(E4+E5+E6+F4+F5+F6),"") -> 0.22104156 | G24: =IF((F4+F5+F6+G4+G5+G6)>0,('Profit & Loss'!G10+'Profit & Loss'!G9)*2/(F4+F5+F6+G4+G5+G6),"") -> 0.21130407 | H24: =IF((G4+G5+G6+H4+H5+H6)>0,('Profit & Loss'!H10+'Profit & Loss'!H9)*2/(G4+G5+G6+H4+H5+H6),"") -> 0.17709947 | I24: =IF((H4+H5+H6+I4+I5+I6)>0,('Profit & Loss'!I10+'Profit & Loss'!I9)*2/(H4+H5+H6+I4+I5+I6),"") -> 0.1716649 | J24: =IF((I4+I5+I6+J4+J5+J6)>0,('Profit & Loss'!J10+'Profit & Loss'!J9)*2/(I4+I5+I6+J4+J5+J6),"") -> 0.19705191 | K24: =IF((J4+J5+J6+K4+K5+K6)>0,('Profit & Loss'!K10+'Profit & Loss'!K9)*2/(J4+J5+J6+K4+K5+K6),"") -> 0.17915168

Sheet Cash Flow
A1: ='Balance Sheet'!A1 -> WIPRO LTD | E1: =UPDATE | J1: SCREENER.IN
A3: Narration | B3: ='Data Sheet'!B81 -> 42825 | C3: ='Data Sheet'!C81 -> 43190 | D3: ='Data Sheet'!D81 -> 43555 | E3: ='Data Sheet'!E81 -> 43921 | F3: ='Data Sheet'!F81 -> 44286 | G3: ='Data Sheet'!G81 -> 44651 | H3: ='Data Sheet'!H81 -> 45016 | I3: ='Data Sheet'!I81 -> 45382 | ... K3: ='Data Sheet'!K81 -> 46112
A4: Cash from Operating Activity | B4: ='Data Sheet'!B82 -> 9277.3 | C4: ='Data Sheet'!C82 -> 8423.3 | D4: ='Data Sheet'!D82 -> 11631.6 | E4: ='Data Sheet'!E82 -> 10064.3 | F4: ='Data Sheet'!F82 -> 14755 | G4: ='Data Sheet'!G82 -> 11079.7 | H4: ='Data Sheet'!H82 -> 13060.1 | I4: ='Data Sheet'!I82 -> 17621.6 | ... K4: ='Data Sheet'!K82 -> 14931.6
A5: Cash from Investing Activity | B5: ='Data Sheet'!B83 -> -11769.5 | C5: ='Data Sheet'!C83 -> 3595.3 | D5: ='Data Sheet'!D83 -> 5065.2 | E5: ='Data Sheet'!E83 -> 3593.4 | F5: ='Data Sheet'!F83 -> 684.9 | G5: ='Data Sheet'!G83 -> -22321.3 | H5: ='Data Sheet'!H83 -> -8169.2 | I5: ='Data Sheet'!I83 -> 1144.1 | ... K5: ='Data Sheet'!K83 -> -2447.5
A6: Cash from Financing Activity | B6: ='Data Sheet'!B84 -> -2275.2 | C6: ='Data Sheet'!C84 -> -12997.8 | D6: ='Data Sheet'!D84 -> -4936.9 | E6: ='Data Sheet'!E84 -> -15099.8 | F6: ='Data Sheet'!F84 -> -12884 | G6: ='Data Sheet'!G84 -> 4658.6 | H6: ='Data Sheet'!H84 -> -6088.1 | I6: ='Data Sheet'!I84 -> -18256.7 | ... K6: ='Data Sheet'!K84 -> -14126
A7: Net Cash Flow | B7: ='Data Sheet'!B85 -> -4767.4 | C7: ='Data Sheet'!C85 -> -979.2 | D7: ='Data Sheet'!D85 -> 11759.9 | E7: ='Data Sheet'!E85 -> -1442.1 | F7: ='Data Sheet'!F85 -> 2555.9 | G7: ='Data Sheet'!G85 -> -6583 | H7: ='Data Sheet'!H85 -> -1197.2 | I7: ='Data Sheet'!I85 -> 509 | ... K7: ='Data Sheet'!K85 -> -1641.9

Sheet Customization
A1: How to use it?
A3: You can customize this workbook as you want.
B4: You can add custom formating, add conditional formating, add your own formulas… do ANYTHING.
B5: Please don't edit the "Data Sheet" only.
A7: After customization, you can upload this back on Screener.
B8: Upload on: | C8: https://www.screener.in/excel/
A10: Download your customized workbooks now onwards.
B11: Now whenever you will "Export to excel" from Screener, it will export your customized file.
A14: TESTING:
B15: This is a testing feature currently.
B16: You can report any formula errors on the worksheet at: support@screener.in

Sheet WACC
C2: COST OF DEBT | J2: COST OF EQUITY
C4: PRE TAX COST OF DEBT | G4: =7.5% -> 0.075 | J4: RISK FREE RATE | N4: =6.75% -> 0.0675
C5: TAX RATE | G5: =25% -> 0.25 | J5: EQUITY RISK PREMIUM | N5: 0.073
C6: POST TAX COST OF DEBT | G6: =G4*(1-G5) -> 0.05625 | J6: LEVERED BETA 4 | N6: ='BETA '!K11 -> 0.93411266
J7: COST OF EQUITY | N7: =N4+(N6*N5) -> 0.13569022
C11: CAPITAL STRUCTURE | J11: LEVERED BETA
F13: CURRENT | G13: TARGET | J13: COMPS MEDIAN UNLEVERED BETA
C14: TOTAL DEBT | E14: =20291 -> 20291 | F14: =E14/E16 -> 0.109033 | G14: =0.078 -> 0.078 | J14: TARGET DEBT/EQUITY
C15: MARKET CAPITALIZATION | E15: =165808.62 -> 165808.62 | F15: =E15/E16 -> 0.890967 | G15: =1-G14 -> 0.922 | J15: TAX RATE
C16: TOTAL CAPITAL | E16: =SUM(E14:E15) -> 186099.62 | F16: =SUM(F14:F15) -> 1 | G16: =SUM(G14:G15) -> 1 | J16: LEVERED BETA
C19: DEBT/EQUITY | F19: =F14/F15 -> 0.12237603 | J19: WEIGHTED AVERAGE COST OF CAPITAL
L21: TOTAL COST | M21: TOTAL WEIGHT
J22: DEBT | L22: =G6 -> 0.05625 | M22: =G14 -> 0.078
J23: EQUITY | L23: =N7 -> 0.13569022 | M23: =G15 -> 0.922
J24: WEIGHTED AVERAGE COST OF CAPITAL | M24: =SUMPRODUCT(L22:L23,M22:M23) -> 0.12949389
